Workbook
Name adequacy: Metric_Codes!$C$45:$C$49
Name authority: Metric_Codes!$C$57:$C$60
Name confidence: Metric_Codes!$C$96:$C$98
Name decision: Metric_Codes!$C$69:$C$71
Name experience: Metric_Codes!$C$72:$C$76
Name ins_imp: #REF!
Name Insurance: Metric_Codes!$C$99:$C$103
Name Insurance_Role: Metric_Codes!$C$50:$C$52
Name Magnitude: Metric_Codes!$C$3:$C$7
Name participation: Metric_Codes!$C$66:$C$68
Name Preparedness: Metric_Codes!$C$61:$C$65
Name Primary: Metric_Codes!$C$50:$C$52
Name quality: Metric_Codes!$C$91:$C$95
Name Recovery_Insurance: Metric_Codes!$C$99:$C$103
Name resource_source: Metric_Codes!$C$34:$C$38
Name resource_speed: Metric_Codes!$C$39:$C$44
Name Scale: Metric_Codes!$C$8:$C$10
Name severity: Metric_Codes!$C$29:$C$33
Name speed: Metric_Codes!$C$82:$C$90

Sheet Data_030520
A1: CS ID | B1: Disaster Name | C1: Country | D1: ISO | E1: Disaster Type | F1: Disaster Subtype | G1: Type | H1: Year | I1: Magnitude | J1: Hazard Magnitude Normalised | K1: Locus | L1: Scale | M1: Population | N1: Economy Type | O1: Economy 2 | P1: Economic Freedom | Q1: Income Group | R1: Economic Growth cat | S1: GDP Growth | T1: GDP per Capita | U1: GNI per Capita | V1: IHDI Value | W1: Gini Coefficient | X1: Corrupt. Index | Y1: Non-Life Insurance Penetration | Z1: Damage Severity | AA1: Economic Loss | AB1: Fatalities | AC1: Displaced | AD1: Affected Population | AE1: Proportion Population Affected | AF1: Self vs external finance | AG1: Government aid | AH1: Non-Governmental aid | AI1: Insured loss | AJ1: Speed of funding | AK1: Adequacy funding | AL1: Role of Insurance | AM1: Resourcing - Confidence | AN1: State of Democracy | AO1: Disaster Management Authority | AP1: Preparedness | AQ1: Public Participation | AR1: Decision Making | AS1: Quality | AT1: Experience | AU1: Economy - Speed | AV1: EconomySpeed - Months | AW1: Economy - Quality | AX1: Economy - Quality Coded | AY1: Economy - Confidence | AZ1: Society - Speed | BA1: SocietySpeed - Months | BB1: Society - Amenity | BC1: Society - Amenity Coded | BD1: Society - Safety | BE1: Society - Safety Coded | BF1: Society total | BG1: Society - Confidence | BH1: Insurance Contribution to Recovery Outcome | BI1: Sources | BJ1: Comments
A2: 1 | B2: 2004 Bangladesh Floods | C2: Bangladesh | D2: BGD | E2: Flood | F2: Riverine Flood | G2: Climate | H2: 2004 | I2: 21,420 km2 | J2: Catastrophic damage | K2: NE & cntrl BGD | L2: Regional | M2: 141307489 | O2: Mixed | P2: 55.6 | Q2: Lower middle | R2: Growing | S2: 0.052395329 | T2: 460.758 | U2: 1650 | V2: 0.462 | W2: 32.4 | X2: 26 | Y2: 0.001588108 | Z2: 60-80% | AA2: 2200000 | AB2: 730 | AC2: 38000 | AD2: 36000000 | AE2: 0.25476357 | AF2: Mostly external | AG2: 60000000 | AH2: 209000000 | AJ2: >12 Months | AK2: Totally insufficient | AL2: Miniimal | AM2: High | AN2: Hybrid regime | AO2: Central gov. | AP2: Unprepared | AQ2: Inadequate | AR2: Limited scientific basis | AS2: Poor | AT2: Frequent | AU2: 6-11 Months | AV2: 9 | AW2: Worse | AX2: =VLOOKUP(AW2,Metric_Codes!$C$91:$D$95,2,FALSE) -> 2 | AY2: Medium | AZ2: 6-11 Months | BA2: 9 | BB2: Same | BC2: =VLOOKUP(BB2,Metric_Codes!$C$91:$D$95,2,FALSE) -> 3 | BD2: Improved | BE2: =VLOOKUP(BD2,Metric_Codes!$C$91:$D$95,2,FALSE) -> 4 | BF2: =(BC2+BE2)/2 -> 3.5 | BG2: Medium | BH2: Negligible | BI2: 96 | BJ2: The floods exacerbated the underlying problems of poverty, unemployment, food insecurity, fresh water supply, health and communication problems. The lack of development in the private insurance markets in Bangladesh has impeded speedy recovery of large industries after floods. Consequently, the central government is responsible for a major share of post-disaster the costs of immediate relief.
A3: 2 | B3: 2012 Hurricane Sandy | C3: United States | D3: USA | E3: Storm | F3: Extratropical Cyclone | G3: Climate | H3: 2012 | I3: CAT 3 | J3: Severe damage | K3: New York/New Jersey | L3: Regional | M3: 313993272 | N3: A: Service-Dominated Economy (more than 75% of economy based on services) | O3: Service-Oriented | P3: 76.8 | Q3: High | R3: Growing | S3: 0.022240309 | T3: 51450.959 | U3: 52850 | V3: 0.797 | W3: 41 | X3: 71 | Y3: 0.04345404 | Z3: 60-80% | AA3: 50000000 | AB3: 54 | AC3: 776000 | AD3: 8000000 | AE3: 0.025478253 | AF3: Mostly external | AG3: 51000000 | AI3: 22800000 | AJ3: >12 Months | AK3: Sufficient | AL3: Major | AM3: High | AN3: Full democracy | AO3: Specialised gov. agency | AP3: Somewhat prepared | AQ3: Adequate | AR3: Established scientific basis | AS3: Good | AT3: Frequent | AU3: <6 Months | AV3: 3 | AW3: Same | AX3: =VLOOKUP(AW3,Metric_Codes!$C$91:$D$95,2,FALSE) -> 3 | AY3: Medium | AZ3: 3-5 Years | BA3: 36 | BB3: Improved | BC3: =VLOOKUP(BB3,Metric_Codes!$C$91:$D$95,2,FALSE) -> 4 | BD3: Improved | BE3: =VLOOKUP(BD3,Metric_Codes!$C$91:$D$95,2,FALSE) -> 4 | BF3: =(BC3+BE3)/2 -> 4 | BG3: Medium | BH3: Crucial | BI3: 69 | BJ3: Sandy the US insurance industry’s second costliest natural disaster. High-value, commercial properties, public infrastructure, and business losses comprised a large proportion of the insured total, while the federal National Flood Insurance Program (NFIP)
A4: 3 | B4: 2005 Hurricane Katrina | C4: United States | D4: USA | E4: Storm | F4: Tropical Cyclone | G4: Climate | H4: 2005 | I4: CAT 5 | J4: Extremely catastrophic damage | K4: New Orleans | L4: Regional | M4: 295516599 | N4: A: Service-Dominated Economy (more than 75% of economy based on services) | O4: Service-Oriented | P4: 76.8 | Q4: High | R4: Growing | S4: 0.033452161 | T4: 44307.921 | U4: 44740 | V4: 0.797 | W4: 40.5 | X4: 71 | Y4: 0.04663638 | Z4: 60-80% | AA4: 125000000 | AB4: 1836 | AC4: 1500000 | AD4: 500000 | AE4: 0.0016919523 | AF4: Mostly external | AG4: 70000000 | AH4: 854000 | AI4: 60000000 | AJ4: >12 Months | AK4: Insufficient | AL4: Major | AM4: High | AN4: Full democracy | AO4: Specialised gov. agency | AP4: Unprepared | AQ4: Inadequate | AR4: Established scientific basis | AS4: Poor | AT4: Frequent | AU4: 3-5 Years | AV4: 48 | AW4: Worse | AX4: =VLOOKUP(AW4,Metric_Codes!$C$91:$D$95,2,FALSE) -> 2 | AY4: Medium | AZ4: 3-5 Years | BA4: 60 | BB4: Worse | BC4: =VLOOKUP(BB4,Metric_Codes!$C$91:$D$95,2,FALSE) -> 2 | BD4: Improved | BE4: =VLOOKUP(BD4,Metric_Codes!$C$91:$D$95,2,FALSE) -> 4 | BF4: =(BC4+BE4)/2 -> 3 | BG4: Medium | BH4: Important | BI4: 22 | BJ4: The hurricane trio had a wide-range of effects on the energy sector, housing, infrastructure, construction and, travel and tourism sectors in the Gulf states of the USA. The storms revealed several fundamental flaws in the management of hurricanes characterized by inept disaster response and inefficiencies in administration of aid after Katrina.
A5: 4 | B5: 2014 India(-Pakistan) floods | C5: India | D5: IND | E5: Flood | F5: Riverine Flood | G5: Climate | H5: 2014 | I5: CAT 4 | J5: Catastrophic damage | K5: Jammu & Kashmir | L5: Regional | M5: 1293859290 | N5: C: Service with Industry (service 50-67% and Industry >25%) | O5: Service-Oriented | P5: 55.2 | Q5: Lower middle | R5: Growing | S5: 0.074102276 | T5: 1574.004 | U5: 5610 | V5: 0.468 | W5: 35.1 | X5: 41 | Y5: 0.006868531 | Z5: 60-80% | AA5: 7000000 | AB5: 53 | AC5: 1300000 | AD5: 920000 | AE5: 0.00071105104 | AF5: Mostly self-funded | AI5: 530000 | AJ5: <6 Months | AK5: Insufficient | AL5: Miniimal | AM5: High | AN5: Full democracy | AO5: Central gov. | AP5: Unprepared | AQ5: Inadequate | AR5: Limited scientific basis | AS5: Mediocre | AT5: Frequent | AU5: <6 Months | AV5: 3 | AW5: Worse | AX5: =VLOOKUP(AW5,Metric_Codes!$C$91:$D$95,2,FALSE) -> 2 | AY5: Medium | AZ5: 6-11 Months | BA5: 9 | BB5: Same | BC5: =VLOOKUP(BB5,Metric_Codes!$C$91:$D$95,2,FALSE) -> 3 | BD5: Same | BE5: =VLOOKUP(BD5,Metric_Codes!$C$91:$D$95,2,FALSE) -> 3 | BF5: =(BC5+BE5)/2 -> 3 | BG5: Medium | BH5: Negligible | BI5: 66 | BJ5: Lack of flood prevention measures, early-warning systems and weak recovery planning processes were cited as chief reasons for the disaster impacts. Agriculture and tourism were the worst affected sectors and this had a significant impact on the regional economy. The floods also exposed political fragilities including the failure of the state to provide timely relief.
A6: 5 | B6: 2013 Typhoon Haiyan (Yolanda) | C6: Philippines | D6: PHL | E6: Storm | F6: Tropical Cyclone | G6: Climate | H6: 2013 | I6: CAT 5 | J6: Extremely catastrophic damage | K6: Eastern Visayas: Tacloban City | L6: Regional | M6: 98481032 | N6: C: Service with Industry (service 50-67% and Industry >25%) | O6: Service-Oriented | P6: 63.8 | Q6: Lower middle | R6: Growing | S6: 0.070640243 | T6: 2760.289 | U6: 7930 | V6: 0.574 | W6: 40.1 | X6: 36 | Y6: 0.004640428 | Z6: 60-80% | AA6: 10000000 | AB6: 7354 | AC6: 4000000 | AD6: 16106870 | AE6: 0.16355302 | AF6: Mostly self-funded | AG6: 2100000 | AH6: 865000 | AI6: 700000 | AJ6: <12 Months | AK6: Sufficient | AL6: Moderate | AM6: High | AN6: Flawed democracy | AO6: Specially-formed agency | AP6: Somewhat prepared | AQ6: Adequate | AR6: Limited scientific basis | AS6: Mediocre | AT6: Frequent | AU6: 1-2 Years | AV6: 18 | AW6: Same | AX6: =VLOOKUP(AW6,Metric_Codes!$C$91:$D$95,2,FALSE) -> 3 | AY6: High | AZ6: 3-5 Years | BA6: 36 | BB6: Improved | BC6: =VLOOKUP(BB6,Metric_Codes!$C$91:$D$95,2,FALSE) -> 4 | BD6: Same | BE6: =VLOOKUP(BD6,Metric_Codes!$C$91:$D$95,2,FALSE) -> 3 | BF6: =(BC6+BE6)/2 -> 3.5 | BG6: High | BH6: Small | BI6: 56 | BJ6: Recovery complicated by Bohol earthquake 3 weeks earlier; Survey of 30 experts;
A7: 6 | B7: 2017 Typhoon Damrey (Ramil) | C7: Vietnam | D7: VNM | E7: Storm | F7: Tropical Cyclone | G7: Climate | H7: 2017 | I7: CAT 2 | J7: Moderate damage | K7: Khanh Hoa Province | L7: Regional | M7: 95540800 | N7: F: Industry with Service (Industry and Service both 33-50%) | O7: Industry with Service | P7: 55.3 | Q7: Lower middle | R7: Growing | S7: 0.068122457 | T7: 2343.125 | U7: 6450 | V7: 0.574 | W7: 34.8 | X7: 33 | Y7: 0.008 | Z7: 20-40% | AA7: 1000000 | AB7: 123 | AC7: 36000 | AD7: 4330000 | AE7: 0.045320952 | AF7: Mostly self-funded | AG7: 13000000 | AJ7: <6 Months | AK7: Insufficient | AL7: Miniimal | AM7: High | AN7: Authoritarian | AO7: Central gov. | AP7: Well prepared | AQ7: Adequate | AR7: Established scientific basis | AS7: Good | AT7: Frequent | AU7: 1-2 Years | AV7: 18 | AW7: Same | AX7: =VLOOKUP(AW7,Metric_Codes!$C$91:$D$95,2,FALSE) -> 3 | AY7: High | AZ7: <6 Months | BA7: 3 | BB7: Same | BC7: =VLOOKUP(BB7,Metric_Codes!$C$91:$D$95,2,FALSE) -> 3 | BD7: Improved | BE7: =VLOOKUP(BD7,Metric_Codes!$C$91:$D$95,2,FALSE) -> 4 | BF7: =(BC7+BE7)/2 -> 3.5 | BG7: High | BH7: Negligible | BI7: 71 | BJ7: Govt grants for poorest based on level of damage; Agriculture and fisheries hit hardest and little Govt aid or incentives to recover; Country experiencing rapid economic growth
A8: 7 | B8: 2013 European floods (Germany) | C8: Germany | D8: DEU | E8: Flood | F8: Riverine Flood | G8: Climate | H8: 2013 | I8: Force 12 | J8: Severe damage | K8: N. Germany (Hamburg) | L8: National | M8: 80645605 | N8: B: Service-Oriented Economy (67-75% of economy based on services) | O8: Mixed | P8: 73.5 | Q8: High | R8: Stable | S8: 0.0048958448 | T8: 47262.283 | U8: 46250 | V8: 0.861 | W8: 31.7 | X8: 80 | Y8: 0.03465669 | Z8: 0-20% | AA8: 12900000 | AB8: 4 | AD8: 1000000 | AE8: 0.012399932 | AF8: Mostly external | AG8: 8000000 | AH8: 0 | AI8: 700000 | AJ8: <12 Months | AK8: Sufficient | AL8: Major | AM8: High | AN8: Full democracy | AO8: Specialised gov. agency | AP8: Well prepared | AQ8: Adequate | AR8: Established scientific basis | AS8: Very good | AT8: Occasional | AU8: <6 Months | AV8: 3 | AW8: Same | AX8: =VLOOKUP(AW8,Metric_Codes!$C$91:$D$95,2,FALSE) -> 3 | AY8: High | AZ8: <1 Month | BA8: 1 | BB8: Same | BC8: =VLOOKUP(BB8,Metric_Codes!$C$91:$D$95,2,FALSE) -> 3 | BD8: Improved | BE8: =VLOOKUP(BD8,Metric_Codes!$C$91:$D$95,2,FALSE) -> 4 | BF8: =(BC8+BE8)/2 -> 3.5 | BG8: High | BH8: Important | BI8: 39 | BJ8: Previous major floods in 2002 and improvements in flood protection and management meant damage less in some places; significant changes in policy since and moves to private insurance rather than State as main funder
A9: 8 | B9: 2007 UK floods | C9: United Kingdom | D9: GBR | E9: Flood | F9: Riverine Flood | G9: Climate | H9: 2007 | I9: Force 13 | J9: Severe damage | K9: S & cntrl British Isles | L9: National | M9: 61322463 | N9: A: Service-Dominated Economy (more than 75% of economy based on services) | O9: Service-Oriented | P9: 78.9 | Q9: High | R9: Growing | S9: 0.023567082 | T9: 50134.316 | U9: 35540 | V9: 0.835 | W9: 33.2 | X9: 80 | Y9: 0.02840852 | Z9: 0-20% | AA9: 4000000 | AB9: 13 | AC9: 30000 | AD9: 1000000 | AE9: 0.016307238 | AF9: Mostly external | AH9: 0 | AI9: 670000 | AJ9: <12 Months | AK9: Sufficient | AL9: Major | AM9: High | AN9: Full democracy | AO9: Specialised gov. agency | AP9: Well prepared | AQ9: Adequate | AR9: Established scientific basis | AS9: Very good | AT9: Occasional | AU9: 6-11 Months | AV9: 9 | AW9: Same | AX9: =VLOOKUP(AW9,Metric_Codes!$C$91:$D$95,2,FALSE) -> 3 | AY9: High | AZ9: 1-2 Years | BA9: 12 | BB9: Same | BC9: =VLOOKUP(BB9,Metric_Codes!$C$91:$D$95,2,FALSE) -> 3 | BD9: Improved | BE9: =VLOOKUP(BD9,Metric_Codes!$C$91:$D$95,2,FALSE) -> 4 | BF9: =(BC9+BE9)/2 -> 3.5 | BG9: High | BH9: Crucial | BI9: 92 | BJ9: Kick started major reviews by Pitt and Bonfield plus significant investment in flood protection and changes in policy; private insurance funded household and business recovery
A10: 9 | B10: 2004 Typhoon Tokage (Siony) | C10: Japan | D10: JPN | E10: Storm | F10: Tropical Cyclone | G10: Climate | H10: 2004 | I10: CAT 4 | J10: Catastrophic damage | K10: Kyushu Island | L10: Regional | M10: 127761000 | N10: B: Service-Oriented Economy (67-75% of economy based on services) | O10: Service-Oriented | P10: 72.1 | Q10: High | R10: Growing | S10: 0.022046879 | T10: 37688.722 | U10: 30930 | V10: 0.876 | W10: 32.1 | X10: 73 | Y10: 0.02224048 | Z10: 20-40% | AA10: 2300000 | AB10: 89 | AC10: 21000 | AD10: 84792 | AE10: 0.00066367671 | AF10: Mostly external | AI10: 1100000 | AJ10: <12 Months | AK10: Sufficient | AL10: Moderate | AM10: Medium | AN10: Full democracy | AO10: Specialised gov. agency | AP10: Well prepared | AQ10: Adequate | AR10: Established scientific basis | AS10: Very good | AT10: Frequent | AU10: <6 Months | AV10: 3 | AW10: Same | AX10: =VLOOKUP(AW10,Metric_Codes!$C$91:$D$95,2,FALSE) -> 3 | AY10: Low | AZ10: 1-2 Years | BA10: 12 | BB10: Same | BC10: =VLOOKUP(BB10,Metric_Codes!$C$91:$D$95,2,FALSE) -> 3 | BD10: Same | BE10: =VLOOKUP(BD10,Metric_Codes!$C$91:$D$95,2,FALSE) -> 3 | BF10: =(BC10+BE10)/2 -> 3 | BG10: Low | BH10: Small | BI10: 1 | BJ10: Affected entire S part of Japan; 1 of 5 major typhoons in 2004 causing widesread flooding
A11: 10 | B11: 2010 China Floods | C11: China | D11: CHN | E11: Flood | F11: Riverine Flood | G11: Climate | H11: 2010 | I11: Flood 4 | J11: Catastrophic damage | K11: 28 mainland Provinces | L11: National | M11: 1337705000 | N11: C: Service with Industry (service 50-67% and Industry >25%) | O11: Mixed | P11: 67.3 | Q11: Upper middle | R11: Growing | S11: 0.1063614 | T11: 4560.513 | U11: 9290 | V11: 0.643 | W11: 42.2 | X11: 39 | Y11: 0.01192495 | Z11: 60-80% | AA11: 18171000 | AB11: 1691 | AC11: 15200000 | AD11: 134000000 | AE11: 0.10017156 | AF11: Mostly self-funded | AI11: 596000 | AJ11: <12 Months | AK11: Insufficient | AL11: Miniimal | AM11: High | AN11: Authoritarian | AO11: Central gov. | AP11: Somewhat prepared | AQ11: Inadequate | AR11: Established scientific basis | AS11: Good | AT11: Major | AU11: 1-2 Years | AV11: 18 | AW11: Same | AX11: =VLOOKUP(AW11,Metric_Codes!$C$91:$D$95,2,FALSE) -> 3 | AY11: Low | AZ11: 1-2 Years | BA11: 18 | BB11: Same | BC11: =VLOOKUP(BB11,Metric_Codes!$C$91:$D$95,2,FALSE) -> 3 | BD11: Improved | BE11: =VLOOKUP(BD11,Metric_Codes!$C$91:$D$95,2,FALSE) -> 4 | BF11: =(BC11+BE11)/2 -> 3.5 | BG11: Low | BH11: Negligible | BI11: 5 | BJ11: Severe monsoon season; environmental concerns about over development along Yangtze; most caualties from mudslides; little impact on agricultual production
A12: 11 | B12: 1998 Hurricane Mitch | C12: Honduras | D12: HND | E12: Storm | F12: Tropical Cyclone | G12: Climate | H12: 1998 | I12: CAT 5 | J12: Extremely catastrophic damage | K12: Nationwide | L12: National | M12: 6192026 | N12: D: Service with Industrial/Ag Mix (Service >50%, Industry 15-25% and Ag 15-30%) | O12: Mixed | P12: 60.2 | Q12: Lower middle | R12: Growing | S12: 0.036 | T12: 1028.2 | U12: 2430 | V12: 0.459 | W12: 50.5 | X12: 29 | Y12: 0.006 | Z12: 80-100% | AA12: 3800000 | AB12: 22658 | AC12: 441150 | AD12: 868228 | AE12: 0.14021711 | AF12: Mostly external | AH12: 2800000 | AI12: 150000 | AJ12: >12 Months | AK12: Insufficient | AL12: Moderate | AM12: High | AN12: Hybrid regime | AO12: Central gov. | AP12: Completely unprepared | AQ12: Inadequate | AR12: Limited scientific basis | AS12: Poor | AT12: Frequent | AU12: 3-5 Years | AV12: 48 | AW12: Much worse | AX12: =VLOOKUP(AW12,Metric_Codes!$C$91:$D$95,2,FALSE) -> 1 | AY12: Medium | AZ12: 3-5 Years | BA12: 60 | BB12: Same | BC12: =VLOOKUP(BB12,Metric_Codes!$C$91:$D$95,2,FALSE) -> 3 | BD12: Same | BE12: =VLOOKUP(BD12,Metric_Codes!$C$91:$D$95,2,FALSE) -> 3 | BF12: =(BC12+BE12)/2 -> 3 | BG12: Medium | BH12: Small | BI12: 10 | BJ12: Huge rainfall and flooding, deforestation;direct and indirect losses 70% GDP; 70% agriculture destroyed; prompted debate about morality of international debt
A13: 12 | B13: 2004 Hurricane Frances | C13: Bahamas, The | D13: BHS | E13: Storm | F13: Tropical Cyclone | G13: Climate | H13: 2004 | I13: CAT 4 | J13: Catastrophic damage | K13: All islands | L13: National | M13: 322526 | O13: Industry-Oriented | P13: 62.9 | Q13: High | R13: Stable | S13: 0.0088283993 | T13: 28076.155 | U13: 21380 | V13: 0.755 | W13: 46 | X13: 65 | Y13: 0.03588563 | Z13: 20-40% | AA13: 1000000 | AB13: 2 | AC13: 2500 | AD13: 8000 | AE13: 0.024804202 | AF13: Mostly self-funded | AI13: 230000 | AJ13: >12 Months | AK13: Insufficient | AL13: Moderate | AM13: High | AN13: Flawed democracy | AO13: Central gov. | AP13: Unprepared | AQ13: Inadequate | AR13: Limited scientific basis | AS13: Poor | AT13: Occasional | AU13: 6-11 Months | AV13: 9 | AW13: Same | AX13: =VLOOKUP(AW13,Metric_Codes!$C$91:$D$95,2,FALSE) -> 3 | AY13: Low | AZ13: 1-2 Years | BA13: 18 | BB13: Same | BC13: =VLOOKUP(BB13,Metric_Codes!$C$91:$D$95,2,FALSE) -> 3 | BD13: Same | BE13: =VLOOKUP(BD13,Metric_Codes!$C$91:$D$95,2,FALSE) -> 3 | BF13: =(BC13+BE13)/2 -> 3 | BG13: Low | BH13: Small | BI13: 12 | BJ13: Also hit Florida and USA where it caused most economic damage (US 9 billion) and fatalities;
A14: 13 | B14: 2004 Hurricane Ivan | C14: Jamaica | D14: JAM | E14: Storm | F14: Tropical Cyclone | G14: Climate | H14: 2004 | I14: CAT 5 | J14: Extremely catastrophic damage | K14: Nationwide | L14: National | M14: 2728777 | O14: Service-Oriented | P14: 68.6 | Q14: Upper middle | R14: Stable | S14: 0.013237251 | T14: 3719.974 | U14: 6820 | V14: 0.608 | W14: 45.5 | X14: 44 | Y14: 0.0302802 | Z14: 60-80% | AA14: 595000 | AB14: 15 | AC14: 18000 | AD14: 350000 | AE14: 0.12826259 | AF14: Mostly self-funded | AH14: 40000 | AI14: 200000 | AJ14: >12 Months | AK14: Insufficient | AL14: Moderate | AM14: High | AN14: Flawed democracy | AO14: Specialised gov. agency | AP14: Somewhat prepared | AQ14: Inadequate | AR14: No scientific basis | AS14: Poor | AT14: Frequent | AU14: 6-11 Months | AV14: 9 | AW14: Same | AX14: =VLOOKUP(AW14,Metric_Codes!$C$91:$D$95,2,FALSE) -> 3 | AY14: Medium | AZ14: 1-2 Years | BA14: 18 | BB14: Same | BC14: =VLOOKUP(BB14,Metric_Codes!$C$91:$D$95,2,FALSE) -> 3 | BD14: Same | BE14: =VLOOKUP(BD14,Metric_Codes!$C$91:$D$95,2,FALSE) -> 3 | BF14: =(BC14+BE14)/2 -> 3 | BG14: Medium | BH14: Small | BI14: 44 | BJ14: Creation of Office of National Reconstruction (ONR) outside the legally established agencies unhelpful; Parish Disaster Committees, were expected to have, but lacked, the capacity for assessment and response; big hit for agricultural production
A15: 14 | B15: 1994 Northridge earthquake | C15: United States | D15: USA | E15: Earthquake | F15: Earthquake & Tsunami | G15: Geophysical | H15: 1994 | I15: 6.7 Mw | J15: Severe damage | K15: Northridge | L15: Regional | M15: 263126000 | N15: A: Service-Dominated Economy (more than 75% of economy based on services) | O15: Service-Oriented | P15: 76.8 | Q15: High | R15: Growing | S15: 0.04 | T15: 27776.6 | U15: 52308 | V15: 0.755 | W15: 41 | X15: 71 | Y15: 0.04813937 | Z15: 60-80% | AA15: 30000000 | AB15: 72 | AC15: 114000 | AD15: 3800000 | AE15: 0.01444175 | AF15: Mostly external | AG15: 8600000 | AI15: 13900000 | AJ15: <12 Months | AK15: Sufficient | AL15: Major | AM15: High | AN15: Full democracy | AO15: Central gov. | AP15: Somewhat prepared | AQ15: Adequate | AR15: Established scientific basis | AS15: Good | AT15: Infrequent | AU15: 1-2 Years | AV15: 18 | AW15: Same | AX15: =VLOOKUP(AW15,Metric_Codes!$C$91:$D$95,2,FALSE) -> 3 | AY15: High | AZ15: 1-2 Years | BA15: 18 | BB15: Same | BC15: =VLOOKUP(BB15,Metric_Codes!$C$91:$D$95,2,FALSE) -> 3 | BD15: Same | BE15: =VLOOKUP(BD15,Metric_Codes!$C$91:$D$95,2,FALSE) -> 3 | BF15: =(BC15+BE15)/2 -> 3 | BG15: High | BH15: Important | BI15: 37 | BJ15: Private household insurnace reduced recovery time by 1 year over familes recieving governments grants
A16: 15 | B16: 2003 Bam earthquake | C16: Iran, Islamic Rep. | D16: IRN | E16: Earthquake | F16: Earthquake | G16: Geophysical | H16: 2003 | I16: 6.6 Mw | J16: Severe damage | K16: Bam | L16: Regional | M16: 68812713 | N16: F: Industry with Service (Industry and Service both 33-50%) | O16: Mixed | P16: 51.1 | Q16: Upper middle | R16: Growing | S16: 0.07 | T16: 2231.3 | U16: 13451 | V16: 0.498 | W16: 38 | X16: 28 | Y16: 0.009347397 | Z16: 80-100% | AA16: 500000 | AB16: 30000 | AC16: 75600 | AD16: 100000 | AE16: 0.0014532198 | AF16: Self-funded | AG16: 410000 | AJ16: >24 Months | AK16: Totally insufficient | AL16: Miniimal | AM16: High | AN16: Authoritarian | AO16: Central gov. | AP16: Unprepared | AQ16: Inadequate | AR16: Limited scientific basis | AS16: Very poor | AT16: Frequent | AU16: 11-20 Years | AV16: 180 | AW16: Much worse | AX16: =VLOOKUP(AW16,Metric_Codes!$C$91:$D$95,2,FALSE) -> 1 | AY16: Medium | AZ16: 6-10 Years | BA16: 120 | BB16: Worse | BC16: =VLOOKUP(BB16,Metric_Codes!$C$91:$D$95,2,FALSE) -> 2 | BD16: Improved | BE16: =VLOOKUP(BD16,Metric_Codes!$C$91:$D$95,2,FALSE) -> 4 | BF16: =(BC16+BE16)/2 -> 3 | BG16: High | BH16: Negligible | BI16: 86 | BJ16: Collapse of adobe structures caused high casualties; dates producing area; never fully recovered; many housing plots still vacant because owners
A17: 16 | B17: 2004 Indian Ocean earthquake and tsunami | C17: Thailand | D17: THA | E17: Earthquake & Tsunami | F17: Earthquake | G17: Geophysical | H17: 2004 | I17: 9.1 Mw | J17: Extremely catastrophic damage | K17: Indian Ocean | L17: Regional | M17: 65002231 | N17: C: Service with Industry (service 50-67% and Industry >25%) | O17: Industry with Service | P17: 68.3 | Q17: Upper middle | R17: Growing | S17: 0.06 | T17: 2659.8 | U17: 13364 | V17: 0.573 | W17: 39 | X17: 36 | Y17: 0.01253271 | Z17: 80-100% | AA17: 30000000 | AB17: 9311 | AC17: 1800000 | AD17: 2133784 | AE17: 0.032826319 | AF17: Equal | AG17: 1700000 | AI17: 2700000 | AJ17: <12 Months | AK17: Surplus | AL17: Miniimal | AM17: Medium | AN17: Hybrid regime | AO17: Central gov. | AP17: Unprepared | AQ17: Inadequate | AR17: Limited scientific basis | AS17: Poor | AT17: Infrequent | AU17: 3-5 Years | AV17: 36 | AW17: Improved | AX17: =VLOOKUP(AW17,Metric_Codes!$C$91:$D$95,2,FALSE) -> 4 | AY17: High | AZ17: 3-5 Years | BA17: 36 | BB17: Worse | BC17: =VLOOKUP(BB17,Metric_Codes!$C$91:$D$95,2,FALSE) -> 2 | BD17: Same | BE17: =VLOOKUP(BD17,Metric_Codes!$C$91:$D$95,2,FALSE) -> 3 | BF17: =(BC17+BE17)/2 -> 2.5 | BG17: High | BH17: Negligible | BI17: 7 | BJ17: Huge disaster; Massive international aid slowed recovery in some places like Thailand; influx of new people kick started economy
A18: 17 | B18: 2005 Kashmir earthquake | C18: Pakistan | D18: PAK | E18: Earthquake | F18: Earthquake | G18: Geophysical | H18: 2005 | I18: 7.6 Mw | J18: Catastrophic damage | K18: Kashmir NW Frontier | L18: Regional | M18: 153909667 | N18: C: Service with Industry (service 50-67% and Industry >25%) | O18: Industry with Service | P18: 61 | Q18: Lower middle | R18: Growing | S18: 0.09 | T18: 711.5 | U18: 4652 | V18: 0.375 | W18: 30 | X18: 33 | Y18: 0.003924284 | Z18: 60-80% | AA18: 5200000 | AB18: 87000 | AC18: 3200000 | AD18: 10143700 | AE18: 0.065906841 | AF18: Mostly self-funded | AG18: 483000 | AI18: 5000 | AJ18: >12 Months | AK18: Insufficient | AL18: Miniimal | AM18: High | AN18: Hybrid regime | AO18: Specially-formed agency | AP18: Unprepared | AQ18: Inadequate | AR18: No scientific basis | AS18: Poor | AT18: Frequent | AU18: 3-5 Years | AV18: 48 | AW18: Worse | AX18: =VLOOKUP(AW18,Metric_Codes!$C$91:$D$95,2,FALSE) -> 2 | AY18: Medium | AZ18: 6-10 Years | BA18: 96 | BB18: Worse | BC18: =VLOOKUP(BB18,Metric_Codes!$C$91:$D$95,2,FALSE) -> 2 | BD18: Same | BE18: =VLOOKUP(BD18,Metric_Codes!$C$91:$D$95,2,FALSE) -> 3 | BF18: =(BC18+BE18)/2 -> 2.5 | BG18: High | BH18: Negligible | BI18: 375 | BJ18: High death toll, especially of school childre, caused by poor construction; army suffered high casualities which affected command and control in a military state; complicated by Kashmir conflict; plans for relocate Balakot thwarted; Speciall agency EERA; hopes of building back better unrealised
A19: 18 | B19: 2008 Sichuan (Wenchuan) earthquake | C19: China | D19: CHN | E19: Earthquake | F19: Earthquake & Tsunami | G19: Geophysical | H19: 2008 | I19: 7.9 Mw | J19: Catastrophic damage | K19: Wenchuan | L19: Regional | M19: 1324655000 | N19: C: Service with Industry (service 50-67% and Industry >25%) | O19: Mixed | P19: 67.3 | Q19: Upper middle | R19: Growing | S19: 0.1 | T19: 3471.2 | U19: 11477 | V19: 0.643 | W19: 37 | X19: 39 | Y19: 0.009855344 | Z19: 60-80% | AA19: 130000000 | AB19: 87587 | AC19: 5000000 | AD19: 15000000 | AE19: 0.011323703 | AF19: Mostly external | AG19: 10000000 | AI19: 366000 | AJ19: <6 Months | AK19: Sufficient | AL19: Miniimal | AM19: High | AN19: Authoritarian | AO19: Central gov. | AP19: Unprepared | AQ19: Inadequate | AR19: Limited scientific basis | AS19: Poor | AT19: Frequent | AU19: 1-2 Years | AV19: 18 | AW19: Improved | AX19: =VLOOKUP(AW19,Metric_Codes!$C$91:$D$95,2,FALSE) -> 4 | AY19: Medium | AZ19: 1-2 Years | BA19: 12 | BB19: Worse | BC19: =VLOOKUP(BB19,Metric_Codes!$C$91:$D$95,2,FALSE) -> 2 | BD19: Improved | BE19: =VLOOKUP(BD19,Metric_Codes!$C$91:$D$95,2,FALSE) -> 4 | BF19: =(BC19+BE19)/2 -> 3 | BG19: High | BH19: Negligible | BI19: 36 | BJ19: Rapid recovery;massive aid effort from unaffected cities in south; issues that rapid rebuilding insensitive to special environmental and cultural character of region;
A20: 19 | B20: 2009 L'Aquila earthquake | C20: Italy | D20: ITA | E20: Earthquake | F20: Earthquake | G20: Geophysical | H20: 2009 | I20: 6.2 Mw | J20: Severe damage | K20: L'Aquila | L20: Regional | M20: 59095365 | N20: A: Service-Dominated Economy (more than 75% of economy based on services) | O20: Industry-Oriented | P20: 62.2 | Q20: High | R20: Contracting | S20: -0.06 | T20: 36976.8 | U20: 32669 | V20: 0.768 | W20: 35 | X20: 52 | Y20: 0.02396951 | Z20: 60-80% | AA20: 11600000 | AB20: 308 | AC20: 65000 | AD20: 72000 | AE20: 0.0012183697 | AF20: Equal | AG20: 484000 | AI20: 200000 | AJ20: >12 Months | AK20: Insufficient | AL20: Moderate | AM20: High | AN20: Flawed democracy | AO20: Central gov. | AP20: Somewhat prepared | AQ20: Inadequate | AR20: No scientific basis | AS20: Very poor | AT20: Frequent | AU20: 6-10 Years | AV20: 96 | AW20: Much worse | AX20: =VLOOKUP(AW20,Metric_Codes!$C$91:$D$95,2,FALSE) -> 1 | AY20: High | AZ20: 6-10 Years | BA20: 120 | BB20: Much worse | BC20: =VLOOKUP(BB20,Metric_Codes!$C$91:$D$95,2,FALSE) -> 1 | BD20: Improved | BE20: =VLOOKUP(BD20,Metric_Codes!$C$91:$D$95,2,FALSE) -> 4 | BF20: =(BC20+BE20)/2 -> 2.5 | BG20: High | BH20: Small | BI20: 40 | BJ20: Stagnant regional economy; lack of cooperation between various local authorities - municiplaity, province and region; inappropriate intervention by Berlusconi central govewrnment in relocating displaced to new distant settlement; ancient city centre 'moth-balled'; heroic effort by fire brigade to scaffold and preserve historic buildings
A21: 20 | B21: 2010 Maule earthquake | C21: Chile | D21: CHL | E21: Earthquake & Tsunami | F21: Earthquake | G21: Geophysical | H21: 2010 | I21: 8.8 Mw | J21: Extremely catastrophic damage | K21: Concepción | L21: Regional | M21: 16993354 | N21: B: Service-Oriented Economy (67-75% of economy based on services) | O21: Service-Oriented | P21: 58.4 | Q21: High | R21: Growing | S21: 0.06 | T21: 12860.2 | U21: 20804 | V21: 0.661 | W21: 51 | X21: 67 | Y21: 0.01481713 | Z21: 40-60% | AA21: 30000000 | AB21: 547 | AC21: 800000 | AD21: 5540000 | AE21: 0.3260098 | AF21: Equal | AG21: 110000 | AI21: 5500000 | AJ21: >12 Months | AK21: Sufficient | AL21: Moderate | AM21: Medium | AN21: Flawed democracy | AO21: Specially-formed agency | AP21: Well prepared | AQ21: Extensive | AR21: Established scientific basis | AS21: Very good | AT21: Frequent | AU21: 3-5 Years | AV21: 36 | AW21: Improved | AX21: =VLOOKUP(AW21,Metric_Codes!$C$91:$D$95,2,FALSE) -> 4 | AY21: High | AZ21: 3-5 Years | BA21: 36 | BB21: Improved | BC21: =VLOOKUP(BB21,Metric_Codes!$C$91:$D$95,2,FALSE) -> 4 | BD21: Improved | BE21: =VLOOKUP(BD21,Metric_Codes!$C$91:$D$95,2,FALSE) -> 4 | BF21: =(BC21+BE21)/2 -> 4 | BG21: High | BH21: Moderate | BI21: 59 | BJ21: Fast response by central govt to prepare national plan and legislate for funding; delegating implementation to regional government who set up team of archiects and planners to plan and manage reconstruction; exemplorary community involvement; effort to provide temporary accommodation for local businesses;
A22: 21 | B22: 2011 Christchurch earthquake | C22: New Zealand | D22: NZL | E22: Earthquake | F22: Earthquake | G22: Geophysical | H22: 2011 | I22: 6.3 Mw | J22: Severe damage | K22: Christchurch | L22: Regional | M22: 4384000 | N22: A: Service-Dominated Economy (more than 75% of economy based on services) | O22: Service-Oriented | P22: 84.4 | Q22: High | R22: Stable | S22: 0.01 | T22: 38426.6 | U22: 32569 | V22: 0.846 | W22: 33 | X22: 87 | Y22: 0.04931718 | Z22: 40-60% | AA22: 15000000 | AB22: 181 | AC22: 70000 | AD22: 348435 | AE22: 0.079478786 | AF22: Mostly external | AG22: 11400000 | AI22: 12000000 | AJ22: <12 Months | AK22: Sufficient | AL22: Major | AM22: High | AN22: Full democracy | AO22: Specially-formed agency | AP22: Well prepared | AQ22: Adequate | AR22: Established scientific basis | AS22: Mediocre | AT22: Infrequent | AU22: 3-5 Years | AV22: 48 | AW22: Same | AX22: =VLOOKUP(AW22,Metric_Codes!$C$91:$D$95,2,FALSE) -> 3 | AY22: High | AZ22: 3-5 Years | BA22: 60 | BB22: Same | BC22: =VLOOKUP(BB22,Metric_Codes!$C$91:$D$95,2,FALSE) -> 3 | BD22: Improved | BE22: =VLOOKUP(BD22,Metric_Codes!$C$91:$D$95,2,FALSE) -> 4 | BF22: =(BC22+BE22)/2 -> 3.5 | BG22: High | BH22: Crucial | BI22: 77 | BJ22: Severe liquifaction in Avon valley has meant large residential area red zones and then abandoned; city centre decimated; businesses relocated to 6 periferal commercial centres; v high level of insurance; minister advocated demolition of heritage masonry buildings; many after shocks created intense complexity to resolve claims
A23: 22 | B23: 2011 Tōhoku earthquake and tsunami | C23: Japan | D23: JPN | E23: Earthquake & Tsunami | F23: Earthquake | G23: Geophysical | H23: 2011 | I23: 9.0 Mw | J23: Extremely catastrophic damage | K23: Tohoku | L23: Regional | M23: 127833000 | N23: B: Service-Oriented Economy (67-75% of economy based on services) | O23: Service-Oriented | P23: 72.1 | Q23: High | R23: Contracting | S23: -0.05 | T23: 48168 | U23: 36747 | V23: 0.779 | W23: 32 | X23: 73 | Y23: 0.02186681 | Z23: 60-80% | AA23: 210000000 | AB23: 20350 | AC23: 5150000 | AD23: 9630000 | AE23: 0.075332661 | AF23: Mostly external | AG23: 266000000 | AI23: 35000000 | AJ23: <12 Months | AK23: Sufficient | AL23: Major | AM23: High | AN23: Full democracy | AO23: Specialised gov. agency | AP23: Somewhat prepared | AQ23: Adequate | AR23: Established scientific basis | AS23: Mediocre | AT23: Frequent | AU23: 6-10 Years | AV23: 96 | AW23: Worse | AX23: =VLOOKUP(AW23,Metric_Codes!$C$91:$D$95,2,FALSE) -> 2 | AY23: High | AZ23: 6-10 Years | BA23: 108 | BB23: Worse | BC23: =VLOOKUP(BB23,Metric_Codes!$C$91:$D$95,2,FALSE) -> 2 | BD23: Much improved | BE23: =VLOOKUP(BD23,Metric_Codes!$C$91:$D$95,2,FALSE) -> 5 | BF23: =(BC23+BE23)/2 -> 3.5 | BG23: High | BH23: Important | BI23: 92 | BJ23: Severe shock to highly prepared country that imagined it was protected; high death toll in Sendai plain area; Iwate province already in demographic and economic decline; plans to relocate people from small ports deemed as unviable and consolidation of settlements thwarted by requirment to consult and reach concensus withelderly men
A24: 23 | B24: 2011 Van earthquake | C24: Turkey | D24: TUR | E24: Earthquake | F24: Earthquake & Tsunami | G24: Geophysical | H24: 2011 | I24: 7.1 Mw | J24: Catastrophic damage | K24: Van | L24: Regional | M24: 73409455 | N24: B: Service-Oriented Economy (67-75% of economy based on services) | O24: Industry with Service | P24: 64.6 | Q24: Upper middle | R24: Growing | S24: 0.08 | T24: 11340.8 | U24: 18391 | V24: 0.639 | W24: 39 | X24: 41 | Y24: 0.01091015 | Z24: 0-20% | AA24: 1500000 | AB24: 601 | AC24: 180000 | AD24: 1000000 | AE24: 0.013622223 | AF24: Mostly self-funded | AG24: 2000000 | AI24: 200000 | AJ24: >24 Months | AK24: Sufficient | AL24: Miniimal | AM24: High | AN24: Hybrid regime | AO24: Specialised gov. agency | AP24: Well prepared | AQ24: Inadequate | AR24: Established scientific basis | AS24: Mediocre | AT24: Frequent | AU24: 3-5 Years | AV24: 48 | AW24: Same | AX24: =VLOOKUP(AW24,Metric_Codes!$C$91:$D$95,2,FALSE) -> 3 | AY24: High | AZ24: 1-2 Years | BA24: 18 | BB24: Worse | BC24: =VLOOKUP(BB24,Metric_Codes!$C$91:$D$95,2,FALSE) -> 2 | BD24: Improved | BE24: =VLOOKUP(BD24,Metric_Codes!$C$91:$D$95,2,FALSE) -> 4 | BF24: =(BC24+BE24)/2 -> 3 | BG24: High | BH24: Negligible | BI24: 133 | BJ24: Modertae earthquake in fast east away from main centres of power; Kurdish area; compicated by Kurdish separatist movement; new Toki housing constructed very quickly with no regard for local ways of life or architecture; safety of repair compromised by corruption
A25: 24 | B25: 2015 Gorkha earthquake | C25: Nepal | D25: NPL | E25: Earthquake | F25: Earthquake | G25: Geophysical | H25: 2015 | I25: 7.8 Mw | J25: Catastrophic damage | K25: Gorkha | L25: National | M25: 28656282 | O25: Industry-Oriented | P25: 53.8 | Q25: Low | R25: Growing | S25: 0.0332 | T25: 747.16 | U25: 2500 | V25: 0.427 | W25: 32.8 | X25: 31 | Y25: <0.5% | Z25: 60-80% | AA25: 5174000 | AB25: 8831 | AC25: 81000 | AD25: 5639722 | AE25: 0.19680578 | AF25: Mostly self-funded | AG25: 178000 | AH25: 241000 | AI25: 100000 | AJ25: >12 Months | AK25: Insufficient | AL25: Miniimal | AM25: High | AN25: Hybrid regime | AO25: Specially-formed agency | AP25: Unprepared | AQ25: Inadequate | AR25: No scientific basis | AS25: Poor | AT25: Frequent | AU25: 3-5 Years | AV25: 48 | AW25: Same | AX25: =VLOOKUP(AW25,Metric_Codes!$C$91:$D$95,2,FALSE) -> 3 | AY25: High | AZ25: 6-10 Years | BA25: 84 | BB25: Same | BC25: =VLOOKUP(BB25,Metric_Codes!$C$91:$D$95,2,FALSE) -> 3 | BD25: Same | BE25: =VLOOKUP(BD25,Metric_Codes!$C$91:$D$95,2,FALSE) -> 3 | BF25: =(BC25+BE25)/2 -> 3 | BG25: High | BH25: Negligible | BI25: 61 | BJ25: High death toll from poor constrcution in both rural and urban areas; Earthquake advice to crawl under a table meant that many killed when they ran back indoors rather than staying safe outside; compensation to rebuild hampered by corruption;
A26: 25 | B26: 1995 Great Hanshin (Kobe) earthquake | C26: Japan | D26: JPN | E26: Earthquake | F26: Earthquake | G26: Geophysical | H26: 1995 | I26: 6.9 Mw | J26: Severe damage | K26: Kobe | L26: Regional | M26: 92500572 | N26: B: Service-Oriented Economy (67-75% of economy based on services) | O26: Service-Oriented | P26: 72.1 | Q26: High | R26: Growing | S26: 0.027 | T26: 43440.4 | U26: 23610 | V26: 0.876 | W26: 32.1 | X26: 73 | Y26: 0.02405965 | Z26: 60-80% | AA26: 100000000 | AB26: 5297 | AD26: 541636 | AE26: 0.0058554881 | AF26: Equal | AG26: 8070000 | AH26: 44812000 | AI26: 3000000 | AJ26: <12 Months | AK26: Sufficient | AL26: Moderate | AM26: Medium | AN26: Full democracy | AO26: Central gov. | AP26: Well prepared | AQ26: Inadequate | AR26: Established scientific basis | AS26: Good | AT26: Frequent | AU26: 1-2 Years | AV26: 18 | AW26: Worse | AX26: =VLOOKUP(AW26,Metric_Codes!$C$91:$D$95,2,FALSE) -> 2 | AY26: High | AZ26: 3-5 Years | BA26: 48 | BB26: Improved | BC26: =VLOOKUP(BB26,Metric_Codes!$C$91:$D$95,2,FALSE) -> 4 | BD26: Much improved | BE26: =VLOOKUP(BD26,Metric_Codes!$C$91:$D$95,2,FALSE) -> 5 | BF26: =(BC26+BE26)/2 -> 4.5 | BG26: High | BH26: Small | BI26: 11 | BJ26: High death toll from heavy stone roofs and removal of internal sheer walls;
A27: 26 | B27: 2010 Haiti earthquake | C27: Haiti | D27: HTI | E27: Earthquake & Tsunami | F27: Earthquake & Tsunami | G27: Geophysical | H27: 2010 | I27: 7.0 Mw | J27: Catastrophic damage | K27: Port-au-Prince | L27: Regional | M27: 9999617 | O27: Service-Oriented | P27: 52.7 | Q27: Low | R27: Contracting | S27: -0.055 | T27: 662.3 | U27: 1480 | V27: 0.304 | W27: 41.1 | X27: 20 | Y27: 0.003 | Z27: 80-100% | AA27: 8000000 | AB27: 222570 | AC27: 1500000 | AD27: 3700000 | AE27: 0.37001417 | AF27: Mostly self-funded | AH27: 1600000 | AI27: 150000 | AJ27: <12 Months | AK27: Insufficient | AL27: Miniimal | AM27: High | AN27: Hybrid regime | AO27: Central gov. | AP27: Completely unprepared | AQ27: Extensive | AR27: Limited scientific basis | AS27: Very poor | AT27: Frequent | AU27: 6-10 Years | AV27: 96 | AW27: Same | AX27: =VLOOKUP(AW27,Metric_Codes!$C$91:$D$95,2,FALSE) -> 3 | AY27: Medium | AZ27: 6-10 Years | BA27: 108 | BB27: Same | BC27: =VLOOKUP(BB27,Metric_Codes!$C$91:$D$95,2,FALSE) -> 3 | BD27: Same | BE27: =VLOOKUP(BD27,Metric_Codes!$C$91:$D$95,2,FALSE) -> 3 | BF27: =(BC27+BE27)/2 -> 3 | BG27: Medium | BH27: Negligible | BI27: 18 | BJ27: Massive death toll; chaotic; lack of effective government; lack of datato measure impact, assess need or track recovery. Many NGOs involved in recovery
A28: 27 | B28: 2010 Mentawai earthquake and tsunami | C28: Indonesia | D28: IDN | E28: Earthquake & Tsunami | F28: Earthquake & Tsunami | G28: Geophysical | H28: 2010 | I28: 7.8 Mw | J28: Catastrophic damage | K28: Mentawai | L28: Regional | M28: 242524123 | N28: C: Service with Industry (service 50-67% and Industry >25%) | O28: Mixed | P28: 65.8 | Q28: Lower middle | R28: Growing | S28: 0.062 | T28: 3113.5 | U28: 8040 | V28: 0.563 | W28: 38.1 | X28: 38 | Y28: 0.004087398 | Z28: 40-60% | AA28: 3482 | AB28: 530 | AC28: 20000 | AD28: 11864 | AE28: 4.8918845e-05 | AF28: Mostly self-funded | AH28: 81000 | AJ28: >24 Months | AK28: Insufficient | AL28: Miniimal | AM28: High | AN28: Flawed democracy | AO28: Specialised gov. agency | AP28: Somewhat prepared | AQ28: Inadequate | AR28: Limited scientific basis | AS28: Poor | AT28: Frequent | AU28: 1-2 Years | AV28: 18 | AW28: Same | AX28: =VLOOKUP(AW28,Metric_Codes!$C$91:$D$95,2,FALSE) -> 3 | AY28: Low | AZ28: 3-5 Years | BA28: 36 | BB28: Same | BC28: =VLOOKUP(BB28,Metric_Codes!$C$91:$D$95,2,FALSE) -> 3 | BD28: Improved | BE28: =VLOOKUP(BD28,Metric_Codes!$C$91:$D$95,2,FALSE) -> 4 | BF28: =(BC28+BE28)/2 -> 3.5 | BG28: Medium | BH28: Negligible | BI28: 12 | BJ28: Isolated Christain area in a Muslim country
A29: 28 | B29: 1931 China Floods | C29: China | D29: CHN | E29: Flood | F29: Riverine Flood | G29: Climate | H29: 1931 | I29: 180,000 km2; max water leve 16 m (Wuhan); av. 1.7 m above Shanghai Bund | J29: Extremely catastrophic damage | K29: Anhui, Hubei (esp. Wuhan), Hunan, Jiangsu, Zhejiang, Jiangxi, Henan, Shandong | L29: National | M29: 667070000 | N29: C: Service with Industry (service 50-67% and Industry >25%) | O29: Mixed | P29: 67.3 | Q29: Upper middle | R29: Contracting | S29: -0.2727 | T29: 89.52 | U29: 990 | V29: 0.643 | W29: 38.6 | X29: 39 | Z29: 80-100% | AA29: 1400000 | AB29: 3700000 | AC29: 25000000 | AF29: Mostly self-funded | AJ29: >24 Months | AK29: Totally insufficient | AL29: Miniimal | AM29: High | AN29: Authoritarian | AO29: Central gov. | AP29: Completely unprepared | AQ29: Inadequate | AR29: Established scientific basis | AS29: Very poor | AT29: Frequent | AU29: 11-20 Years | AV29: 180 | AW29: Improved | AX29: =VLOOKUP(AW29,Metric_Codes!$C$91:$D$95,2,FALSE) -> 4 | AY29: Low | AZ29: 11-20 Years | BA29: 180 | BB29: Improved | BC29: =VLOOKUP(BB29,Metric_Codes!$C$91:$D$95,2,FALSE) -> 4 | BD29: Improved | BE29: =VLOOKUP(BD29,Metric_Codes!$C$91:$D$95,2,FALSE) -> 4 | BF29: =(BC29+BE29)/2 -> 4 | BG29: Low | BH29: Negligible | BI29: 5 | BJ29: recovery slowed by japanese invasion, civil war and Communist take-over
A30: 29 | B30: 1937 (Ohio River) Great Flood | C30: United States | D30: USA | E30: Flood | F30: Riverine Flood | G30: Climate | H30: 1937 | I30: Max water Evansville, Indiana (16 m); Cincinnati (24 m); Louisville (17 m); Paducah, Kentucky (18 m) | J30: Catastrophic damage | K30: Ohio | L30: Regional | M30: 180671000 | N30: A: Service-Dominated Economy (more than 75% of economy based on services) | O30: Service-Oriented | P30: 76.8 | Q30: High | R30: Growing | S30: 0.023 | T30: 3007.12 | U30: 23730 | V30: 0.797 | W30: 41.5 | X30: 71 | Z30: 60-80% | AA30: 1516000 | AB30: 385 | AC30: 1000000 | AF30: Mostly self-funded | AG30: 1068000 | AH30: 31000 | AJ30: >12 Months | AK30: Insufficient | AL30: Miniimal | AM30: High | AN30: Full democracy | AO30: Central gov. | AP30: Unprepared | AQ30: Adequate | AR30: Established scientific basis | AS30: Poor | AT30: Frequent | AU30: 6-10 Years | AV30: 96 | AW30: Improved | AX30: =VLOOKUP(AW30,Metric_Codes!$C$91:$D$95,2,FALSE) -> 4 | AY30: Low | AZ30: 6-10 Years | BA30: 96 | BB30: Improved | BC30: =VLOOKUP(BB30,Metric_Codes!$C$91:$D$95,2,FALSE) -> 4 | BD30: Much improved | BE30: =VLOOKUP(BD30,Metric_Codes!$C$91:$D$95,2,FALSE) -> 5 | BF30: =(BC30+BE30)/2 -> 4.5 | BG30: Low | BH30: Negligible | BI30: 23 | BJ30: recovery slowed by Great Depression
A31: 30 | B31: 1939 China Floods | C31: China | D31: CHN | E31: Flood | F31: Riverine Flood | G31: Climate | H31: 1939 | I31: Assumption | J31: Catastrophic damage | K31: Tientsin | L31: Local | M31: 667070000 | N31: C: Service with Industry (service 50-67% and Industry >25%) | O31: Mixed | P31: 67.3 | Q31: Upper middle | R31: Contracting | S31: -0.2727 | T31: 89.52 | U31: 990 | V31: 0.643 | W31: 38.6 | X31: 39 | Z31: 60-80% | AA31: 1400000 | AB31: 20000 | AD31: 3000000 | AE31: 0.0044972791 | AF31: Self-funded | AK31: Totally insufficient | AL31: Miniimal | AM31: High | AN31: Authoritarian | AO31: Central gov. | AP31: Completely unprepared | AQ31: Inadequate | AR31: Established scientific basis | AS31: Poor | AT31: Frequent | AU31: 11-20 Years | AV31: 180 | AW31: Same | AX31: =VLOOKUP(AW31,Metric_Codes!$C$91:$D$95,2,FALSE) -> 3 | AY31: Low | AZ31: 11-20 Years | BA31: 144 | BB31: Same | BC31: =VLOOKUP(BB31,Metric_Codes!$C$91:$D$95,2,FALSE) -> 3 | BD31: Improved | BE31: =VLOOKUP(BD31,Metric_Codes!$C$91:$D$95,2,FALSE) -> 4 | BF31: =(BC31+BE31)/2 -> 3.5 | BG31: Low | BH31: Negligible | BI31: 3 | BJ31: recovery slowed by 2nd WW, and Communist Great leap Forward
A32: 31 | B32: 1949 Guatemala Floods | C32: Guatemala | D32: GTM | E32: Flood | F32: Riverine Flood | G32: Climate | H32: 1949 | I32: Assumption | J32: Extremely catastrophic damage | K32: Pacific coast | L32: Regional | M32: 4210747 | O32: Service-Oriented | P32: 62.6 | Q32: Upper middle | R32: Growing | S32: 0.043 | T32: 247.84 | U32: 3230 | V32: 0.467 | W32: 48.3 | X32: 27 | Y32: <0.5% | Z32: 20-40% | AA32: 15000 | AB32: 1000 | AC32: 20000 | AF32: Mostly self-funded | AK32: Insufficient | AL32: Miniimal | AM32: High | AN32: Hybrid regime | AO32: Central gov. | AP32: Completely unprepared | AQ32: Inadequate | AR32: Limited scientific basis | AS32: Poor | AT32: Frequent | AU32: 1-2 Years | AV32: 18 | AW32: Same | AX32: =VLOOKUP(AW32,Metric_Codes!$C$91:$D$95,2,FALSE) -> 3 | AY32: Low | AZ32: 3-5 Years | BA32: 36 | BB32: Same | BC32: =VLOOKUP(BB32,Metric_Codes!$C$91:$D$95,2,FALSE) -> 3 | BD32: Same | BE32: =VLOOKUP(BD32,Metric_Codes!$C$91:$D$95,2,FALSE) -> 3 | BF32: =(BC32+BE32)/2 -> 3 | BG32: Low | BH32: Negligible | BI32: 4 | BJ32: discepancy in number of fatalities EMDAT 40,000
A33: 32 | B33: 1953 North Kyushu Flood | C33: Japan | D33: JPN | E33: Flood | F33: Riverine Flood | G33: Climate | H33: 1953 | I33: Kamamoto city 70% inundated; 2.5-3 m | J33: Catastrophic damage | K33: Northern Kyushu -Kumamoto/Fukuoka | L33: Regional | M33: 92500572 | N33: B: Service-Oriented Economy (67-75% of economy based on services) | O33: Service-Oriented | P33: 72.1 | Q33: High | R33: Growing | S33: 0.1204 | T33: 479 | U33: 19620 | V33: 0.876 | W33: 32.1 | X33: 73 | Y33: ~1% | Z33: 20-40% | AA33: 1991000 | AB33: 759 | AD33: 1886760 | AE33: 0.020397279 | AF33: Mostly self-funded | AJ33: >12 Months | AK33: Sufficient | AL33: Miniimal | AM33: High | AN33: Full democracy | AO33: Central gov. | AP33: Somewhat prepared | AQ33: Adequate | AR33: Established scientific basis | AS33: Poor | AT33: Frequent | AU33: 1-2 Years | AV33: 18 | AW33: Same | AX33: =VLOOKUP(AW33,Metric_Codes!$C$91:$D$95,2,FALSE) -> 3 | AY33: Low | AZ33: 1-2 Years | BA33: 18 | BB33: Same | BC33: =VLOOKUP(BB33,Metric_Codes!$C$91:$D$95,2,FALSE) -> 3 | BD33: Improved | BE33: =VLOOKUP(BD33,Metric_Codes!$C$91:$D$95,2,FALSE) -> 4 | BF33: =(BC33+BE33)/2 -> 3.5 | BG33: Low | BH33: Negligible | BI33: 4 | BJ33: EMDAT 2,566 fatalities
A34: 33 | B34: 1953 North Sea Flood | C34: Netherlands | D34: NLD | E34: Flood | F34: Coastal Flood | G34: Climate | H34: 1953 | I34: Max water 5.6 m AMSL; 50% Netherlands <1 m AMSL | J34: Catastrophic damage | K34: South East coast | L34: Regional | M34: 11486631 | N34: A: Service-Dominated Economy (more than 75% of economy based on services) | O34: Service-Dominated | P34: 76.8 | Q34: High | R34: Stable | S34: 0.003 | T34: 1068.78 | U34: 18730 | V34: 0.857 | W34: 28.2 | X34: 82 | Y34: <3% | Z34: 0-20% | AA34: 300000 | AB34: 1836 | AC34: 72000 | AD34: 300000 | AE34: 0.026117318 | AF34: Mostly external | AJ34: <12 Months | AK34: Sufficient | AL34: Major | AM34: High | AN34: Full democracy | AO34: Central gov. | AP34: Well prepared | AQ34: Adequate | AR34: Established scientific basis | AS34: Good | AT34: Infrequent | AU34: 6-11 Months | AV34: 9 | AW34: Improved | AX34: =VLOOKUP(AW34,Metric_Codes!$C$91:$D$95,2,FALSE) -> 4 | AY34: Medium | AZ34: 1-2 Years | BA34: 18 | BB34: Improved | BC34: =VLOOKUP(BB34,Metric_Codes!$C$91:$D$95,2,FALSE) -> 4 | BD34: Much improved | BE34: =VLOOKUP(BD34,Metric_Codes!$C$91:$D$95,2,FALSE) -> 5 | BF34: =(BC34+BE34)/2 -> 4.5 | BG34: Medium | BH34: Important | BI34: 12 | BJ34: Also UK with similar recovery speed and quality
A35: 34 | B35: 1954 Iran Summer Floods | C35: Iran, Islamic Rep. | D35: IRN | E35: Flood | F35: Flash Flood | G35: Climate | H35: 1954 | I35: Assumption | J35: Catastrophic damage | K35: Farahzad, Tehran | L35: Local | M35: 21906903 | N35: F: Industry with Service (Industry and Service both 33-50%) | O35: Mixed | P35: 51.1 | Q35: Upper middle | R35: Growing | S35: 0.1148 | T35: 191.68 | U35: 7390 | V35: 0.707 | W35: 40 | X35: 28 | Y35: <0.3 | Z35: 40-60% | AB35: 2150 | AF35: Mostly self-funded | AK35: Insufficient | AL35: Miniimal | AM35: High | AN35: Authoritarian | AO35: Central gov. | AP35: Unprepared | AQ35: Inadequate | AR35: Limited scientific basis | AS35: Poor | AT35: Frequent | AU35: 6-11 Months | AV35: 9 | AW35: Same | AX35: =VLOOKUP(AW35,Metric_Codes!$C$91:$D$95,2,FALSE) -> 3 | AY35: Low | AZ35: 1-2 Years | BA35: 18 | BB35: Same | BC35: =VLOOKUP(BB35,Metric_Codes!$C$91:$D$95,2,FALSE) -> 3 | BD35: Same | BE35: =VLOOKUP(BD35,Metric_Codes!$C$91:$D$95,2,FALSE) -> 3 | BF35: =(BC35+BE35)/2 -> 3 | BG35: Low | BH35: Negligible | BI35: 2 | BJ35: period of political turmoil
A36: 35 | B36: 1962 Rubi Flood | C36: Spain | D36: ESP | E36: Flood | F36: Flash Flood | G36: Climate | H36: 1962 | I36: 200cm rainfall in <2hr; <1:200 yr | J36: Extremely catastrophic damage | K36: Lobregat, Barcelona | L36: Local | M36: 31023366 | N36: A: Service-Dominated Economy (more than 75% of economy based on services) | O36: Industry with Service | P36: 65.7 | Q36: High | R36: Growing | S36: 0.0995 | T36: 520.21 | U36: 13530 | V36: 0.754 | W36: 36.2 | X36: 58 | Y36: <1% | Z36: 20-40% | AA36: 80000 | AB36: 815 | AF36: Mostly self-funded | AK36: Insufficient | AL36: Moderate | AM36: High | AN36: Full democracy | AO36: Central gov. | AP36: Unprepared | AQ36: Adequate | AR36: Established scientific basis | AS36: Mediocre | AT36: Occasional | AU36: 6-11 Months | AV36: 9 | AW36: Improved | AX36: =VLOOKUP(AW36,Metric_Codes!$C$91:$D$95,2,FALSE) -> 4 | AY36: Low | AZ36: 1-2 Years | BA36: 18 | BB36: Improved | BC36: =VLOOKUP(BB36,Metric_Codes!$C$91:$D$95,2,FALSE) -> 4 | BD36: Improved | BE36: =VLOOKUP(BD36,Metric_Codes!$C$91:$D$95,2,FALSE) -> 4 | BF36: =(BC36+BE36)/2 -> 4 | BG36: Low | BH36: Small | BI36: 4 | BJ36: big influx of immigrants from S America and N Africa
A37: 36 | B37: 1963 Landslide of the Vajont Dam | C37: Italy | D37: ITA | E37: Flood | F37: Riverine Flood | G37: Climate | H37: 1963 | I37: flood wave overtop dam in 250 m high wave | J37: Extremely catastrophic damage | K37: Piave Valley north Venice | L37: Local | M37: 51252000 | N37: A: Service-Dominated Economy (more than 75% of economy based on services) | O37: Industry-Oriented | P37: 62.2 | Q37: High | R37: Growing | S37: 0.062 | T37: 1126.02 | U37: 18330 | V37: 0.771 | W37: 35.4 | X37: 52 | Y37: <0.8 | Z37: 80-100% | AA37: 2000000 | AB37: 1917 | AC37: 1300000 | AD37: 1300000 | AE37: 0.025364864 | AF37: External | AJ37: >24 Months | AK37: Sufficient | AL37: Miniimal | AM37: High | AN37: Flawed democracy | AO37: Central gov. | AP37: Completely unprepared | AQ37: Inadequate | AR37: Limited scientific basis | AS37: Mediocre | AT37: Infrequent | AU37: 6-10 Years | AV37: 96 | AW37: Improved | AX37: =VLOOKUP(AW37,Metric_Codes!$C$91:$D$95,2,FALSE) -> 4 | AY37: Low | BB37: Worse | BC37: =VLOOKUP(BB37,Metric_Codes!$C$91:$D$95,2,FALSE) -> 2 | BD37: Much improved | BE37: =VLOOKUP(BD37,Metric_Codes!$C$91:$D$95,2,FALSE) -> 5 | BF37: =(BC37+BE37)/2 -> 3.5 | BG37: Medium | BH37: Negligible | BI37: 8 | BJ37: 80% of inhabitants killed survivors moved 50km to newly built village Vajont, Longarone, the town in path of tsunami, was rebuilt
A38: 37 | B38: 1966 Jordan Flood | C38: Jordan | D38: JOR | E38: Flood | F38: Flash Flood | G38: Climate | H38: 1966 | I38: 1:50 RP | J38: Catastrophic damage | K38: Ma'an | L38: Local | M38: 1265806 | O38: Industry-Oriented | P38: 66.5 | Q38: Upper middle | R38: Growing | S38: 0.2431 | T38: 519.89 | U38: 3850 | V38: 0.617 | W38: 33.7 | X38: 49 | Y38: 0 | Z38: 40-60% | AA38: 1400 | AB38: 259 | AC38: 2500 | AD38: 5792 | AE38: 0.0045757407 | AF38: Mostly self-funded | AK38: Insufficient | AL38: Miniimal | AM38: High | AN38: Authoritarian | AO38: Central gov. | AP38: Unprepared | AQ38: Inadequate | AR38: Limited scientific basis | AS38: Very poor | AT38: Frequent | AU38: 6-11 Months | AV38: 9 | AW38: Same | AX38: =VLOOKUP(AW38,Metric_Codes!$C$91:$D$95,2,FALSE) -> 3 | AY38: Low | AZ38: 1-2 Years | BA38: 18 | BB38: Same | BC38: =VLOOKUP(BB38,Metric_Codes!$C$91:$D$95,2,FALSE) -> 3 | BD38: Same | BE38: =VLOOKUP(BD38,Metric_Codes!$C$91:$D$95,2,FALSE) -> 3 | BF38: =(BC38+BE38)/2 -> 3 | BG38: Low | BH38: Negligible | BI38: 7 | BJ38: Poor urban planning, recent huge refugee problem
A39: 38 | B39: 1967 Lisbon Flood | C39: Portugal | D39: PRT | E39: Flood | F39: Flash Flood | G39: Climate | H39: 1967 | I39: >1:100 yr rainfall | J39: Extremely catastrophic damage | K39: Lisbon | L39: Local | M39: 8874520 | N39: A: Service-Dominated Economy (more than 75% of economy based on services) | O39: Service-Oriented | P39: 65.3 | Q39: High | R39: Growing | S39: 0.0754 | T39: 646.82 | U39: 11770 | V39: 0.732 | W39: 35.5 | X39: 64 | Y39: <2% | Z39: 40-60% | AA39: 3000 | AB39: 462 | AD39: 1100 | AE39: 0.00012395037 | AF39: Mostly self-funded | AK39: Insufficient | AL39: Miniimal | AM39: High | AN39: Flawed democracy | AO39: Central gov. | AP39: Unprepared | AQ39: Adequate | AR39: Established scientific basis | AS39: Poor | AT39: Frequent | AU39: 6-11 Months | AV39: 9 | AW39: Same | AX39: =VLOOKUP(AW39,Metric_Codes!$C$91:$D$95,2,FALSE) -> 3 | AY39: Low | AZ39: 6-11 Months | BA39: 9 | BB39: Same | BC39: =VLOOKUP(BB39,Metric_Codes!$C$91:$D$95,2,FALSE) -> 3 | BD39: Same | BE39: =VLOOKUP(BD39,Metric_Codes!$C$91:$D$95,2,FALSE) -> 3 | BF39: =(BC39+BE39)/2 -> 3 | BG39: Low | BH39: Negligible | BI39: 5 | BJ39: Lack of information; 20,000 houses were destroyed. Officially, there were 462 dead, but the number may have reached 700. In the face of Salazar's apathy, 5,000 students helped the victims. A movement that marked a generatio
A40: 39 | B40: 1972 Seoul Kyonggi Flood | C40: Korea, Rep. | D40: KOR | E40: Flood | F40: Riverine Flood | G40: Climate | H40: 1972 | I40: Seoul 45cm rainfall | J40: Catastrophic damage | K40: Seoul; Kyonggi, Kangwon, North Chungchong | L40: Regional | M40: 33505406 | N40: C: Service with Industry (service 50-67% and Industry >25%) | O40: Mixed | P40: 72.3 | Q40: High | R40: Growing | S40: 0.0715 | T40: 323.6 | U40: 8260 | V40: 0.773 | W40: 31.6 | X40: 57 | Y40: <0.5% | Z40: 40-60% | AA40: 72800 | AB40: 672 | AC40: 326000 | AD40: 1126785 | AE40: 0.033629946 | AF40: Mostly self-funded | AK40: Insufficient | AL40: Miniimal | AM40: High | AN40: Flawed democracy[a] | AO40: Central gov. | AP40: Somewhat prepared | AQ40: Inadequate | AR40: Limited scientific basis | AS40: Poor | AT40: Frequent | AU40: <6 Months | AV40: 3 | AW40: Same | AX40: =VLOOKUP(AW40,Metric_Codes!$C$91:$D$95,2,FALSE) -> 3 | AY40: Low | AZ40: 6-11 Months | BA40: 6 | BB40: Same | BC40: =VLOOKUP(BB40,Metric_Codes!$C$91:$D$95,2,FALSE) -> 3 | BD40: Same | BE40: =VLOOKUP(BD40,Metric_Codes!$C$91:$D$95,2,FALSE) -> 3 | BF40: =(BC40+BE40)/2 -> 3 | BG40: Low | BH40: Negligible | BI40: 6 | BJ40: Floods on Han River every 5 years; flood control, especially dams, has reduced risk; people cope with trafiic jams and loss of water supply
A41: 40 | B41: 1974 Bangladesh Floods and Famine | C41: Bangladesh | D41: BGD | E41: Flood | F41: Riverine Flood | G41: Climate | H41: 1974 | I41: area 52,720km2 | J41: Catastrophic damage | K41: Brahmaputra river | L41: National | M41: 69884420 | O41: Mixed | P41: 55.6 | Q41: Lower middle | R41: Growing | S41: 0.0959 | T41: 179 | U41: 850 | V41: 0.462 | W41: 32.4 | X41: 26 | Y41: 0 | Z41: 60-80% | AA41: 579200 | AB41: 28700 | AC41: 2000000 | AD41: 38000000 | AE41: 0.54375496 | AF41: Self-funded | AJ41: >12 Months | AK41: Totally insufficient | AL41: Miniimal | AM41: High | AN41: Hybrid regime | AO41: Central gov. | AP41: Unprepared | AQ41: Inadequate | AR41: No scientific basis | AS41: Very poor | AT41: Frequent | AU41: 3-5 Years | AV41: 48 | AW41: Worse | AX41: =VLOOKUP(AW41,Metric_Codes!$C$91:$D$95,2,FALSE) -> 2 | AY41: Low | AZ41: 6-11 Months | BA41: 9 | BB41: Same | BC41: =VLOOKUP(BB41,Metric_Codes!$C$91:$D$95,2,FALSE) -> 3 | BD41: Same | BE41: =VLOOKUP(BD41,Metric_Codes!$C$91:$D$95,2,FALSE) -> 3 | BF41: =(BC41+BE41)/2 -> 3 | BG41: Low | BH41: Negligible | BI41: 11 | BJ41: monsoon; famine; post 1971 independence turmoil; market mismanagement; rice price inflation; world-wide food prices; bankrupt government; American embargo on food aid; 1.5 million dead
A42: 41 | B42: 1988 Rio Flood | C42: Brazil | D42: BRA | E42: Flood | F42: Riverine Flood | G42: Climate | H42: 1988 | I42: 246mm rainfall overnight (95mm annual average) | J42: Catastrophic damage | K42: Rio; Piaui state, Ceara state | L42: Regional | M42: 144001542 | N42: B: Service-Oriented Economy (67-75% of economy based on services) | O42: Service-Oriented | P42: 51.9 | Q42: Upper middle | R42: Contracting | S42: -0.001 | T42: 2294.4 | U42: 6510 | V42: 0.578 | W42: 53.3 | X42: 35 | Y42: 0.008078475 | Z42: 20-40% | AA42: 935000 | AB42: 289 | AC42: 18560 | AD42: 3020734 | AE42: 0.020977095 | AF42: Mostly self-funded | AG42: 225000 | AH42: 175000 | AK42: Insufficient | AL42: Miniimal | AM42: High | AN42: Flawed democracy | AO42: Central gov. | AP42: Unprepared | AQ42: Inadequate | AR42: Limited scientific basis | AS42: Poor | AT42: Frequent | AU42: 6-11 Months | AV42: 9 | AW42: Same | AX42: =VLOOKUP(AW42,Metric_Codes!$C$91:$D$95,2,FALSE) -> 3 | AY42: Low | AZ42: 3-5 Years | BA42: 36 | BB42: Same | BC42: =VLOOKUP(BB42,Metric_Codes!$C$91:$D$95,2,FALSE) -> 3 | BD42: Improved | BE42: =VLOOKUP(BD42,Metric_Codes!$C$91:$D$95,2,FALSE) -> 4 | BF42: =(BC42+BE42)/2 -> 3.5 | BG42: Low | BH42: Negligible | BI42: 3 | BJ42: urban planning failures; inadequate local government
A43: 42 | B43: 1991 Malawi Floods | C43: Malawi | D43: MWI | E43: Flood | F43: Flash Flood | G43: Climate | H43: 1991 | I43: Assumption | J43: Extremely catastrophic damage | K43: Phalombe | L43: Local | M43: 9641153 | O43: Industry with Service | P43: 51.4 | Q43: Low | R43: Growing | S43: 0.087 | T43: 228.6 | U43: 520 | V43: 0.332 | W43: 44.7 | X43: 32 | Y43: 0 | Z43: 20-40% | AA43: 24000 | AB43: 472 | AC43: 150000 | AD43: 150000 | AE43: 0.015558305 | AF43: Mostly self-funded | AH43: 2296 | AK43: Insufficient | AL43: Miniimal | AM43: High | AN43: Hybrid regime | AO43: Central gov. | AP43: Unprepared | AQ43: Inadequate | AR43: Limited scientific basis | AS43: Very poor | AT43: Frequent | AU43: 6-11 Months | AV43: 9 | AW43: Same | AX43: =VLOOKUP(AW43,Metric_Codes!$C$91:$D$95,2,FALSE) -> 3 | AY43: Low | AZ43: 1-2 Years | BA43: 18 | BB43: Same | BC43: =VLOOKUP(BB43,Metric_Codes!$C$91:$D$95,2,FALSE) -> 3 | BD43: Same | BE43: =VLOOKUP(BD43,Metric_Codes!$C$91:$D$95,2,FALSE) -> 3 | BF43: =(BC43+BE43)/2 -> 3 | BG43: Low | BH43: Negligible | BI43: 9 | BJ43: Unregulated urban development; HIV epidemic
A44: 43 | B44: 1993 Great (Mississippi and Missouri Rivers) Flood | C44: United States | D44: USA | E44: Flood | F44: Riverine Flood | G44: Climate | H44: 1993 | I44: area 830,000km2; in such paces as St Louis, river levels 6m above flood stage | J44: Extremely catastrophic damage | K44: Mississippi & Missouri | L44: Regional | M44: 259919000 | N44: A: Service-Dominated Economy (more than 75% of economy based on services) | O44: Service-Oriented | P44: 76.8 | Q44: High | R44: Growing | S44: 0.027 | T44: 26464.9 | U44: 26000 | V44: 0.797 | W44: 41.5 | X44: 71 | Y44: 0.04913344 | Z44: 60-80% | AA44: 12000000 | AB44: 48 | AD44: 31000 | AE44: 0.00011926793 | AF44: Mostly self-funded | AG44: 1140000 | AI44: 1000000 | AJ44: >12 Months | AK44: Insufficient | AL44: Moderate | AM44: High | AN44: Full democracy | AO44: Central gov. | AP44: Somewhat prepared | AQ44: Inadequate | AR44: Established scientific basis | AS44: Mediocre | AT44: Frequent | AU44: 6-10 Years | AV44: 96 | AW44: Improved | AX44: =VLOOKUP(AW44,Metric_Codes!$C$91:$D$95,2,FALSE) -> 4 | AY44: Medium | AZ44: 3-5 Years | BA44: 48 | BB44: Same | BC44: =VLOOKUP(BB44,Metric_Codes!$C$91:$D$95,2,FALSE) -> 3 | BD44: Same | BE44: =VLOOKUP(BD44,Metric_Codes!$C$91:$D$95,2,FALSE) -> 3 | BF44: =(BC44+BE44)/2 -> 3 | BG44: Medium | BH44: Small | BI44: 43 | BJ44: Lasted from May to August; worst flood since 1927; floodwall saved St Louis; impacts lasted for years; 17 million acres flooded; barge traffic stopped for 2 months; one or worst disaster in US history; yet more homes built on flood plains and little done to reinforce levees post disaster
A45: 44 | B45: 1995 North Korea Floods and Famine | C45: Korea, Dem. People's Rep. | D45: PRK | E45: Flood | F45: Riverine Flood | G45: Climate | H45: 1995 | I45: Assumption | J45: Catastrophic damage | K45: 30% Nation | L45: Regional | M45: 21862299 | O45: Service-Dominated | P45: 5.9 | Q45: Low | R45: Contracting | S45: - | T45: - | U45: - | V45: - | W45: - | X45: 14 | Y45: 0.02464142 | Z45: 60-80% | AA45: 15000000 | AB45: 68 | AC45: 500000 | AD45: 5700000 | AE45: 0.26072281 | AF45: Self-funded | AH45: 1200 | AK45: Totally insufficient | AL45: Miniimal | AM45: High | AN45: Authoritarian | AO45: Central gov. | AP45: Completely unprepared | AQ45: Inadequate | AR45: Limited scientific basis | AS45: Very poor | AT45: Occasional | AW45: Same | AX45: =VLOOKUP(AW45,Metric_Codes!$C$91:$D$95,2,FALSE) -> 3 | AY45: Low | AZ45: 6-10 Years | BA45: 96 | BB45: Same | BC45: =VLOOKUP(BB45,Metric_Codes!$C$91:$D$95,2,FALSE) -> 3 | BD45: Same | BE45: =VLOOKUP(BD45,Metric_Codes!$C$91:$D$95,2,FALSE) -> 3 | BF45: =(BC45+BE45)/2 -> 3 | BG45: Low | BH45: Negligible | BI45: 2 | BJ45: 12% grain production lost; failure of distribution system; poor government decisions; 'Arduous March' famine 600,000-3,500,000 deaths; rice production fell from 3.5 million tons in 1993 to 0.98 in 1996; extensive deforestation
A46: 45 | B46: 1999 Vargas Tragedy | C46: Venezuela, RB | D46: VEN | E46: Flood | F46: Flash Flood | G46: Climate | H46: 1999 | I46: Assumption | J46: Extremely catastrophic damage | K46: Vargas State | L46: Regional | M46: 24028689 | N46: C: Service with Industry (service 50-67% and Industry >25%) | O46: Service-Oriented | P46: 25.9 | Q46: Upper middle | R46: Contracting | S46: -0.06 | T46: 4077.5 | U46: 10810 | V46: 0.636 | W46: 46.9 | X46: 18 | Y46: 0.01893619 | Z46: 60-80% | AA46: 3160000 | AB46: 30000 | AC46: 122888 | AD46: 483635 | AE46: 0.020127399 | AF46: Mostly self-funded | AK46: Insufficient | AL46: Miniimal | AM46: High | AN46: Authoritarian | AO46: Central gov. | AP46: Completely unprepared | AQ46: Inadequate | AR46: Established scientific basis | AS46: Very poor | AT46: Occasional | AU46: 6-10 Years | AV46: 96 | AW46: Worse | AX46: =VLOOKUP(AW46,Metric_Codes!$C$91:$D$95,2,FALSE) -> 2 | AY46: Low | AZ46: 11-20 Years | BA46: 144 | BB46: Worse | BC46: =VLOOKUP(BB46,Metric_Codes!$C$91:$D$95,2,FALSE) -> 2 | BD46: Same | BE46: =VLOOKUP(BD46,Metric_Codes!$C$91:$D$95,2,FALSE) -> 3 | BF46: =(BC46+BE46)/2 -> 2.5 | BG46: Low | BH46: Negligible | BI46: 14 | BJ46: Political polarisation; corruption and incompetence; In power only 10 months, Chavez lost interest in managing recovery; major relocation of survivors to Barquisimeto, Lara State, population numbers recovered in 4 years
A47: 46 | B47: 2010(-2011) Queensland Floods | C47: Australia | D47: AUS | E47: Flood | F47: Riverine Flood | G47: Climate | H47: 2010 | I47: Assumption | J47: Catastrophic damage | K47: Brisbane | L47: Regional | M47: 22031750 | N47: A: Service-Dominated Economy (more than 75% of economy based on services) | O47: Service-Dominated | P47: 80.9 | Q47: High | R47: Growing | S47: 0.021 | T47: 51936.9 | U47: 37750 | V47: 0.861 | W47: 35.8 | X47: 77 | Y47: 0.02172549 | Z47: 40-60% | AA47: 7300000 | AB47: 35 | AC47: 52000 | AD47: 175000 | AE47: 0.0079430821 | AF47: Equal | AG47: 30000 | AI47: 1500000 | AJ47: <12 Months | AK47: Sufficient | AL47: Major | AM47: High | AN47: Full democracy | AO47: Specially-formed agency | AP47: Somewhat prepared | AQ47: Adequate | AR47: Established scientific basis | AS47: Good | AT47: Occasional | AU47: 6-11 Months | AV47: 9 | AW47: Same | AX47: =VLOOKUP(AW47,Metric_Codes!$C$91:$D$95,2,FALSE) -> 3 | AY47: Medium | AZ47: 3-5 Years | BA47: 36 | BB47: Same | BC47: =VLOOKUP(BB47,Metric_Codes!$C$91:$D$95,2,FALSE) -> 3 | BD47: Same | BE47: =VLOOKUP(BD47,Metric_Codes!$C$91:$D$95,2,FALSE) -> 3 | BF47: =(BC47+BE47)/2 -> 3 | BG47: Medium | BH47: Important | BI47: 23 | BJ47: $440 million spent on recovery
A48: 47 | B48: 2010 Central European Floods | C48: Poland | D48: POL | E48: Flood | F48: Riverine Flood | G48: Climate | H48: 2010 | I48: 6.65 m in Trestno | J48: Catastrophic damage | K48: National | L48: National | M48: 38042794 | N48: B: Service-Oriented Economy (67-75% of economy based on services) | O48: Industry with Service | P48: 67.8 | Q48: High | R48: Growing | S48: 0.036 | T48: 12597.9 | U48: 20380 | V48: 0.787 | W48: 30.8 | X48: 60 | Y48: 0.01843549 | Z48: 40-60% | AA48: 3080000 | AB48: 16 | AC48: 23000 | AD48: 100000 | AE48: 0.0026286187 | AF48: Equal | AI48: 570000 | AJ48: >12 Months | AK48: Sufficient | AL48: Moderate | AM48: High | AN48: Flawed democracy | AO48: Central gov. | AP48: Somewhat prepared | AQ48: Adequate | AR48: Established scientific basis | AS48: Mediocre | AT48: Occasional | AU48: 6-11 Months | AV48: 9 | AW48: Same | AX48: =VLOOKUP(AW48,Metric_Codes!$C$91:$D$95,2,FALSE) -> 3 | AY48: Low | AZ48: 1-2 Years | BA48: 18 | BB48: Same | BC48: =VLOOKUP(BB48,Metric_Codes!$C$91:$D$95,2,FALSE) -> 3 | BD48: Improved | BE48: =VLOOKUP(BD48,Metric_Codes!$C$91:$D$95,2,FALSE) -> 4 | BF48: =(BC48+BE48)/2 -> 3.5 | BG48: Low | BH48: Small | BI48: 10 | BJ48: Czech republic, Germany, Hungary also affected
A49: 48 | B49: 2011 Rio de Janeiro Floods | C49: Brazil | D49: BRA | E49: Flood | F49: Riverine Flood | G49: Climate | H49: 2011 | I49: Assumption | J49: Catastrophic damage | K49: Rio State | L49: Regional | M49: 198686688 | N49: B: Service-Oriented Economy (67-75% of economy based on services) | O49: Service-Oriented | P49: 51.9 | Q49: Upper middle | R49: Growing | S49: 0.04 | T49: 13167.5 | U49: 14580 | V49: 0.578 | W49: 53.3 | X49: 35 | Y49: 0.01479434 | Z49: 20-40% | AA49: 1000000 | AB49: 900 | AC49: 30000 | AD49: 45000 | AE49: 0.00022648724 | AF49: Mostly self-funded | AG49: 466000 | AI49: 200000 | AJ49: N/A | AK49: Insufficient | AL49: Miniimal | AM49: High | AN49: Flawed democracy | AO49: Central gov. | AP49: Unprepared | AQ49: Inadequate | AR49: Limited scientific basis | AS49: Poor | AT49: Frequent | AU49: <6 Months | AV49: 3 | AW49: Same | AX49: =VLOOKUP(AW49,Metric_Codes!$C$91:$D$95,2,FALSE) -> 3 | AY49: Low | AZ49: 1-2 Years | BA49: 18 | BB49: Same | BC49: =VLOOKUP(BB49,Metric_Codes!$C$91:$D$95,2,FALSE) -> 3 | BD49: Same | BE49: =VLOOKUP(BD49,Metric_Codes!$C$91:$D$95,2,FALSE) -> 3 | BF49: =(BC49+BE49)/2 -> 3 | BG49: Low | BH49: Negligible | BI49: 9 | BJ49: rapid unregulated urban growth
A50: 49 | B50: 2011 Thailand Floods | C50: Thailand | D50: THA | E50: Flood | F50: Riverine Flood | G50: Climate | H50: 2011 | I50: Rainfall over n. Thailand 344% above mean; metres depth | J50: Extremely catastrophic damage | K50: Northern Thailand | L50: Regional | M50: 67530130 | N50: C: Service with Industry (service 50-67% and Industry >25%) | O50: Industry with Service | P50: 68.3 | Q50: Upper middle | R50: Stable | S50: 0.008 | T50: 5491.2 | U50: 13210 | V50: 0.636 | W50: 36.5 | X50: 36 | Y50: 0.01401686 | Z50: 60-80% | AA50: 45000000 | AB50: 813 | AD50: 9500000 | AE50: 0.14067795 | AF50: Mostly external | AG50: 1600000 | AH50: 16100000 | AI50: 10800000 | AJ50: >12 Months | AK50: Sufficient | AL50: Moderate | AM50: Medium | AN50: Hybrid regime | AO50: Central gov. | AP50: Unprepared | AQ50: Inadequate | AR50: Limited scientific basis | AS50: Poor | AT50: Occasional | AU50: 6-11 Months | AV50: 9 | AW50: Same | AX50: =VLOOKUP(AW50,Metric_Codes!$C$91:$D$95,2,FALSE) -> 3 | AY50: Low | AZ50: 1-2 Years | BA50: 18 | BB50: Same | BC50: =VLOOKUP(BB50,Metric_Codes!$C$91:$D$95,2,FALSE) -> 3 | BD50: Improved | BE50: =VLOOKUP(BD50,Metric_Codes!$C$91:$D$95,2,FALSE) -> 4 | BF50: =(BC50+BE50)/2 -> 3.5 | BG50: Low | BH50: Moderate | BI50: 7 | BJ50: charitable aid not international; <1% residential insurance cover; major change in perception ofnon-life insurance risk; new industrial parks badly hit; hydological mismanagement; flood waters released from Bhumiphol dam; period of acute political turmoil; lawsuit against government
A51: 50 | B51: 2013 North India Floods | C51: India | D51: IND | E51: Flood | F51: Riverine Flood | G51: Climate | H51: 2013 | I51: Assumption | J51: Extremely catastrophic damage | K51: Uttarakhand; North India | L51: Regional | M51: 1278562210 | N51: C: Service with Industry (service 50-67% and Industry >25%) | O51: Service-Oriented | P51: 55.2 | Q51: Lower middle | R51: Growing | S51: 6.4 | T51: 1452.2 | U51: 5190 | V51: 0.468 | W51: 35.7 | X51: 41 | Y51: 0.007045723 | Z51: 40-60% | AA51: 1100000 | AB51: 6054 | AD51: 504473 | AE51: 0.00039456273 | AF51: Self-funded | AG51: 140000 | AJ51: >12 Months | AK51: Insufficient | AL51: Miniimal | AM51: High | AN51: Full democracy | AO51: Central gov. | AP51: Unprepared | AQ51: Inadequate | AR51: Limited scientific basis | AS51: Poor | AT51: Occasional | AU51: 1-2 Years | AV51: 18 | AW51: Same | AX51: =VLOOKUP(AW51,Metric_Codes!$C$91:$D$95,2,FALSE) -> 3 | AY51: Low | AZ51: 3-5 Years | BA51: 36 | BB51: Same | BC51: =VLOOKUP(BB51,Metric_Codes!$C$91:$D$95,2,FALSE) -> 3 | BD51: Same | BE51: =VLOOKUP(BD51,Metric_Codes!$C$91:$D$95,2,FALSE) -> 3 | BF51: =(BC51+BE51)/2 -> 3 | BG51: Low | BH51: Negligible | BI51: 4 | BJ51: warning from India Meteorological Dept not widely disseminated
A52: 51 | B52: 2013 Philippines Floods | C52: Philippines | D52: PHL | E52: Flood | F52: Riverine Flood | G52: Climate | H52: 2013 | I52: Assumption | J52: Extremely catastrophic damage | K52: Manila; Luzon | L52: Regional | M52: 98481032 | N52: C: Service with Industry (service 50-67% and Industry >25%) | O52: Service-Oriented | P52: 63.8 | Q52: Lower middle | R52: Growing | S52: 0.071 | T52: 2760.3 | U52: 7930 | V52: 0.574 | W52: 40.1 | X52: 36 | Y52: 0.004640428 | Z52: 40-60% | AA52: 2190000 | AB52: 31 | AD52: 3096422 | AE52: 0.031441811 | AF52: Mostly self-funded | AJ52: >12 Months | AK52: Insufficient | AL52: Miniimal | AM52: High | AN52: Flawed democracy | AO52: Central gov. | AP52: Somewhat prepared | AQ52: Inadequate | AR52: Limited scientific basis | AS52: Poor | AT52: Frequent | AU52: <1 Month | AV52: 1 | AW52: Same | AX52: =VLOOKUP(AW52,Metric_Codes!$C$91:$D$95,2,FALSE) -> 3 | AY52: Medium | AZ52: <1 Month | BA52: 1 | BB52: Same | BC52: =VLOOKUP(BB52,Metric_Codes!$C$91:$D$95,2,FALSE) -> 3 | BD52: Same | BE52: =VLOOKUP(BD52,Metric_Codes!$C$91:$D$95,2,FALSE) -> 3 | BF52: =(BC52+BE52)/2 -> 3 | BG52: Medium | BH52: Negligible | BI52: 13 | BJ52: Monsoon rains/ tropical storms from mid-June culminating in Haiyan in November
A53: 52 | B53: 1937 Great Hong Kong typhoon | C53: China | D53: CHN | E53: Storm | F53: Tropical Cyclone | G53: Climate | H53: 1937 | I53: Max Gust 240 km/h | J53: Catastrophic damage | K53: Hong Kong | L53: Regional | M53: 667070000 | N53: C: Service with Industry (service 50-67% and Industry >25%) | O53: Mixed | P53: 67.3 | Q53: Upper middle | R53: Contracting | S53: -0.2727 | T53: 89.52 | U53: 990 | V53: 0.643 | W53: 38.6 | X53: 39 | Z53: 20-40% | AB53: 11000 | AE53: 0 | AF53: Self-funded | AK53: Totally insufficient | AL53: Miniimal | AM53: High | AN53: Authoritarian | AO53: Central gov. | AP53: Completely unprepared | AQ53: Inadequate | AR53: Limited scientific basis | AS53: Poor | AT53: Frequent | AU53: 1-2 Years | AV53: 18 | AW53: Same | AX53: =VLOOKUP(AW53,Metric_Codes!$C$91:$D$95,2,FALSE) -> 3 | AY53: Low | AZ53: 1-2 Years | BA53: 18 | BB53: Same | BC53: =VLOOKUP(BB53,Metric_Codes!$C$91:$D$95,2,FALSE) -> 3 | BD53: Same | BE53: =VLOOKUP(BD53,Metric_Codes!$C$91:$D$95,2,FALSE) -> 3 | BF53: =(BC53+BE53)/2 -> 3 | BG53: Low | BH53: Negligible | BI53: 7 | BJ53: Main loss to shipping, both large and small vessels
A54: 53 | B54: 1943 Chennai (Madras) flood or Rajputana flood (less severe) | C54: India | D54: IND | E54: Flood | F54: Riverine Flood | G54: Climate | H54: 1943 | I54: Assumption | J54: Severe damage | K54: Madras (Chennai) | L54: Local | M54: 449480608 | N54: C: Service with Industry (service 50-67% and Industry >25%) | O54: Service-Oriented | P54: 55.2 | Q54: Lower middle | R54: Growing | S54: 0.0372 | T54: 81.28 | U54: 1120 | V54: 0.468 | W54: 35.7 | X54: 41 | Z54: 20-40% | AB54: 5000 | AE54: 0 | AF54: Self-funded | AK54: Totally insufficient | AL54: Miniimal | AM54: High | AN54: Full democracy | AO54: Central gov. | AP54: Completely unprepared | AQ54: Inadequate | AR54: Limited scientific basis | AS54: Very poor | AT54: Frequent | AU54: <6 Months | AV54: 3 | AW54: Same | AX54: =VLOOKUP(AW54,Metric_Codes!$C$91:$D$95,2,FALSE) -> 3 | AY54: Low | AZ54: 6-11 Months | BA54: 9 | BB54: Same | BC54: =VLOOKUP(BB54,Metric_Codes!$C$91:$D$95,2,FALSE) -> 3 | BD54: Same | BE54: =VLOOKUP(BD54,Metric_Codes!$C$91:$D$95,2,FALSE) -> 3 | BF54: =(BC54+BE54)/2 -> 3 | BG54: Low | BH54: Negligible | BI54: 2 | BJ54: Followed by Great Bengal famine
A55: 54 | B55: 1985 Typhoon Cecil (Rubing) | C55: Vietnam | D55: VNM | E55: Storm | F55: Tropical Cyclone | G55: Climate | H55: 1985 | I55: CAT 3 | J55: Severe damage | L55: Regional | M55: 61049373 | N55: F: Industry with Service (Industry and Service both 33-50%) | O55: Industry with Service | P55: 55.3 | Q55: Lower middle | R55: Growing | S55: 0.038 | T55: 230.9 | U55: 880 | V55: 0.574 | W55: 35.3 | X55: 33 | Y55: 0 | Z55: 40-60% | AA55: 65000 | AB55: 798 | AC55: 225000 | AD55: 450257 | AE55: 0.0073752928 | AF55: Mostly self-funded | AK55: Insufficient | AL55: Miniimal | AM55: High | AN55: Authoritarian | AO55: Central gov. | AP55: Somewhat prepared | AQ55: Inadequate | AR55: Limited scientific basis | AS55: Mediocre | AT55: Frequent | AU55: 1-2 Years | AV55: 18 | AW55: Same | AX55: =VLOOKUP(AW55,Metric_Codes!$C$91:$D$95,2,FALSE) -> 3 | AY55: Low | AZ55: 1-2 Years | BA55: 18 | BB55: Same | BC55: =VLOOKUP(BB55,Metric_Codes!$C$91:$D$95,2,FALSE) -> 3 | BD55: Same | BE55: =VLOOKUP(BD55,Metric_Codes!$C$91:$D$95,2,FALSE) -> 3 | BF55: =(BC55+BE55)/2 -> 3 | BG55: Low | BH55: Negligible | BI55: 1 | BJ55: Recovering and restructuring after Vietnam war and war with China, state control of industry and business
A56: 55 | B56: 1975 Typhoon Nina (Bebeng) | C56: China | D56: CHN | E56: Storm | F56: Tropical Cyclone | G56: Climate | H56: 1975 | I56: CAT 3 | J56: Severe damage | K56: Huai river basin | L56: Regional | M56: 916395000 | N56: C: Service with Industry (service 50-67% and Industry >25%) | O56: Mixed | P56: 67.3 | Q56: Upper middle | R56: Growing | S56: 0.087 | T56: 178.3 | U56: 990 | V56: 0.643 | W56: 38.6 | X56: 39 | Y56: <0.05% | Z56: 60-80% | AA56: 1200000 | AB56: 171000 | AD56: 11000000 | AE56: 0.012003557 | AF56: Mostly self-funded | AJ56: <12 Months | AK56: Insufficient | AL56: Miniimal | AM56: High | AN56: Authoritarian | AO56: Central gov. | AP56: Completely unprepared | AQ56: Inadequate | AR56: Limited scientific basis | AS56: Mediocre | AT56: Frequent | AU56: 3-5 Years | AV56: 48 | AW56: Improved | AX56: =VLOOKUP(AW56,Metric_Codes!$C$91:$D$95,2,FALSE) -> 4 | AY56: Low | AZ56: 3-5 Years | BA56: 48 | BB56: Same | BC56: =VLOOKUP(BB56,Metric_Codes!$C$91:$D$95,2,FALSE) -> 3 | BD56: Improved | BE56: =VLOOKUP(BD56,Metric_Codes!$C$91:$D$95,2,FALSE) -> 4 | BF56: =(BC56+BE56)/2 -> 3.5 | BG56: Low | BH56: Negligible | BI56: 4 | BJ56: Torrential rain caused 62 dam failures, including Banqiao dam. Causing main loss of life and economic damage.
A57: 56 | B57: 1977 Andhra Pradesh Cyclone (Devi Taluk ) | C57: India | D57: IND | E57: Storm | F57: Tropical Cyclone | G57: Climate | H57: 1977 | I57: CAT 4 | J57: Catastrophic damage | K57: Krishna River delta; Avanigadda | L57: Regional | M57: 650485030 | N57: C: Service with Industry (service 50-67% and Industry >25%) | O57: Service-Oriented | P57: 55.2 | Q57: Lower middle | R57: Growing | S57: 0.073 | T57: 184.3 | U57: 1120 | V57: 0.468 | W57: 35.7 | X57: 41 | Y57: ~0.3 | Z57: 60-80% | AA57: 498535 | AB57: 14204 | AC57: 5432400 | AD57: 14469800 | AE57: 0.022244632 | AF57: Self-funded | AK57: Insufficient | AL57: Miniimal | AM57: High | AN57: Full democracy | AO57: Central gov. | AP57: Completely unprepared | AQ57: Inadequate | AR57: Limited scientific basis | AS57: Very poor | AT57: Major | AU57: 1-2 Years | AV57: 18 | AW57: Same | AX57: =VLOOKUP(AW57,Metric_Codes!$C$91:$D$95,2,FALSE) -> 3 | AY57: Low | AZ57: 1-2 Years | BA57: 18 | BB57: Same | BC57: =VLOOKUP(BB57,Metric_Codes!$C$91:$D$95,2,FALSE) -> 3 | BD57: Improved | BE57: =VLOOKUP(BD57,Metric_Codes!$C$91:$D$95,2,FALSE) -> 4 | BF57: =(BC57+BE57)/2 -> 3.5 | BG57: Low | BH57: Negligible | BI57: 8 | BJ57: Overwhelming loss of life; Government failure to act swiftly and effectively; big international aid effort; cover up; 5 ministers resigned; evidence of corruption
A58: 57 | B58: 1989 Hurricane Hugo | C58: United States | D58: USA | E58: Storm | F58: Tropical Cyclone | G58: Climate | H58: 1989 | I58: CAT 4 | J58: Catastrophic damage | K58: South Carolina, Charlestown | L58: Regional | M58: 246819000 | N58: A: Service-Dominated Economy (more than 75% of economy based on services) | O58: Service-Oriented | P58: 76.8 | Q58: High | R58: Growing | S58: 0.037 | T58: 22922.4 | U58: 23730 | V58: 0.797 | W58: 41.5 | X58: 71 | Y58: 0.05061626 | Z58: 40-60% | AA58: 7000000 | AB58: 51 | AC58: 25000 | AD58: 25000 | AE58: 0.0001012888 | AF58: Equal | AI58: 4200000 | AJ58: >12 Months | AK58: Sufficient | AL58: Major | AM58: High | AN58: Full democracy | AO58: Specialised gov. agency | AP58: Somewhat prepared | AQ58: Adequate | AR58: Established scientific basis | AS58: Poor | AT58: Occasional | AU58: 3-5 Years | AV58: 48 | AW58: Same | AX58: =VLOOKUP(AW58,Metric_Codes!$C$91:$D$95,2,FALSE) -> 3 | AY58: Low | AZ58: 3-5 Years | BA58: 48 | BB58: Same | BC58: =VLOOKUP(BB58,Metric_Codes!$C$91:$D$95,2,FALSE) -> 3 | BD58: Improved | BE58: =VLOOKUP(BD58,Metric_Codes!$C$91:$D$95,2,FALSE) -> 4 | BF58: =(BC58+BE58)/2 -> 3.5 | BG58: Low | BH58: Important | BI58: 11 | BJ58: Further $3 billion loss in Caribbean; FEMA heavily criticised for bureaucratic incompetence; significant improvement in building codes and preparedness post disaster
A59: 58 | B59: 1990 Storm Daria (Burns' Day Storm) | C59: United Kingdom | D59: GBR | E59: Storm | F59: Extratropical Cyclone | G59: Climate | H59: 1990 | I59: Max Gust 172 km/h | J59: Moderate damage | K59: Extensive across UK | L59: National | M59: 57247586 | N59: A: Service-Dominated Economy (more than 75% of economy based on services) | O59: Service-Oriented | P59: 78.9 | Q59: High | R59: Stable | S59: 0.007 | T59: 19095.5 | U59: 16990 | V59: 0.835 | W59: 33.2 | X59: 80 | Y59: 0.0297331 | Z59: 20-40% | AA59: 3400000 | AB59: 47 | AD59: 1000000 | AE59: 0.017467985 | AF59: Mostly external | AI59: 2500000 | AJ59: <12 Months | AK59: Sufficient | AL59: Major | AM59: High | AN59: Full democracy | AO59: Central gov. | AP59: Well prepared | AQ59: Adequate | AR59: Established scientific basis | AS59: Good | AT59: Occasional | AU59: 6-11 Months | AV59: 9 | AW59: Same | AX59: =VLOOKUP(AW59,Metric_Codes!$C$91:$D$95,2,FALSE) -> 3 | AY59: Low | AZ59: 1-2 Years | BA59: 18 | BB59: Same | BC59: =VLOOKUP(BB59,Metric_Codes!$C$91:$D$95,2,FALSE) -> 3 | BD59: Same | BE59: =VLOOKUP(BD59,Metric_Codes!$C$91:$D$95,2,FALSE) -> 3 | BF59: =(BC59+BE59)/2 -> 3 | BG59: Low | BH59: Important | BI59: 4 | BJ59: Wet snow
A60: 59 | B60: 1991 Typhoon Mireille (Rosing) | C60: Japan | D60: JPN | E60: Storm | F60: Tropical Cyclone | G60: Climate | H60: 1991 | I60: CAT 4 | J60: Catastrophic damage | K60: Extensive across Japan | L60: National | M60: 123921000 | N60: B: Service-Oriented Economy (67-75% of economy based on services) | O60: Service-Oriented | P60: 72.1 | Q60: High | R60: Growing | S60: 0.034 | T60: 28925 | U60: 20880 | V60: 0.876 | W60: 32.1 | X60: 73 | Y60: 0.02421038 | Z60: 40-60% | AA60: 10000000 | AB60: 66 | AC60: 351 | AD60: 91128 | AE60: 0.00073537173 | AF60: Equal | AI60: 6000000 | AJ60: <12 Months | AK60: Sufficient | AL60: Moderate | AM60: Medium | AN60: Full democracy | AO60: Specialised gov. agency | AP60: Well prepared | AQ60: Adequate | AR60: Established scientific basis | AS60: Good | AT60: Frequent | AU60: 1-2 Years | AV60: 18 | AW60: Same | AX60: =VLOOKUP(AW60,Metric_Codes!$C$91:$D$95,2,FALSE) -> 3 | AY60: Low | AZ60: 1-2 Years | BA60: 18 | BB60: Same | BC60: =VLOOKUP(BB60,Metric_Codes!$C$91:$D$95,2,FALSE) -> 3 | BD60: Improved | BE60: =VLOOKUP(BD60,Metric_Codes!$C$91:$D$95,2,FALSE) -> 4 | BF60: =(BC60+BE60)/2 -> 3.5 | BG60: Low | BH60: Small | BI60: 2 | BJ60: Costliest typhoon on record. Also hit Philippines
A61: 60 | B61: 1991 Bangladesh Cyclone | C61: Bangladesh | D61: BGD | E61: Storm | F61: Tropical Cyclone | G61: Climate | H61: 1991 | I61: CAT 5 | J61: Extremely catastrophic damage | K61: SE Coast | L61: Regional | M61: 108727432 | O61: Mixed | P61: 55.6 | Q61: Lower middle | R61: Growing | S61: 0.035 | T61: 284.7 | U61: 890 | V61: 0.462 | W61: 32.4 | X61: 26 | Y61: 0.001498652 | Z61: 60-80% | AA61: 1780000 | AB61: 138866 | AC61: 300000 | AD61: 15438849 | AE61: 0.14199589 | AF61: Self-funded | AK61: Totally insufficient | AL61: Miniimal | AM61: High | AN61: Hybrid regime | AO61: Central gov. | AP61: Unprepared | AQ61: Inadequate | AR61: Limited scientific basis | AS61: Poor | AT61: Frequent | AU61: 1-2 Years | AV61: 18 | AW61: Same | AX61: =VLOOKUP(AW61,Metric_Codes!$C$91:$D$95,2,FALSE) -> 3 | AY61: Low | AZ61: 6-11 Months | BA61: 9 | BB61: Same | BC61: =VLOOKUP(BB61,Metric_Codes!$C$91:$D$95,2,FALSE) -> 3 | BD61: Improved | BE61: =VLOOKUP(BD61,Metric_Codes!$C$91:$D$95,2,FALSE) -> 4 | BF61: =(BC61+BE61)/2 -> 3.5 | BG61: Low | BH61: Negligible | BI61: 3 | BJ61: Extreme high tide 5.5m above norma and 6m storm surge; land washed away; big impact on agriculture and fisheries; improved warning and reforestation; US lead Operation Sea Angel 1 month
A62: 61 | B62: 1992 Hurricane Andrew | C62: United States | D62: USA | E62: Storm | F62: Tropical Cyclone | G62: Climate | H62: 1992 | I62: CAT 5 | J62: Extremely catastrophic damage | K62: S Florida; Louisiana | L62: Regional | M62: 256514000 | N62: A: Service-Dominated Economy (more than 75% of economy based on services) | O62: Service-Oriented | P62: 76.8 | Q62: High | R62: Growing | S62: 0.036 | T62: 25493 | U62: 25180 | V62: 0.797 | W62: 41.5 | X62: 71 | Y62: 0.04895889 | Z62: 40-60% | AA62: 26500000 | AB62: 44 | AC62: 250000 | AD62: 250055 | AE62: 0.00097482009 | AF62: Equal | AG62: 11100000 | AI62: 27300000 | AJ62: >12 Months | AK62: Sufficient | AL62: Major | AM62: High | AN62: Full democracy | AO62: Central gov. | AP62: Somewhat prepared | AQ62: Adequate | AR62: Established scientific basis | AS62: Poor | AT62: Frequent | AU62: 1-2 Years | AV62: 18 | AW62: Same | AX62: =VLOOKUP(AW62,Metric_Codes!$C$91:$D$95,2,FALSE) -> 3 | AY62: Low | AZ62: 1-2 Years | BA62: 18 | BB62: Same | BC62: =VLOOKUP(BB62,Metric_Codes!$C$91:$D$95,2,FALSE) -> 3 | BD62: Improved | BE62: =VLOOKUP(BD62,Metric_Codes!$C$91:$D$95,2,FALSE) -> 4 | BF62: =(BC62+BE62)/2 -> 3.5 | BG62: Low | BH62: Important | BI62: 4 | BJ62: Local and State Govt overwhelmed; Criticism of FEMA; Damage caused by faulty construction; 1 day warning; Improved building codes - storm shutters or impct resistant glass; Burmese python escapees populate Everglades
A63: 62 | B63: 1993 Tropical Storm Bret | C63: Venezuela, RB | D63: VEN | E63: Storm | F63: Tropical Cyclone | G63: Climate | H63: 1993 | I63: Max Gust 95 km/h | J63: Minor damage | K63: Barinas State; Caracas | L63: Regional | M63: 21263443 | N63: C: Service with Industry (service 50-67% and Industry >25%) | O63: Service-Oriented | P63: 25.9 | Q63: Upper middle | R63: Stable | S63: 0.003 | T63: 2824.8 | U63: 10700 | V63: 0.636 | W63: 46.9 | X63: 18 | Y63: 0.02418856 | Z63: 20-40% | AA63: 25000 | AB63: 173 | AC63: 11000 | AE63: #VALUE! | AF63: Self-funded | AH63: 543 | AK63: Insufficient | AL63: Miniimal | AM63: High | AN63: Authoritarian | AO63: Central gov. | AP63: Unprepared | AQ63: Inadequate | AR63: Limited scientific basis | AS63: Poor | AT63: Occasional | AU63: 6-11 Months | AV63: 9 | AW63: Same | AX63: =VLOOKUP(AW63,Metric_Codes!$C$91:$D$95,2,FALSE) -> 3 | AY63: Low | AZ63: 6-11 Months | BA63: 9 | BB63: Same | BC63: =VLOOKUP(BB63,Metric_Codes!$C$91:$D$95,2,FALSE) -> 3 | BD63: Same | BE63: =VLOOKUP(BD63,Metric_Codes!$C$91:$D$95,2,FALSE) -> 3 | BF63: =(BC63+BE63)/2 -> 3 | BG63: Low | BH63: Negligible | BI63: 2 | BJ63: Heavy rainfall, flooding and mudslides most destructive;
A64: 63 | B64: 1999 Cyclones Lothar and Martin | C64: France | D64: FRA | E64: Storm | F64: Tropical Cyclone | G64: Climate | H64: 1999 | I64: Max Gust 150-200 km/h | J64: Severe damage | K64: Western and central Europe | L64: National | M64: 60496718 | N64: A: Service-Dominated Economy (more than 75% of economy based on services) | O64: Service-Oriented | P64: 63.8 | Q64: High | R64: Growing | S64: 0.034 | T64: 24673.2 | U64: 24930 | V64: 0.808 | W64: 32.3 | X64: 72 | Y64: 0.0274193 | Z64: 0-20% | AA64: 8000000 | AB64: 88 | AD64: 3400011 | AE64: 0.056201578 | AF64: Mostly external | AI64: 6500000 | AJ64: <12 Months | AK64: Sufficient | AL64: Major | AM64: High | AN64: Full democracy | AO64: Central gov. | AP64: Well prepared | AQ64: Adequate | AR64: Established scientific basis | AS64: Good | AT64: Occasional | AU64: <6 Months | AV64: 3 | AW64: Same | AX64: =VLOOKUP(AW64,Metric_Codes!$C$91:$D$95,2,FALSE) -> 3 | AY64: Low | AZ64: 6-11 Months | BA64: 6 | BB64: Same | BC64: =VLOOKUP(BB64,Metric_Codes!$C$91:$D$95,2,FALSE) -> 3 | BD64: Same | BE64: =VLOOKUP(BD64,Metric_Codes!$C$91:$D$95,2,FALSE) -> 3 | BF64: =(BC64+BE64)/2 -> 3 | BG64: Low | BH64: Important | BI64: 9 | BJ64: Major energy outage; devastated forests; clustering of various storms
A65: 64 | B65: 1999 Hurricane Floyd | C65: United States | D65: USA | E65: Storm | F65: Tropical Cyclone | G65: Climate | H65: 1999 | I65: CAT 4 | J65: Catastrophic damage | K65: Bahamas, Eastern seaboard USA, N Carolina | L65: Regional | M65: 279040000 | N65: A: Service-Dominated Economy (more than 75% of economy based on services) | O65: Service-Oriented | P65: 76.8 | Q65: High | R65: Growing | S65: 0.047 | T65: 34620.9 | U65: 34850 | V65: 0.797 | W65: 41.5 | X65: 71 | Y65: 0.0420686 | Z65: 20-40% | AA65: 7000000 | AB65: 70 | AD65: 3000010 | AE65: 0.010751183 | AF65: Equal | AG65: 4433000 | AH65: 459000 | AI65: 2200000 | AJ65: >12 Months | AK65: Sufficient | AL65: Major | AM65: High | AN65: Full democracy | AO65: Specialised gov. agency | AP65: Well prepared | AQ65: Adequate | AR65: Established scientific basis | AS65: Good | AT65: Frequent | AU65: <6 Months | AV65: 3 | AW65: Same | AX65: =VLOOKUP(AW65,Metric_Codes!$C$91:$D$95,2,FALSE) -> 3 | AY65: Low | AZ65: 6-11 Months | BA65: 6 | BB65: Same | BC65: =VLOOKUP(BB65,Metric_Codes!$C$91:$D$95,2,FALSE) -> 3 | BD65: Improved | BE65: =VLOOKUP(BD65,Metric_Codes!$C$91:$D$95,2,FALSE) -> 4 | BF65: =(BC65+BE65)/2 -> 3.5 | BG65: Low | BH65: Important | BI65: 10 | BJ65: Torrential rain and flooding; FEMA criticised for slow response; but increased awareness, better hazard mapping, insurance, provision for vulnerable
A66: 65 | B66: 1999 Typhoon Bart (Oniang) | C66: Japan | D66: JPN | E66: Storm | F66: Tropical Cyclone | G66: Climate | H66: 1999 | I66: CAT 5 | J66: Extremely catastrophic damage | K66: Kumamoto Prefecture on Ky?sh? | L66: Regional | M66: 126631000 | N66: B: Service-Oriented Economy (67-75% of economy based on services) | O66: Service-Oriented | P66: 72.1 | Q66: High | R66: Contracting | S66: -0.003 | T66: 36026.6 | U66: 25630 | V66: 0.876 | W66: 32.1 | X66: 73 | Y66: 0.02258906 | Z66: 20-40% | AA66: 5000000 | AB66: 26 | AC66: 6900 | AD66: 27338 | AE66: 0.00021588711 | AF66: Equal | AI66: 3500000 | AJ66: <12 Months | AK66: Sufficient | AL66: Moderate | AM66: Medium | AN66: Full democracy | AO66: Specialised gov. agency | AP66: Well prepared | AQ66: Adequate | AR66: Established scientific basis | AS66: Good | AT66: Frequent | AU66: <6 Months | AV66: 3 | AW66: Same | AX66: =VLOOKUP(AW66,Metric_Codes!$C$91:$D$95,2,FALSE) -> 3 | AY66: Low | AZ66: 6-11 Months | BA66: 9 | BB66: Same | BC66: =VLOOKUP(BB66,Metric_Codes!$C$91:$D$95,2,FALSE) -> 3 | BD66: Same | BE66: =VLOOKUP(BD66,Metric_Codes!$C$91:$D$95,2,FALSE) -> 3 | BF66: =(BC66+BE66)/2 -> 3 | BG66: Low | BH66: Small | BI66: 2 | BJ66: Known in Philippines as Oniang, Kadena Air Base was badly damaged; Heavy flooding and landslides
A67: 66 | B67: 1999 Cyclone Anatol | C67: Denmark | D67: DNK | E67: Storm | F67: Tropical Cyclone | G67: Climate | H67: 1999 | I67: Max Gust 184 km/h | J67: Severe damage | K67: Denmark, N Germany, Hamburg, Schleswig-Holstein | L67: National | M67: 5321799 | N67: A: Service-Dominated Economy (more than 75% of economy based on services) | O67: Service-Dominated | P67: 76.7 | Q67: High | R67: Growing | S67: 0.029 | T67: 33440.8 | U67: 26430 | V67: 0.86 | W67: 28.2 | X67: 88 | Y67: 0.02280509 | Z67: 0-20% | AA67: 3000000 | AB67: 20 | AE67: #VALUE! | AF67: Mostly external | AI67: 2000000 | AJ67: <12 Months | AK67: Sufficient | AL67: Major | AM67: High | AN67: Full democracy | AO67: Central gov. | AP67: Well prepared | AQ67: Adequate | AR67: Established scientific basis | AS67: Good | AT67: Infrequent | AU67: <6 Months | AV67: 3 | AW67: Same | AX67: =VLOOKUP(AW67,Metric_Codes!$C$91:$D$95,2,FALSE) -> 3 | AY67: Low | AZ67: 6-11 Months | BA67: 6 | BB67: Same | BC67: =VLOOKUP(BB67,Metric_Codes!$C$91:$D$95,2,FALSE) -> 3 | BD67: Same | BE67: =VLOOKUP(BD67,Metric_Codes!$C$91:$D$95,2,FALSE) -> 3 | BF67: =(BC67+BE67)/2 -> 3 | BG67: Low | BH67: Important | BI67: 2 | BJ67: One of series of 3 storms
A68: 67 | B68: 2000 Typhoon Prapiroon (Lusing) | C68: Korea, Dem. People's Rep. | D68: PRK | E68: Storm | F68: Tropical Cyclone | G68: Climate | H68: 2000 | I68: CAT 1 | J68: Minor damage | L68: National | M68: 22929075 | O68: Service-Dominated | P68: 5.9 | Q68: Low | R68: Contracting | X68: 14 | Y68: 0.02544235 | Z68: 40-60% | AA68: 6000000 | AB68: 46 | AC68: 147000 | AD68: 627180 | AE68: 0.027353044 | AF68: Self-funded | AK68: Insufficient | AL68: Miniimal | AM68: High | AN68: Authoritarian | AO68: Central gov. | AP68: Completely unprepared | AQ68: Inadequate | AR68: Limited scientific basis | AT68: Occasional | BH68: Negligible | BI68: 0 | BJ68: NOT ABLE TO FIND INFO
A69: 68 | B69: 2004 Hurricane Jeanne | C69: Haiti | D69: HTI | E69: Storm | F69: Tropical Cyclone | G69: Climate | H69: 2004 | I69: CAT 3 | J69: Severe damage | K69: Gonaives | L69: National | M69: 9119178 | O69: Service-Oriented | P69: 52.7 | Q69: Low | R69: Contracting | S69: -0.035 | T69: 387.9 | U69: 1340 | V69: 0.304 | W69: 41.1 | X69: 20 | Y69: 0 | Z69: 40-60% | AA69: 50000 | AB69: 3006 | AC69: 250000 | AD69: 315594 | AE69: 0.034607725 | AF69: Mostly self-funded | AH69: 2046 | AK69: Totally insufficient | AL69: Miniimal | AM69: High | AN69: Hybrid regime | AO69: None | AP69: Completely unprepared | AQ69: Inadequate | AR69: No scientific basis | AS69: Very poor | AT69: Occasional | AU69: 1-2 Years | AV69: 18 | AW69: Same | AX69: =VLOOKUP(AW69,Metric_Codes!$C$91:$D$95,2,FALSE) -> 3 | AY69: Low | AZ69: 3-5 Years | BA69: 36 | BB69: Same | BC69: =VLOOKUP(BB69,Metric_Codes!$C$91:$D$95,2,FALSE) -> 3 | BD69: Same | BE69: =VLOOKUP(BD69,Metric_Codes!$C$91:$D$95,2,FALSE) -> 3 | BF69: =(BC69+BE69)/2 -> 3 | BG69: Low | BH69: Negligible | BI69: 9 | BJ69: Severe rainfall, mudslides aggravated by deforestation; Also hit Caribbean and USA
A70: 69 | B70: 2008 Cyclone Nargis | C70: Myanmar | D70: MMR | E70: Storm | F70: Tropical Cyclone | G70: Climate | H70: 2008 | I70: CAT 4 | J70: Catastrophic damage | K70: Irrawaddy Delta, Labutta Town | L70: Regional | M70: 49479752 | O70: Service-Oriented | P70: 53.6 | Q70: Lower middle | R70: Growing | S70: 0.103 | T70: 644 | U70: 2990 | V70: 0.466 | W70: 38.1 | X70: 29 | Y70: 0 | Z70: 60-80% | AA70: 12900000 | AB70: 138366 | AD70: 2420000 | AE70: 0.048908895 | AF70: Self-funded | AK70: Insufficient | AL70: Miniimal | AM70: High | AN70: Authoritarian | AO70: Central gov. | AP70: Completely unprepared | AQ70: Inadequate | AR70: Limited scientific basis | AS70: Very poor | AT70: Frequent | AU70: 1-2 Years | AV70: 18 | AW70: Same | AX70: =VLOOKUP(AW70,Metric_Codes!$C$91:$D$95,2,FALSE) -> 3 | AY70: Low | AZ70: 3-5 Years | BA70: 36 | BB70: Same | BC70: =VLOOKUP(BB70,Metric_Codes!$C$91:$D$95,2,FALSE) -> 3 | BD70: Same | BE70: =VLOOKUP(BD70,Metric_Codes!$C$91:$D$95,2,FALSE) -> 3 | BF70: =(BC70+BE70)/2 -> 3 | BG70: Low | BH70: Negligible | BI70: 9 | BJ70: Probably more than 138000 deaths; Relief affected by Sichuan earthquake 3 months later; Relief hampered by actions of miltary junta
A71: 70 | B71: 2009 Cyclone Klaus | C71: Spain | D71: ESP | E71: Storm | F71: Tropical Cyclone | G71: Climate | H71: 2009 | I71: Max Gust 216 km/h | J71: Catastrophic damage | K71: Santander, Bilboa, Barcelona, Alicante | L71: Regional | M71: 46362946 | N71: A: Service-Dominated Economy (more than 75% of economy based on services) | O71: Industry with Service | P71: 65.7 | Q71: High | R71: Contracting | S71: -0.036 | T71: 32334 | U71: 31790 | V71: 0.754 | W71: 36.2 | X71: 58 | Y71: 0.02862988 | Z71: 0-20% | AA71: 1900000 | AB71: 14 | AE71: #VALUE! | AF71: Equal | AI71: 1500000 | AJ71: >12 Months | AK71: Sufficient | AL71: Moderate | AM71: Medium | AN71: Full democracy | AO71: Central gov. | AP71: Well prepared | AQ71: Adequate | AR71: Established scientific basis | AS71: Good | AT71: Infrequent | AU71: 6-11 Months | AV71: 9 | AW71: Same | AX71: =VLOOKUP(AW71,Metric_Codes!$C$91:$D$95,2,FALSE) -> 3 | AY71: Low | AZ71: 1-2 Years | BA71: 18 | BB71: Same | BC71: =VLOOKUP(BB71,Metric_Codes!$C$91:$D$95,2,FALSE) -> 3 | BD71: Same | BE71: =VLOOKUP(BD71,Metric_Codes!$C$91:$D$95,2,FALSE) -> 3 | BF71: =(BC71+BE71)/2 -> 3 | BG71: Low | BH71: Moderate | BI71: 7 | BJ71: Strong winds, freak 28m waves at Santander; Widespread, also affected France and italy; new island emerged at Royan; economic recovery complicated by 2008 crash
A72: 71 | B72: 2009 Typhoon Morakot (Kiko) | C72: Taiwan, China | D72: TWN | E72: Storm | F72: Tropical Cyclone | G72: Climate | H72: 2009 | I72: CAT 1 | J72: Minor damage | K72: Southern Region | L72: Regional | M72: 22974350 | N72: Sectoral GDP missing/incomplete | O72: Service-Oriented | P72: 77.3 | Q72: High | R72: Contracting | S72: -0.016 | T72: 16960 | U72: 17531 | V72: - | W72: 46.5 | X72: 63 | Y72: 0.03023565 | Z72: 40-60% | AA72: 3300000 | AB72: 673 | AD72: 2307523 | AE72: 0.1004391 | AF72: Self-funded | AI72: 91000 | AJ72: >12 Months | AK72: Insufficient | AL72: Miniimal | AM72: High | AN72: Flawed democracy | AO72: Central gov. | AP72: Unprepared | AQ72: Inadequate | AR72: Established scientific basis | AS72: Mediocre | AT72: Frequent | AU72: 1-2 Years | AV72: 18 | AW72: Same | AX72: =VLOOKUP(AW72,Metric_Codes!$C$91:$D$95,2,FALSE) -> 3 | AY72: Low | AZ72: 1-2 Years | BA72: 18 | BB72: Same | BC72: =VLOOKUP(BB72,Metric_Codes!$C$91:$D$95,2,FALSE) -> 3 | BD72: Same | BE72: =VLOOKUP(BD72,Metric_Codes!$C$91:$D$95,2,FALSE) -> 3 | BF72: =(BC72+BE72)/2 -> 3 | BG72: Low | BH72: Negligible | BI72: 2 | BJ72: Worse disaster in 50 years; Severe flooding; slow response; also hit Philippines; led to improvements in disaster management
A73: 72 | B73: 2010 Cyclone Xynthia | C73: France | D73: FRA | E73: Storm | F73: Tropical Cyclone | G73: Climate | H73: 2010 | I73: Max Gust 228 km/h | J73: Catastrophic damage | K73: NW coast | L73: Regional | M73: 65027507 | N73: A: Service-Dominated Economy (more than 75% of economy based on services) | O73: Service-Oriented | P73: 63.8 | Q73: High | R73: Stable | S73: 0.02 | T73: 40638.3 | U73: 36730 | V73: 0.808 | W73: 32.3 | X73: 72 | Y73: 0.03079843 | Z73: 0-20% | AA73: 4230000 | AB73: 53 | AD73: 500079 | AE73: 0.0076902687 | AF73: Mostly external | AI73: 1320000 | AJ73: <12 Months | AK73: Sufficient | AL73: Major | AM73: High | AN73: Full democracy | AO73: Central gov. | AP73: Well prepared | AQ73: Adequate | AR73: Established scientific basis | AS73: Good | AT73: Occasional | AU73: 6-11 Months | AV73: 9 | AW73: Same | AX73: =VLOOKUP(AW73,Metric_Codes!$C$91:$D$95,2,FALSE) -> 3 | AY73: Low | AZ73: 1-2 Years | BA73: 18 | BB73: Same | BC73: =VLOOKUP(BB73,Metric_Codes!$C$91:$D$95,2,FALSE) -> 3 | BD73: Improved | BE73: =VLOOKUP(BD73,Metric_Codes!$C$91:$D$95,2,FALSE) -> 4 | BF73: =(BC73+BE73)/2 -> 3.5 | BG73: Low | BH73: Important | BI73: 12 | BJ73: Flooding along Atlantic and Channel coast; Storm protection shutters trapped people in flooded homes; Mayor and Deputy imprisoned for granting permission for development in flood hazard zone; French Government decided to destroy 1,510 houses in the affected areas
A74: 73 | B74: 1906 Ecuador–Colombia earthquake | C74: Ecuador | D74: ECU | E74: Earthquake | F74: Earthquake | G74: Geophysical | H74: 1906 | I74: 8.8 Muk | J74: Extremely catastrophic damage | K74: Coast Colombia-Ecuador border | L74: Regional | M74: 4545550 | N74: C: Service with Industry (service 50-67% and Industry >25%) | O74: Service-Oriented | P74: 46.9 | Q74: Upper middle | R74: Growing | S74: 0.0512 | T74: 455.27 | U74: 4450 | V74: 0.603 | W74: 44.7 | X74: 34 | Z74: 20-40% | AA74: 3000 | AB74: 1000 | AE74: #VALUE! | AF74: Self-funded | AK74: Totally insufficient | AL74: Miniimal | AM74: High | AN74: Flawed democracy | AO74: Central gov. | AP74: Unprepared | AQ74: Inadequate | AR74: Limited scientific basis | AS74: Poor | AT74: Frequent | AU74: 3-5 Years | AV74: 48 | AW74: Same | AX74: =VLOOKUP(AW74,Metric_Codes!$C$91:$D$95,2,FALSE) -> 3 | AY74: Low | AZ74: 3-5 Years | BA74: 48 | BB74: Same | BC74: =VLOOKUP(BB74,Metric_Codes!$C$91:$D$95,2,FALSE) -> 3 | BD74: Improved | BE74: =VLOOKUP(BD74,Metric_Codes!$C$91:$D$95,2,FALSE) -> 4 | BF74: =(BC74+BE74)/2 -> 3.5 | BG74: Low | BH74: Negligible | BI74: 7 | BJ74: Tsunami waves (3) arrived 12.5 hours after earthquake;
A75: 74 | B75: 1908 Messina earthquake | C75: Italy | D75: ITA | E75: Earthquake & Tsunami | F75: Earthquake & Tsunami | G75: Geophysical | H75: 1908 | I75: 7.5 Ms | J75: Catastrophic damage | K75: Messina | L75: Regional | M75: 50199700 | N75: A: Service-Dominated Economy (more than 75% of economy based on services) | O75: Industry-Oriented | P75: 62.2 | Q75: High | R75: Growing | S75: 0.0821 | T75: 804.49 | U75: 18330 | V75: 0.771 | W75: 35.4 | X75: 52 | Z75: 60-80% | AA75: 116000 | AB75: 75000 | AD75: 150000 | AE75: 0.0029880657 | AF75: Self-funded | AK75: Insufficient | AL75: Miniimal | AM75: High | AN75: Flawed democracy | AO75: None | AP75: Completely unprepared | AQ75: Adequate | AR75: Limited scientific basis | AS75: Poor | AT75: Frequent | AU75: 11-20 Years | AV75: 180 | AW75: Worse | AX75: =VLOOKUP(AW75,Metric_Codes!$C$91:$D$95,2,FALSE) -> 2 | AY75: Low | AZ75: 11-20 Years | BA75: 180 | BB75: Worse | BC75: =VLOOKUP(BB75,Metric_Codes!$C$91:$D$95,2,FALSE) -> 2 | BD75: Improved | BE75: =VLOOKUP(BD75,Metric_Codes!$C$91:$D$95,2,FALSE) -> 4 | BF75: =(BC75+BE75)/2 -> 3 | BG75: Low | BH75: Negligible | BI75: 4 | BJ75: Most destructive European earthquake ever; levelled Messina and Reggio; killed half population Messina; Widespread fires; 5am so many people asleep; 12 m tsunami 10 minutes after quake; Cities reconstructed in grid plan; many poorest survivors emigrated to USA; huge influx of migrants
A76: 75 | B76: 1920 Haiyuan earthquake | C76: China | D76: CHN | E76: Earthquake | F76: Earthquake | G76: Geophysical | H76: 1920 | I76: 8.6 Ms | J76: Extremely catastrophic damage | K76: Lijunbu-Haiyuan-Ganyanchi | L76: Regional | M76: 667070000 | N76: C: Service with Industry (service 50-67% and Industry >25%) | O76: Mixed | P76: 67.3 | Q76: Upper middle | R76: Contracting | S76: -0.2727 | T76: 89.52 | U76: 990 | V76: 0.643 | W76: 38.6 | X76: 39 | Y76: 0 | Z76: 80-100% | AA76: 1490000 | AB76: 273400 | AE76: #VALUE! | AF76: Self-funded | AK76: Totally insufficient | AL76: Miniimal | AM76: High | AN76: Authoritarian | AO76: Central gov. | AP76: Unprepared | AQ76: Inadequate | AR76: Limited scientific basis | AS76: Very poor | AT76: Frequent | AU76: 6-10 Years | AV76: 96 | AW76: Same | AX76: =VLOOKUP(AW76,Metric_Codes!$C$91:$D$95,2,FALSE) -> 3 | AY76: Low | AZ76: 6-10 Years | BA76: 96 | BB76: Same | BC76: =VLOOKUP(BB76,Metric_Codes!$C$91:$D$95,2,FALSE) -> 3 | BD76: Same | BE76: =VLOOKUP(BD76,Metric_Codes!$C$91:$D$95,2,FALSE) -> 3 | BF76: =(BC76+BE76)/2 -> 3 | BG76: Low | BH76: Negligible | BI76: 6 | BJ76: Earthquake indiced loess landslides caused high fatalities and damage; severe winter weather, after shocks and temporary shelter caused many deaths
A77: 76 | B77: 1922 Vallenar earthquake | C77: Chile | D77: CHL | E77: Earthquake & Tsunami | F77: Earthquake & Tsunami | G77: Geophysical | H77: 1922 | I77: 8.7 Mw | J77: Extremely catastrophic damage | K77: Caldera, Atacama region, near border with Argentina | L77: Regional | M77: 7716625 | N77: B: Service-Oriented Economy (67-75% of economy based on services) | O77: Service-Oriented | P77: 58.4 | Q77: High | R77: Growing | S77: 0.0525 | T77: 532.62 | U77: 4270 | V77: 0.71 | W77: 46.6 | X77: 67 | Z77: 40-60% | AA77: 25000 | AB77: 1000 | AE77: #VALUE! | AF77: Self-funded | AK77: Totally insufficient | AL77: Miniimal | AM77: High | AN77: Flawed democracy | AO77: Central gov. | AP77: Unprepared | AQ77: Inadequate | AR77: Limited scientific basis | AS77: Poor | AT77: Frequent | AU77: 3-5 Years | AV77: 48 | AW77: Same | AX77: =VLOOKUP(AW77,Metric_Codes!$C$91:$D$95,2,FALSE) -> 3 | AY77: Low | AZ77: 6-10 Years | BA77: 96 | BB77: Same | BC77: =VLOOKUP(BB77,Metric_Codes!$C$91:$D$95,2,FALSE) -> 3 | BD77: Improved | BE77: =VLOOKUP(BD77,Metric_Codes!$C$91:$D$95,2,FALSE) -> 4 | BF77: =(BC77+BE77)/2 -> 3.5 | BG77: Low | BH77: Negligible | BI77: 4 | BJ77: Tsunami 15 mins - 2 hours after quake;
A78: 77 | B78: 1923 Great Kantō earthquake | C78: Japan | D78: JPN | E78: Earthquake | F78: Earthquake | G78: Geophysical | H78: 1923 | I78: 7.9 Muk | J78: Extremely catastrophic damage | K78: Tokyo and Yokahama | L78: Regional | M78: 92500572 | N78: B: Service-Oriented Economy (67-75% of economy based on services) | O78: Service-Oriented | P78: 72.1 | Q78: High | R78: Growing | S78: 0.1204 | T78: 479 | U78: 19620 | V78: 0.876 | W78: 32.1 | X78: 73 | Z78: 80-100% | AA78: 600000 | AB78: 143000 | AD78: 203733 | AE78: 0.0022025053 | AF78: Self-funded | AH78: 20000 | AK78: Totally insufficient | AL78: Miniimal | AM78: Medium | AN78: Full democracy | AO78: Specialised gov. agency | AP78: Unprepared | AQ78: Adequate | AR78: Established scientific basis | AS78: Very poor | AT78: Frequent | AU78: 6-10 Years | AV78: 96 | AW78: Improved | AX78: =VLOOKUP(AW78,Metric_Codes!$C$91:$D$95,2,FALSE) -> 4 | AY78: Medium | AZ78: 6-10 Years | BA78: 96 | BB78: Improved | BC78: =VLOOKUP(BB78,Metric_Codes!$C$91:$D$95,2,FALSE) -> 4 | BD78: Improved | BE78: =VLOOKUP(BD78,Metric_Codes!$C$91:$D$95,2,FALSE) -> 4 | BF78: =(BC78+BE78)/2 -> 4 | BG78: Medium | BH78: Negligible | BI78: 17 | BJ78: Widespread fires in Yokohama; Pogrom of Koreans by vigilantes and of political dissidents by government; Tensions between impetus to rebuild and modernise v return to tradional values and rejection of westernisation; Led indirectly to rise of nationalism, militarism and war
A79: 78 | B79: 1948 Ashgabat earthquake | C79: Turkmenistan | D79: TKM | E79: Earthquake | F79: Earthquake | G79: Geophysical | H79: 1948 | I79: 7.2 Mw | J79: Catastrophic damage | K79: Ashgabat | L79: Local | M79: 1603258 | O79: Mixed | P79: 48.4 | Q79: Upper middle | R79: Growing | U79: 4430 | V79: 0.575 | W79: 40.8 | X79: 41 | Y79: 0 | Z79: 60-80% | AA79: 25000 | AB79: 110000 | AD79: 6000 | AE79: 0.0037423796 | AF79: Self-funded | AK79: Totally insufficient | AL79: Miniimal | AM79: High | AN79: Authoritarian | AO79: Central gov. | AP79: Completely unprepared | AQ79: Inadequate | AR79: Limited scientific basis | AS79: Very poor | AT79: Occasional | AU79: 6-10 Years | AV79: 96 | AW79: Worse | AX79: =VLOOKUP(AW79,Metric_Codes!$C$91:$D$95,2,FALSE) -> 2 | AY79: Low | AZ79: 6-10 Years | BA79: 120 | BB79: Worse | BC79: =VLOOKUP(BB79,Metric_Codes!$C$91:$D$95,2,FALSE) -> 2 | BD79: Improved | BE79: =VLOOKUP(BD79,Metric_Codes!$C$91:$D$95,2,FALSE) -> 4 | BF79: =(BC79+BE79)/2 -> 3 | BG79: Low | BH79: Negligible | BI79: 11 | BJ79: Occurred at night which increased death toll; > 2/3 of inhabitants killed; Darreh Gaz area of neighboring Iran was also damaged; City rebuilt; Districts that spontaneously recovered since 1991 bulldozed by Prresdients intent on gentrifying city
A80: 79 | B80: 1950 Assam–Tibet earthquake | C80: India | D80: IND | E80: Earthquake | F80: Earthquake | G80: Geophysical | H80: 1950 | I80: 8.6 Muk | J80: Extremely catastrophic damage | K80: India NE frontier Assam/Tibet | L80: Regional | M80: 449480608 | N80: C: Service with Industry (service 50-67% and Industry >25%) | O80: Service-Oriented | P80: 55.2 | Q80: Lower middle | R80: Growing | S80: 0.0372 | T80: 81.28 | U80: 1120 | V80: 0.468 | W80: 35.7 | X80: 41 | Y80: <0.3 | Z80: 40-60% | AB80: 1500 | AE80: #VALUE! | AF80: Self-funded | AG80: 597 | AH80: 38 | AK80: Insufficient | AL80: Miniimal | AM80: High | AN80: Full democracy | AO80: Central gov. | AP80: Unprepared | AQ80: Inadequate | AR80: Limited scientific basis | AS80: Poor | AT80: Frequent | AU80: 3-5 Years | AV80: 48 | AW80: Improved | AX80: =VLOOKUP(AW80,Metric_Codes!$C$91:$D$95,2,FALSE) -> 4 | AY80: Low | AZ80: 6-10 Years | BA80: 72 | BB80: Same | BC80: =VLOOKUP(BB80,Metric_Codes!$C$91:$D$95,2,FALSE) -> 3 | BD80: Improved | BE80: =VLOOKUP(BD80,Metric_Codes!$C$91:$D$95,2,FALSE) -> 4 | BF80: =(BC80+BE80)/2 -> 3.5 | BG80: Low | BH80: Negligible | BI80: 5 | BJ80: 3,300 fatalities in Tibet; occasion for increased state presence in developing isolated region of NE frontier to resist Chinese expansion in Tibet
A81: 80 | B81: 1952 Kamchatka earthquakes | C81: Russian Federation | D81: RUS | E81: Earthquake & Tsunami | F81: Earthquake & Tsunami | G81: Geophysical | H81: 1952 | I81: 9.0 Muk | J81: Extremely catastrophic damage | K81: Severo-Kurilsk | L81: Regional | M81: 119897000 | N81: C: Service with Industry (service 50-67% and Industry >25%) | O81: Industry with Service | P81: 58.9 | Q81: Upper middle | R81: Growing | U81: 8000 | V81: 0.738 | W81: 37.7 | X81: 28 | Y81: 0 | Z81: 60-80% | AA81: 1000 | AB81: 2300 | AE81: #VALUE! | AF81: Mostly self-funded | AK81: Insufficient | AL81: Miniimal | AM81: High | AN81: Authoritarian | AO81: Central gov. | AP81: Completely unprepared | AQ81: Inadequate | AR81: Limited scientific basis | AS81: Poor | AT81: Occasional | AW81: Much worse | AX81: =VLOOKUP(AW81,Metric_Codes!$C$91:$D$95,2,FALSE) -> 1 | AY81: Low | BG81: Low | BH81: Negligible | BI81: 9 | BJ81: 40% of population Severo-Kurilsk killed, town relocated
A82: 81 | B82: 1960 Valdivia earthquake | C82: Chile | D82: CHL | E82: Earthquake & Tsunami | F82: Earthquake & Tsunami | G82: Geophysical | H82: 1960 | I82: 9.5 Muk | J82: Extremely catastrophic damage | K82: Lumaco, Temuco, Valdivia | L82: Regional | M82: 7716625 | N82: B: Service-Oriented Economy (67-75% of economy based on services) | O82: Service-Oriented | P82: 58.4 | Q82: High | R82: Growing | S82: 0.0525 | T82: 532.62 | U82: 4270 | V82: 0.71 | W82: 46.6 | X82: 67 | Y82: <0.4% | Z82: 60-80% | AA82: 550000 | AB82: 6000 | AC82: 2000000 | AD82: 2003000 | AE82: 0.25956944 | AF82: Mostly self-funded | AK82: Insufficient | AL82: Miniimal | AM82: High | AN82: Flawed democracy | AO82: Specially-formed agency | AP82: Somewhat prepared | AQ82: Adequate | AR82: Established scientific basis | AS82: Mediocre | AT82: Frequent | AU82: 3-5 Years | AV82: 48 | AW82: Improved | AX82: =VLOOKUP(AW82,Metric_Codes!$C$91:$D$95,2,FALSE) -> 4 | AY82: Medium | AZ82: 6-10 Years | BA82: 72 | BB82: Improved | BC82: =VLOOKUP(BB82,Metric_Codes!$C$91:$D$95,2,FALSE) -> 4 | BD82: Improved | BE82: =VLOOKUP(BD82,Metric_Codes!$C$91:$D$95,2,FALSE) -> 4 | BF82: =(BC82+BE82)/2 -> 4 | BG82: Medium | BH82: Negligible | BI82: 11 | BJ82: Biggest earthquake ever recorded
A83: 82 | B83: 1964 Alaska earthquake | C83: United States | D83: USA | E83: Earthquake & Tsunami | F83: Earthquake & Tsunami | G83: Geophysical | H83: 1964 | I83: 9.2 Muk | J83: Extremely catastrophic damage | K83: Anchorage | L83: Local | M83: 191889000 | N83: A: Service-Dominated Economy (more than 75% of economy based on services) | O83: Service-Oriented | P83: 76.8 | Q83: High | R83: Growing | S83: 0.061 | T83: 3573.94 | U83: 23730 | V83: 0.797 | W83: 41.5 | X83: 71 | Y83: <4% | Z83: 40-60% | AA83: 1020000 | AB83: 131 | AE83: 0 | AF83: Equal | AJ83: >24 Months | AK83: Sufficient | AL83: Moderate | AM83: Medium | AN83: Full democracy | AO83: Specially-formed agency | AP83: Unprepared | AQ83: Adequate | AR83: Established scientific basis | AS83: Good | AT83: Occasional | AU83: 3-5 Years | AV83: 48 | AW83: Improved | AX83: =VLOOKUP(AW83,Metric_Codes!$C$91:$D$95,2,FALSE) -> 4 | AY83: Medium | AZ83: 6-10 Years | BA83: 84 | BB83: Improved | BC83: =VLOOKUP(BB83,Metric_Codes!$C$91:$D$95,2,FALSE) -> 4 | BD83: Improved | BE83: =VLOOKUP(BD83,Metric_Codes!$C$91:$D$95,2,FALSE) -> 4 | BF83: =(BC83+BE83)/2 -> 4 | BG83: Medium | BH83: Moderate | BI83: 8 | BJ83: Tsunami arrived 20 mins after quake; Discovery of oil in Prudoe Bay in 1968 accelerated recovery
A84: 83 | B84: 1970 Ancash earthquake | C84: Peru | D84: PER | E84: Earthquake | F84: Earthquake | G84: Geophysical | H84: 1970 | I84: 7.9 Muk | J84: Catastrophic damage | K84: Widespread; Chimbote; Callejón de Huaylas s | L84: Regional | M84: 13341069 | N84: C: Service with Industry (service 50-67% and Industry >25%) | O84: Service-Oriented | P84: 67.8 | Q84: Upper middle | R84: Growing | S84: 0.0337 | T84: 557.09 | U84: 3220 | V84: 0.606 | W84: 43.3 | X84: 35 | Y84: 0 | Z84: 60-80% | AA84: 530000 | AB84: 66794 | AC84: 1000000 | AD84: 3216240 | AE84: 0.24107813 | AF84: Self-funded | AK84: Insufficient | AL84: Miniimal | AM84: High | AN84: Flawed democracy | AO84: Specially-formed agency | AP84: Completely unprepared | AQ84: Inadequate | AR84: Limited scientific basis | AS84: Poor | AT84: Frequent | AU84: 6-10 Years | AV84: 96 | AW84: Improved | AX84: =VLOOKUP(AW84,Metric_Codes!$C$91:$D$95,2,FALSE) -> 4 | AY84: Medium | AZ84: 11-20 Years | BA84: 180 | BB84: Worse | BC84: =VLOOKUP(BB84,Metric_Codes!$C$91:$D$95,2,FALSE) -> 2 | BD84: Improved | BE84: =VLOOKUP(BD84,Metric_Codes!$C$91:$D$95,2,FALSE) -> 4 | BF84: =(BC84+BE84)/2 -> 3 | BG84: Medium | BH84: Negligible | BI84: 10 | BJ84: The northern wall of Mount Huascarán was destabilized, causing a rock, ice and snow avalanche; world's deadliest avalanche
A85: 84 | B85: 1976 Tangshan earthquake | C85: China | D85: CHN | E85: Earthquake | F85: Earthquake | G85: Geophysical | H85: 1976 | I85: 6.1 Mw | J85: Severe damage | K85: Tangshan | L85: Regional | M85: 930685000 | N85: C: Service with Industry (service 50-67% and Industry >25%) | O85: Mixed | P85: 67.3 | Q85: Upper middle | R85: Contracting | S85: -0.016 | T85: 165.4 | U85: 990 | V85: 0.643 | W85: 38.6 | X85: 39 | Y85: <0.05% | Z85: 80-100% | AA85: 5600000 | AB85: 242419 | AD85: 164000 | AE85: 0.00017621429 | AF85: Mostly self-funded | AJ85: <12 Months | AK85: Insufficient | AL85: Miniimal | AM85: High | AN85: Authoritarian | AO85: Central gov. | AP85: Unprepared | AQ85: Inadequate | AR85: Established scientific basis | AS85: Very poor | AT85: Frequent | AU85: 6-10 Years | AV85: 96 | AW85: Improved | AX85: =VLOOKUP(AW85,Metric_Codes!$C$91:$D$95,2,FALSE) -> 4 | AY85: Low | AZ85: 6-10 Years | BA85: 96 | BB85: Same | BC85: =VLOOKUP(BB85,Metric_Codes!$C$91:$D$95,2,FALSE) -> 3 | BD85: Improved | BE85: =VLOOKUP(BD85,Metric_Codes!$C$91:$D$95,2,FALSE) -> 4 | BF85: =(BC85+BE85)/2 -> 3.5 | BG85: Low | BH85: Negligible | BI85: 2 | BJ85: One of five all time deadliest earthquakes
A86: 85 | B86: 1980 Irpinia earthquake | C86: Italy | D86: ITA | E86: Earthquake | F86: Earthquake | G86: Geophysical | H86: 1980 | I86: 6.9 Mw | J86: Severe damage | K86: Village Conza. Province Avellino | L86: Regional | M86: 56433883 | N86: A: Service-Dominated Economy (more than 75% of economy based on services) | O86: Industry-Oriented | P86: 62.2 | Q86: High | R86: Growing | S86: 0.034 | T86: 8429 | U86: 18330 | V86: 0.771 | W86: 35.4 | X86: 52 | Y86: 0.01038807 | Z86: 60-80% | AA86: 20000000 | AB86: 4689 | AC86: 300000 | AD86: 407700 | AE86: 0.0072243833 | AF86: Equal | AG86: 70000 | AH86: 102000 | AJ86: >24 Months | AK86: Insufficient | AL86: Moderate | AM86: Medium | AN86: Flawed democracy | AO86: Central gov. | AP86: Somewhat prepared | AQ86: Adequate | AR86: Established scientific basis | AS86: Very poor | AT86: Frequent | AW86: Worse | AX86: =VLOOKUP(AW86,Metric_Codes!$C$91:$D$95,2,FALSE) -> 2 | AY86: Medium | AZ86: 21-30 years | BA86: 300 | BB86: Same | BC86: =VLOOKUP(BB86,Metric_Codes!$C$91:$D$95,2,FALSE) -> 3 | BD86: Improved | BE86: =VLOOKUP(BD86,Metric_Codes!$C$91:$D$95,2,FALSE) -> 4 | BF86: =(BC86+BE86)/2 -> 3.5 | BG86: Medium | BH86: Small | BI86: 12 | BJ86: During Sunday evening mass and churches collapsed; Over 500 towns damaged; Only a quarter of aid spent on recontruction or victims, the rest went in bribes to politicians or to Camorra; Organised crime took over construction industry; Extensive scaffolding in Spanish quarter Naples
A87: 86 | B87: 1988 Armenian earthquake | C87: Armenia | D87: ARM | E87: Earthquake | F87: Earthquake | G87: Geophysical | H87: 1988 | I87: 6.7 Mw | J87: Severe damage | K87: Spitak, Leninakan N Armenian | L87: Regional | M87: 3504651 | O87: Industry-Oriented | P87: 67.7 | Q87: Upper middle | R87: Contracting | S87: -0.117 | T87: 637.9 | U87: 2330 | V87: 0.68 | W87: 33.6 | X87: 35 | Y87: 0 | Z87: 60-80% | AA87: 14000000 | AB87: 25000 | AD87: 1642000 | AE87: 0.46852026 | AF87: Self-funded | AG87: 1600000 | AH87: 511000 | AK87: Insufficient | AL87: Miniimal | AM87: High | AN87: Hybrid regime | AO87: Central gov. | AP87: Unprepared | AQ87: Adequate | AR87: Established scientific basis | AS87: Mediocre | AT87: Frequent | AW87: Worse | AX87: =VLOOKUP(AW87,Metric_Codes!$C$91:$D$95,2,FALSE) -> 2 | AY87: Medium | AZ87: 11-20 Years | BA87: 180 | BB87: Worse | BC87: =VLOOKUP(BB87,Metric_Codes!$C$91:$D$95,2,FALSE) -> 2 | BD87: Improved | BE87: =VLOOKUP(BD87,Metric_Codes!$C$91:$D$95,2,FALSE) -> 4 | BF87: =(BC87+BE87)/2 -> 3 | BG87: Medium | BH87: Negligible | BI87: 12 | BJ87: Damage from poorly designed and constructed Soviet era buildings; Recovery complicated by 1988-1994: Nagorno-Karabakh War and collaspse of Soviet Union; Less than fifth of USD 8 billion pledged Soviet aid realised; All 300 industrial facilities damaged, no major industry recovered; Failed attempt to relocate city of Spitak; Reconstruction boosted in 1994 with World Bank loan and community participation
A88: 87 | B88: 1990 Manjil–Rudbar earthquake | C88: Iran, Islamic Rep. | D88: IRN | E88: Earthquake | F88: Earthquake | G88: Geophysical | H88: 1990 | I88: 7.4 Mw | J88: Catastrophic damage | K88: Manjil Rudbar | L88: Regional | M88: 56226185 | N88: F: Industry with Service (Industry and Service both 33-50%) | O88: Mixed | P88: 51.1 | Q88: Upper middle | R88: Growing | S88: 0.138 | T88: 2219.8 | U88: 7390 | V88: 0.707 | W88: 40 | X88: 28 | Y88: 0.002463772 | Z88: 80-100% | AA88: 8000000 | AB88: 40000 | AC88: 106310 | AD88: 710000 | AE88: 0.012627568 | AF88: Self-funded | AK88: Insufficient | AL88: Miniimal | AM88: High | AN88: Authoritarian | AO88: Central gov. | AP88: Unprepared | AQ88: Inadequate | AR88: Limited scientific basis | AS88: Poor | AT88: Frequent | AU88: 6-10 Years | AV88: 96 | AW88: Worse | AX88: =VLOOKUP(AW88,Metric_Codes!$C$91:$D$95,2,FALSE) -> 2 | AY88: High | AZ88: 11-20 Years | BA88: 180 | BB88: Same | BC88: =VLOOKUP(BB88,Metric_Codes!$C$91:$D$95,2,FALSE) -> 3 | BD88: Same | BE88: =VLOOKUP(BD88,Metric_Codes!$C$91:$D$95,2,FALSE) -> 3 | BF88: =(BC88+BE88)/2 -> 3 | BG88: High | BH88: Negligible | BI88: 25 | BJ88: On main road north from Tehran to holiday resorts on Caspian; Industry declined, now caters to passing tourist trade; olive sellers
A89: 88 | B89: 1999 Jiji earthquake | C89: Taiwan, China | D89: TWN | E89: Earthquake | F89: Earthquake | G89: Geophysical | H89: 1999 | I89: 7.6 Mw | J89: Catastrophic damage | K89: Nantou County and Taichung County; Puli town | L89: Regional | M89: 22092000 | N89: Sectoral GDP missing/incomplete | O89: Service-Oriented | P89: 77.3 | Q89: High | R89: Growing | S89: 0.067 | T89: 13768 | U89: 13947 | W89: 46.5 | X89: 63 | Y89: 0.0195975 | Z89: 60-80% | AA89: 14100000 | AB89: 2264 | AC89: 100000 | AD89: 108664 | AE89: 0.0049187036 | AF89: Self-funded | AG89: 1100000 | AH89: 64000 | AJ89: <12 Months | AK89: Sufficient | AL89: Miniimal | AM89: High | AN89: Flawed democracy | AO89: Central gov. | AP89: Unprepared | AQ89: Inadequate | AR89: Established scientific basis | AS89: Poor | AT89: Occasional | AU89: 6-11 Months | AV89: 9 | AW89: Improved | AX89: =VLOOKUP(AW89,Metric_Codes!$C$91:$D$95,2,FALSE) -> 4 | AY89: Medium | AZ89: 3-5 Years | BA89: 36 | BB89: Same | BC89: =VLOOKUP(BB89,Metric_Codes!$C$91:$D$95,2,FALSE) -> 3 | BD89: Improved | BE89: =VLOOKUP(BD89,Metric_Codes!$C$91:$D$95,2,FALSE) -> 4 | BF89: =(BC89+BE89)/2 -> 3.5 | BG89: Medium | BH89: Negligible | BI89: 8 | BJ89: Shoddy construction; resourceful speedy reconstruction; major industries escaped damage
A90: 89 | B90: 2003 Boumerdès earthquake | C90: Algeria | D90: DZA | E90: Earthquake & Tsunami | F90: Earthquake & Tsunami | G90: Geophysical | H90: 2003 | I90: 6.8 Mw | J90: Severe damage | K90: Bourmerdés | L90: Regional | M90: 32403514 | N90: F: Industry with Service (Industry and Service both 33-50%) | O90: Mixed | P90: 46.2 | Q90: Upper middle | R90: Growing | S90: 0.072 | T90: 2094.3 | U90: 9270 | V90: 0.598 | W90: 27.6 | X90: 35 | Y90: 0.005739179 | Z90: 60-80% | AA90: 5000000 | AB90: 2275 | AC90: 200000 | AD90: 210261 | AE90: 0.0064888333 | AF90: Self-funded | AG90: 1200000 | AK90: Insufficient | AL90: Miniimal | AM90: High | AN90: Authoritarian | AO90: Central gov. | AP90: Unprepared | AQ90: Inadequate | AR90: Established scientific basis | AS90: Good | AT90: Frequent | AU90: 1-2 Years | AV90: 18 | AW90: Improved | AX90: =VLOOKUP(AW90,Metric_Codes!$C$91:$D$95,2,FALSE) -> 4 | AY90: Low | AZ90: 3-5 Years | BA90: 36 | BB90: Same | BC90: =VLOOKUP(BB90,Metric_Codes!$C$91:$D$95,2,FALSE) -> 3 | BD90: Improved | BE90: =VLOOKUP(BD90,Metric_Codes!$C$91:$D$95,2,FALSE) -> 4 | BF90: =(BC90+BE90)/2 -> 3.5 | BG90: Low | BH90: Negligible | BI90: 14 | BJ90: Impetus for improvements in disaster risk management and DRR; systemmatic compensation for damage and loss of life; some evidence of corruption
A91: 90 | B91: 2005 Nias–Simeulue earthquake | C91: Indonesia | D91: IDN | E91: Earthquake & Tsunami | F91: Earthquake & Tsunami | G91: Geophysical | H91: 2005 | I91: 8.6 Mw | J91: Extremely catastrophic damage | K91: Islands of Nias Simulue | L91: Regional | M91: 226712730 | N91: C: Service with Industry (service 50-67% and Industry >25%) | O91: Mixed | P91: 65.8 | Q91: Lower middle | R91: Growing | S91: 0.057 | T91: 1260.9 | U91: 5780 | V91: 0.563 | W91: 38.1 | X91: 38 | Y91: 0.005494714 | Z91: 20-40% | AB91: 915 | AC91: 106800 | AD91: 105313 | AE91: 0.00046452178 | AF91: Self-funded | AK91: Insufficient | AL91: Miniimal | AM91: High | AN91: Flawed democracy | AO91: Specialised gov. agency | AP91: Somewhat prepared | AQ91: Adequate | AR91: Established scientific basis | AS91: Mediocre | AT91: Frequent | AU91: 1-2 Years | AV91: 18 | AW91: Improved | AX91: =VLOOKUP(AW91,Metric_Codes!$C$91:$D$95,2,FALSE) -> 4 | AY91: Medium | AZ91: 3-5 Years | BA91: 36 | BB91: Same | BC91: =VLOOKUP(BB91,Metric_Codes!$C$91:$D$95,2,FALSE) -> 3 | BD91: Improved | BE91: =VLOOKUP(BD91,Metric_Codes!$C$91:$D$95,2,FALSE) -> 4 | BF91: =(BC91+BE91)/2 -> 3.5 | BG91: Medium | BH91: Negligible | BI91: 15 | BJ91: Fear of major tsunamiand and evacuation of hundreds of thousands around Indian ocean, but a tsunami did cause damage along 500 km of coast and destroyed homes.
A92: 91 | B92: 2007 Sumatra earthquake | C92: Indonesia | D92: IDN | E92: Earthquake | F92: Earthquake | G92: Geophysical | H92: 2007 | I92: 8.5 Mw | J92: Extremely catastrophic damage | K92: Bengkulu | L92: Regional | M92: 232989141 | N92: C: Service with Industry (service 50-67% and Industry >25%) | O92: Mixed | P92: 65.8 | Q92: Lower middle | R92: Growing | S92: 0.063 | T92: 1855.1 | U92: 6730 | V92: 0.563 | W92: 38.1 | X92: 38 | Y92: 0.004484105 | Z92: 20-40% | AA92: 500000 | AB92: 25 | AC92: 36800 | AD92: 459567 | AE92: 0.0019724825 | AF92: Self-funded | AH92: 3600 | AK92: Insufficient | AL92: Miniimal | AM92: High | AN92: Flawed democracy | AO92: Specialised gov. agency | AP92: Somewhat prepared | AQ92: Adequate | AR92: Established scientific basis | AS92: Good | AT92: Frequent | AU92: 1-2 Years | AV92: 18 | AW92: Same | AX92: =VLOOKUP(AW92,Metric_Codes!$C$91:$D$95,2,FALSE) -> 3 | AY92: Low | AZ92: 1-2 Years | BA92: 18 | BB92: Same | BC92: =VLOOKUP(BB92,Metric_Codes!$C$91:$D$95,2,FALSE) -> 3 | BD92: Same | BE92: =VLOOKUP(BD92,Metric_Codes!$C$91:$D$95,2,FALSE) -> 3 | BF92: =(BC92+BE92)/2 -> 3 | BG92: Low | BH92: Negligible | BI92: 8 | BJ92: Most people evacuated in good time before moderate tsunami
A93: 92 | B93: 1933 Sanriku earthquake | C93: Japan | D93: JPN | E93: Earthquake & Tsunami | F93: Earthquake & Tsunami | G93: Geophysical | H93: 1933 | I93: 8.3 Mw | J93: Extremely catastrophic damage | K93: Tarö Iwate (now Miyako City) | L93: Regional | M93: 92500572 | N93: B: Service-Oriented Economy (67-75% of economy based on services) | O93: Service-Oriented | P93: 72.1 | Q93: High | R93: Growing | S93: 0.1204 | T93: 479 | U93: 19620 | V93: 0.876 | W93: 32.1 | X93: 73 | Y93: - | Z93: 40-60% | AA93: 25000 | AB93: 6064 | AE93: 0 | AF93: Mostly self-funded | AK93: Insufficient | AL93: Miniimal | AM93: High | AN93: Full democracy | AO93: Central gov. | AP93: Somewhat prepared | AQ93: Adequate | AR93: Established scientific basis | AS93: Good | AT93: Frequent | AU93: 3-5 Years | AV93: 48 | AW93: Same | AX93: =VLOOKUP(AW93,Metric_Codes!$C$91:$D$95,2,FALSE) -> 3 | AY93: Medium | AZ93: 3-5 Years | BA93: 48 | BB93: Same | BC93: =VLOOKUP(BB93,Metric_Codes!$C$91:$D$95,2,FALSE) -> 3 | BD93: Improved | BE93: =VLOOKUP(BD93,Metric_Codes!$C$91:$D$95,2,FALSE) -> 4 | BF93: =(BC93+BE93)/2 -> 3.5 | BG93: Medium | BH93: Negligible | BI93: 16 | BJ93: Large tsunami caused extensive damage; some relocation and new sea defences - dykes and walls
A94: 93 | B94: 1956 Amorgos earthquake | C94: Greece | D94: GRC | E94: Earthquake & Tsunami | F94: Earthquake & Tsunami | G94: Geophysical | H94: 1956 | I94: 7.8 Mw | J94: Catastrophic damage | K94: Eastern Aegean, Amorgos, Santorini | L94: Regional | M94: 8331725 | N94: A: Service-Dominated Economy (more than 75% of economy based on services) | O94: Service-Dominated | P94: 57.7 | Q94: High | R94: Growing | S94: 0.1115 | T94: 533.69 | U94: 13590 | V94: 0.753 | W94: 36 | X94: 45 | Y94: <0.5% | Z94: 20-40% | AB94: 53 | AD94: 100 | AE94: 1.2002316e-05 | AF94: Mostly self-funded | AK94: Insufficient | AL94: Miniimal | AM94: High | AN94: Flawed democracy | AO94: Central gov. | AP94: Completely unprepared | AQ94: Adequate | AR94: Limited scientific basis | AS94: Mediocre | AT94: Frequent | AU94: 3-5 Years | AV94: 48 | AW94: Same | AX94: =VLOOKUP(AW94,Metric_Codes!$C$91:$D$95,2,FALSE) -> 3 | AY94: Low | AZ94: 3-5 Years | BA94: 48 | BB94: Same | BC94: =VLOOKUP(BB94,Metric_Codes!$C$91:$D$95,2,FALSE) -> 3 | BD94: Same | BE94: =VLOOKUP(BD94,Metric_Codes!$C$91:$D$95,2,FALSE) -> 3 | BF94: =(BC94+BE94)/2 -> 3 | BG94: Low | BH94: Negligible | BI94: 7 | BJ94: Underwater landslides caused tsunami
A95: 94 | B95: 1976 Moro Gulf earthquake | C95: Philippines | D95: PHL | E95: Earthquake & Tsunami | F95: Earthquake & Tsunami | G95: Geophysical | H95: 1976 | I95: 8.0 Mw | J95: Extremely catastrophic damage | K95: Pagadian City | L95: Regional | M95: 42461193 | N95: C: Service with Industry (service 50-67% and Industry >25%) | O95: Service-Oriented | P95: 63.8 | Q95: Lower middle | R95: Growing | S95: 0.088 | T95: 402.7 | U95: 2550 | V95: 0.574 | W95: 40.1 | X95: 36 | Y95: <1% | Z95: 40-60% | AA95: 134000 | AB95: 6000 | AC95: 93500 | AD95: 181348 | AE95: 0.0042709116 | AF95: Self-funded | AK95: Insufficient | AL95: Miniimal | AM95: High | AN95: Flawed democracy | AO95: Central gov. | AP95: Somewhat prepared | AQ95: Inadequate | AR95: Limited scientific basis | AS95: Poor | AT95: Occasional | AU95: 1-2 Years | AV95: 18 | AW95: Same | AX95: =VLOOKUP(AW95,Metric_Codes!$C$91:$D$95,2,FALSE) -> 3 | AY95: Low | AZ95: 3-5 Years | BA95: 36 | BB95: Same | BC95: =VLOOKUP(BB95,Metric_Codes!$C$91:$D$95,2,FALSE) -> 3 | BD95: Same | BE95: =VLOOKUP(BD95,Metric_Codes!$C$91:$D$95,2,FALSE) -> 3 | BF95: =(BC95+BE95)/2 -> 3 | BG95: Low | BH95: Negligible | BI95: 16 | BJ95: Occured at midnight; tsunami 3-5 minutes after quake; high death toll from lack of awareness; still no hazard maps 35 years later
A96: 95 | B96: 1979 Tumaco earthquake | C96: Colombia | D96: COL | E96: Earthquake & Tsunami | F96: Earthquake & Tsunami | G96: Geophysical | H96: 1979 | I96: 8.2 Mw- 6m | J96: Extremely catastrophic damage | K96: Tumaco and fishing village Charco | L96: Regional | M96: 27113512 | N96: C: Service with Industry (service 50-67% and Industry >25%) | O96: Mixed | P96: 55.4 | Q96: Upper middle | R96: Contracting | S96: -0.052 | T96: 1030.5 | U96: 4590 | V96: 0.571 | W96: 49.7 | X96: 36 | Y96: ~0.9% | Z96: 20-40% | AA96: 8000 | AB96: 579 | AD96: 11042 | AE96: 0.00040725082 | AF96: Self-funded | AK96: Insufficient | AL96: Miniimal | AM96: High | AN96: Flawed democracy | AO96: Central gov. | AP96: Unprepared | AQ96: Adequate | AR96: Established scientific basis | AS96: Mediocre | AT96: Frequent | AU96: 3-5 Years | AV96: 48 | AW96: Same | AX96: =VLOOKUP(AW96,Metric_Codes!$C$91:$D$95,2,FALSE) -> 3 | AY96: Low | AZ96: 6-10 Years | BA96: 96 | BB96: Same | BC96: =VLOOKUP(BB96,Metric_Codes!$C$91:$D$95,2,FALSE) -> 3 | BD96: Improved | BE96: =VLOOKUP(BD96,Metric_Codes!$C$91:$D$95,2,FALSE) -> 4 | BF96: =(BC96+BE96)/2 -> 3.5 | BG96: Low | BH96: Negligible | BI96: 6 | BJ96: Tsunami minutes after quake; Damage from this and 1983 Popayán eathquake led to earthquake code
A97: 96 | B97: 1992 Nicaragua earthquake | C97: Nicaragua | D97: NIC | E97: Earthquake & Tsunami | F97: Earthquake & Tsunami | G97: Geophysical | H97: 1992 | I97: 7.7 Mw | J97: Catastrophic damage | K97: West coast; Masachapa | L97: Regional | M97: 4331277 | O97: Service-Oriented | P97: 57.7 | Q97: Lower middle | R97: Stable | S97: 0.004 | T97: 413.9 | U97: 1420 | V97: 0.507 | W97: 46.2 | X97: 25 | Y97: 0 | Z97: 20-40% | AA97: 25000 | AB97: 179 | AC97: 13000 | AD97: 40500 | AE97: 0.0030014243 | AF97: Self-funded | AK97: Insufficient | AL97: Miniimal | AM97: High | AN97: Authoritarian | AO97: Central gov. | AP97: Unprepared | AQ97: Inadequate | AR97: Limited scientific basis | AS97: Mediocre | AT97: Occasional | AU97: 3-5 Years | AV97: 48 | AW97: Same | AX97: =VLOOKUP(AW97,Metric_Codes!$C$91:$D$95,2,FALSE) -> 3 | AY97: Low | AZ97: 6-10 Years | BA97: 96 | BB97: Same | BC97: =VLOOKUP(BB97,Metric_Codes!$C$91:$D$95,2,FALSE) -> 3 | BD97: Same | BE97: =VLOOKUP(BD97,Metric_Codes!$C$91:$D$95,2,FALSE) -> 3 | BF97: =(BC97+BE97)/2 -> 3 | BG97: Low | BH97: Negligible | BI97: 8 | BJ97: Tsunami caused most damage; 'tsunami earthquake' bigger than expected given size of earthquake and no warning; arrived 20 minutes after quake; field survey by japan team from Tohoku led by Iamamua
A98: 97 | B98: 1993 Hokkaidō earthquake | C98: Japan | D98: JPN | E98: Earthquake & Tsunami | F98: Earthquake & Tsunami | G98: Geophysical | H98: 1993 | I98: 7.7 Mw | J98: Catastrophic damage | K98: Okushiri Island | L98: Regional | M98: 124536000 | N98: B: Service-Oriented Economy (67-75% of economy based on services) | O98: Service-Oriented | P98: 72.1 | Q98: High | R98: Contracting | S98: -0.005 | T98: 35765.9 | U98: 22020 | V98: 0.876 | W98: 32.1 | X98: 73 | Y98: 0.02565349 | Z98: 40-60% | AA98: 1000000 | AB98: 239 | AC98: 1620 | AD98: 7355 | AE98: 5.9059228e-05 | AF98: Equal | AI98: 16000 | AJ98: <12 Months | AK98: Sufficient | AL98: Moderate | AM98: Medium | AN98: Full democracy | AO98: Central gov. | AP98: Somewhat prepared | AQ98: Adequate | AR98: Established scientific basis | AS98: Mediocre | AT98: Frequent | AU98: 6-10 Years | AV98: 96 | AW98: Worse | AX98: =VLOOKUP(AW98,Metric_Codes!$C$91:$D$95,2,FALSE) -> 2 | AY98: Medium | AZ98: 6-10 Years | BA98: 96 | BB98: Worse | BC98: =VLOOKUP(BB98,Metric_Codes!$C$91:$D$95,2,FALSE) -> 2 | BD98: Much improved | BE98: =VLOOKUP(BD98,Metric_Codes!$C$91:$D$95,2,FALSE) -> 5 | BF98: =(BC98+BE98)/2 -> 3.5 | BG98: Medium | BH98: Small | BI98: 4 | BJ98: Okushiri Island rebuilt at great expense with sea walls and evacuation platform; young people left after building boom; fishing industry never recovered; fishing port dwarfed by sea defenses
A99: 98 | B99: 1998 Papua New Guinea earthquake | C99: Papua New Guinea | D99: PNG | E99: Earthquake & Tsunami | F99: Earthquake & Tsunami | G99: Geophysical | H99: 1998 | I99: 7.0 Mw- 15m | J99: Catastrophic damage | K99: Villages Arop and Warapu | L99: Regional | M99: 5291178 | O99: Service-Oriented | P99: 58.4 | Q99: Lower middle | R99: Contracting | S99: -0.038 | T99: 716.2 | U99: 2070 | W99: 41.9 | X99: 28 | Y99: <0.3 | Z99: 40-60% | AA99: 50000 | AB99: 2182 | AC99: 10000 | AD99: 9867 | AE99: 0.0018648021 | AF99: Self-funded | AK99: Insufficient | AL99: Miniimal | AM99: High | AN99: Flawed democracy | AO99: Central gov. | AP99: Unprepared | AQ99: Inadequate | AR99: Limited scientific basis | AS99: Very poor | AT99: Infrequent | AU99: 1-2 Years | AV99: 18 | AW99: Same | AX99: =VLOOKUP(AW99,Metric_Codes!$C$91:$D$95,2,FALSE) -> 3 | AY99: Low | AZ99: 3-5 Years | BA99: 36 | BB99: Same | BC99: =VLOOKUP(BB99,Metric_Codes!$C$91:$D$95,2,FALSE) -> 3 | BD99: Improved | BE99: =VLOOKUP(BD99,Metric_Codes!$C$91:$D$95,2,FALSE) -> 4 | BF99: =(BC99+BE99)/2 -> 3.5 | BG99: Low | BH99: Negligible | BI99: 8 | BJ99: Tsunami caught people unprepared and unaware of danger, hence high death toll; possible escape of natural undersea gas deposit; impact on copra production
A100: 99 | B100: 2001 Southern Peru earthquake | C100: Peru | D100: PER | E100: Earthquake & Tsunami | F100: Earthquake & Tsunami | G100: Geophysical | H100: 2001 | I100: 8.4 Mw- 7 m | J100: Extremely catastrophic damage | K100: Arequipa | L100: Regional | M100: 26261363 | N100: C: Service with Industry (service 50-67% and Industry >25%) | O100: Service-Oriented | P100: 67.8 | Q100: Upper middle | R100: Stable | S100: 0.006 | T100: 1981.2 | U100: 5200 | V100: 0.606 | W100: 43.3 | X100: 35 | Y100: 0.006875957 | Z100: 20-40% | AA100: 300000 | AB100: 145 | AC100: 124865 | AD100: 349978 | AE100: 0.013326726 | AF100: Self-funded | AH100: 8131 | AK100: Insufficient | AL100: Miniimal | AM100: High | AN100: Flawed democracy | AO100: Central gov. | AP100: Unprepared | AQ100: Inadequate | AR100: Established scientific basis | AS100: Poor | AT100: Frequent | AU100: 1-2 Years | AV100: 18 | AW100: Same | AX100: =VLOOKUP(AW100,Metric_Codes!$C$91:$D$95,2,FALSE) -> 3 | AY100: Low | AZ100: 3-5 Years | BA100: 36 | BB100: Same | BC100: =VLOOKUP(BB100,Metric_Codes!$C$91:$D$95,2,FALSE) -> 3 | BD100: Improved | BE100: =VLOOKUP(BD100,Metric_Codes!$C$91:$D$95,2,FALSE) -> 4 | BF100: =(BC100+BE100)/2 -> 3.5 | BG100: Low | BH100: Negligible | BI100: 8 | BJ100: Historic structures sustained most damage, earthquake resistant structures performed well; number of coastal towns destroyed by tsunami where deathtoll would have been much greater if occurred in summer holiday; salination of agricultural areas
...

Sheet Metric_Definitions
A1: Metadata for metrics in the database
A2: Category | B2: Metric | C2: Description | D2: Value Year (where applicable) | E2: Value Scale | F2: Units | G2: Source (where common)
A3: Disaster Profile | B3: Disaster Name | C3: Disaster name as titled on Wikipedia | D3: - | E3: - | F3: - | G3: Wikipedia
B4: Country | C4: Disaster country as defined by the World Bank classification; where event spans multiple countries, only the worst-affected country has been chosen | D4: - | E4: - | F4: - | G4: World Bank
B5: ISO | C5: ISO 3166-1 alpha-3 - three letter country codes | D5: - | E5: - | F5: - | G5: ISO 3166 standard
B6: Disaster Type | C6: Disaster type: flood, storm, earthquake | D6: - | E6: - | F6: - | G6: EM-DAT
B7: Disaster Subtype | C7: Disaster sub-type | D7: - | E7: - | F7: - | G7: EM-DAT
B8: Type | C8: Climate (Weather related) or Geophysical | G8: EM-DAT | K8: Climate or Geophysical
B9: Year | C9: Year of event; where events (primarily floods) occur across multiple years, use the start year | D9: - | E9: - | F9: - | G9: EM-DAT | K9: Geophysical
B10: Magnitude | C10: Dependent on event type | D10: - | E10: - | F10: - | G10: EM-DAT
B11: Hazard Magnitude Normalised | F11: 1-4 rating scale
B12: Locus | C12: Most severely impacted administrative area | D12: - | E12: - | F12: - | G12: -
B13: Scale | D13: - | E13: - | F13: 1-3 rating scale
A14: Antecedent conditions | B14: Population | C14: Total national population | D14: Event Year | E14: National | F14: People | G14: World Bank: https://data.worldbank.org/indicator/sp.pop.totl
B15: Economy Type | C15: Orientation of economy based on proportion of GDP produced by services, industrial, and agricultural sectors | D15: 2018 | E15: National | F15: - | G15: Lookup based on country ISO; CCRS classification, based on proportion OEM GDP - manual overwrite where neccessary
B16: Economy 2 | C16: As Economy Type but with specific percentages defined by World Bank World Development Indicators (see worksheet WB–Economy) | D16: 2018 | E16: National | F16: % | G16: https://wdi.worldbank.org/table/4.2
B17: Economic Freedom | C17: The Economist Democracy Index 2018 https://en.wikipedia.org/wiki/Democracy_Index (see worksheet Countries) | D17: 2018 | E17: National | F17: %
B18: Economic Growth cat | C18: Categorization of country based on whether the GDP Growth is Stable, Growing or Contracting | D18: Event Year | E18: National | F18: 3 Categories
B19: Income Group | C19: According to the World Bank Country Classification | D19: Event Year | E19: National | F19: - | G19: World Bank: https://datahelpdesk.worldbank.org/knowledgebase/articles/906519-world-bank-country-and-lending-groups
B20: GDP Growth | C20: Measure of the annual real economic growth rate | D20: Event Year | E20: National | F20: % | G20: World Bank: https://data.worldbank.org/indicator/NY.GDP.MKTP.KD.ZG?locations=BD
B21: GDP per Capita | C21: Measure of the total output of a country that divides GDP by total population | D21: Event Year | E21: National | F21: US$ | G21: World Bank: https://data.worldbank.org/indicator/ny.gdp.pcap.cd
B22: GNI per Capita | C22: The dollar value of a country's final income in a year, divided by its population. It reflects the average income of a country's citizens. | D22: Event Year | E22: National | F22: US$ | G22: World Bank: https://data.worldbank.org/indicator/ny.gnp.pcap.pp.cd
B23: IHDI Value | C23: The IHDI combines a country's average achievements in health, education and income with how those achievements are distributed among country's population by “discounting” each dimension's average value according to its level ofinequality. | D23: 2017 | E23: National | F23: 0-1 index | G23: United Nations: http://hdr.undp.org/en/composite/IHDI
A24: Load | B24: Gini Coefficient | C24: Inequality/ wealth distribution of residents within country | D24: Most Recent | E24: National | F24: 0-100 index | G24: World Bank: https://data.worldbank.org/indicator/SI.POV.GINI
B25: Corrupt. Index | C25: Corruption perceptions index: higher the score the less corruption 100=zero corruption | D25: 2018 | E25: National | F25: 0-100 index | G25: Transparency International: https://www.transparency.org/research/cpi/overview
B26: Non-Life Insurance Penetration | C26: Insurance premiums as a proportion of GDP | D26: Event Year | E26: National | F26: % | G26: Sigma Swiss Re (data aquired by CCRS, visible on sigma explorer http://www.sigma-explorer.com/ but cant be exported)
B27: Damage Severity | C27: Proportional damage/destruction of physical building stock/infrastructure | D27: - | E27: Locus | F27: 1-5 rating scale | G27: -
B28: Economic Loss | C28: A value of all economic losses directly or indirectly related to the disaster | D28: 2018 | E28: National | F28: 000 US$ | G28: EM-DAT
B29: Fatalities | C29: Number of people who lost their life as a result of the event | D29: - | E29: National | F29: People | G29: EM-DAT
A30: Resourcing | B30: Displaced | C30: Number of people whose house is destroyed or heavily damaged and therefore need shelter after the event | D30: - | E30: National | F30: People | G30: EM-DAT
B31: Affected Population | C31: People requiring immediate assistance during an emergency situation. Conveys the extent, impact, or severity of a disaster in non-spatial terms. | D31: - | E31: National | F31: People | G31: EM-DAT
B32: Proportion Population Affected | C32: Ratio of directly affected population to the total population of country | D32: - | E32: National | F32: % of Population | G32: Calculation: Proportion = Affected/Population
B33: Self vs external finance | C33: Was recovery funded by personal/communal capital and informal insurance networks or were those affected reliant on external finance sources? | D33: - | E33: Locus | F33: 1-5 rating scale | G33: -
B34: Government aid | C34: Total value of governmental aid allocated to the disaster response/recovery | D34: Event Year | E34: National | F34: 000 US$ | G34: -
B35: Non-Governmental aid | C35: Total value of international aid allocated to the disaster response/recovery | D35: Event Year | E35: National | F35: 000 US$ | G35: -
B36: Insured loss | C36: Economic damages which are covered by insurance companies | D36: Event Year | E36: National | F36: 000 US$ | G36: EM-DAT
B37: Speed of funding | C37: The time taken to deliver financial aid to those in need | D37: - | E37: Locus | F37: 1-5 rating scale | G37: -
A38: Organisational | B38: Adequacy funding | C38: The extent to which financial aid was sufficiently and equitably delivered to those in need | D38: - | E38: Locus | F38: 1-5 rating scale | G38: -
B39: Role of Insurance | C39: What proportion insurance comprised of total external funding | D39: - | E39: Locus | F39: 1-3 rating scale
B40: Resourcing - Confidence | C40: Confidence of the author's qualitative assessment of resourcing (i.e. evaluation of speed, adequacy & role of insurance) - to be used as confidence interval | D40: - | E40: Locus | F40: 1-4 rating scale
B41: State of Democracy | C41: The index is based on 60 indicators grouped in five different categories, measuring pluralism, civil liberties and political culture. In addition to a numeric score and a ranking, the index categorises each country in one of four regime types: full democracies, flawed democracies, hybrid regimes and authoritarian regimes. | D41: - | E41: National | F41: Categoric | G41: The Economist Democracy Index 2018
A42: Management | B42: Disaster Management Authority | C42: Type of (governmental) authority responsible for managing and coordinating the relief and recovery effort. May be a (non-/)specialised fixed government agency or specially-formed following the event | D42: - | E42: National | F42: A-C category | G42: -
B43: Preparedness | C43: Level of societal disaster preparedness in terms of warnings and communication, mitigation, disaster management, coordination, planning, legislation, resourcing | F43: 1-5 rating scale
B44: Public Participation | C44: Extent to which stakeholders/communities/individuals are involved in decision making | D44: - | E44: Locus | F44: 1-3 rating scale | G44: -
A45: Recovery - Economy | B45: Decision Making | C45: Is urban planning and other resilience-related decision making based on scientific research and understanding of the hazard | D45: - | E45: Locus | F45: 1-3 rating scale | G45: -
B46: Experience | C46: Previous experience of disasters in the affected region | D46: - | E46: Locus | F46: A-D category | G46: -
B47: Quality | C47: Quality of recovery management and decision making | D47: - | E47: Locus | F47: 1-5 rating scale
A48: Recovery - Society | B48: Economy - Speed | C48: Qualitative assessment of the time taken for the economy to return to 90% of the pre-event level, or to a new stable norm; primary proxy is employment and productivity (measured by GDP where possible) of the disaster locus | D48: - | E48: Locus | F48: 1-8 rating scale | G48: -
B49: EconomySpeed - Months | C49: Median value of Economy - Speed category | F49: Month
B50: Economy - Quality | C50: Qualitative assessment of the quality of the economy once it has returned to 90% of the pre-event level, or to a new stable norm; primary proxy is employment and productivity | D50: - | E50: Locus | F50: 1-5 rating scale | G50: -
B51: Economy - Confidence | C51: Confidence of the author's qualitative assessment of recovery of the economy - to be used as confidence interval | D51: - | E51: - | F51: 1-4 rating scale | G51: -
A52: Recovery - Insurance | B52: Society - Speed | C52: Qualitative assessment of the time taken for the society of the disaster locus to return to 90% of the pre-event level, or to a new stable norm; primary proxy is housing | D52: - | E52: Locus | F52: 1-9 rating scale | G52: -
B53: Society - Speed - Months | C53: Median value of Society - Speed category | F53: Months
B54: Society - Amenity | C54: Qualitative assessment of the quality and amenity of society once it has returned to 90% of the pre-event level, or to a new stable norm; primary proxies include population change, cultural change (for example whether households have been separated), and availability and quality of social services and community spaces | D54: - | E54: Locus | F54: 1-5 rating scale | G54: -
A55: Load Index | B55: Society - Safety | C55: Qualitative assessment of the safety of society once it has returned to 90% of the pre-event level, or to a new stable norm; primary proxies include initiatives to improve resilience of the built environment to natural hazards, so that they are more resistant to failure in the future | D55: - | E55: Locus | F55: 1-5 rating scale
B56: Society total | C56: Mean of Society - Amenity + Society - Safety | E56: Locus | F56: 1-5 rating scale
A58: DRM Index | B58: Society - Confidence | C58: Confidence of the author's qualitative assessment of recovery of society - to be used as confidence interval | D58: - | E58: - | F58: 1-4 rating scale | G58: -
A59: Community Involvement Index | B59: Insurance Contribution to Recovery Outcome | C59: Negligible - Critical | D59: - | E59: Locus | F59: 1-5 rating scale
A60: Recovery Index
B62: Economic (Loss/1000000) * Fatalities
B63: (Scientific basis+Preparedness+Experience) * Decision Quality
B64: State of Democracy * Public Participation
B65: (Economy Speed * Social Speed) / (Economy Quality * Safety * Amenity)

Sheet Metric_Codes
G1: DAMAGE CLASSIFICATION
A2: Metric | B2: Code | C2: Classification | D2: Description
A3: =Metric_Definitions!$B$11 -> Hazard Magnitude Normalised | B3: 1 | C3: Minor damage | F3: TROPICAL CYCLONE | G3: Typical hazard effects | H3: 1-min max sustained wind speed km/h | I3: Potential damage scale | J3: code
B4: 2 | C4: Moderate damage | F4: CAT 1 | G4: V. dangerious winds will produce some damage | H4: 119–153 km/h | I4: Minor damage | J4: 1
B5: 3 | C5: Severe damage | F5: CAT 2 | G5: Extremely dangerous winds will cause extensive damage | H5: 154–177 km/h | I5: Moderate damage | J5: 2
B6: 4 | C6: Catastrophic damage | F6: CAT 3 | G6: Dvastating damage will occur | H6: 178–208 km/h | I6: Severe damage | J6: 3
B7: 5 | C7: Extremely catastrophic damage | F7: CAT 4 | G7: Catastrophic damage will occur | H7: 209–251 km/h | I7: Catastrophic damage | J7: 4
A8: =Metric_Definitions!$B$13 -> Scale | B8: 1 | C8: Local | F8: CAT 5 | G8: Extremely catastrophic damage will occur | H8: ≥ 252 km/h | I8: Extremely catastrophic damage | J8: 5
B9: 2 | C9: Regional
B10: 3 | C10: National | F10: EARTHQUAKE | G10: http://www.geo.mtu.edu/UPSeis/magnitude.html
A11: =Metric_Definitions!$B$15 -> Economy Type | B11: A | C11: Service-Dominated Economy | F11: < 5.4 | G11: Minor damage | I11: Minor damage | J11: 1
B12: B | C12: Service-Oriented Economy | F12: 5.5 - 5.9 | G12: Damage to buildings and other structures | I12: Moderate damage | J12: 2
B13: C | C13: Service with Industry | F13: 6.0 - 6.9 | G13: May cause a lot of damage in very populated areas | I13: Severe damage | J13: 3
B14: D | C14: Service with Industrial/Ag Mix | F14: 7.0 - 7.9 | G14: Major earthquake. Serious damage | I14: Catastrophic damage | J14: 4
B15: E | C15: Industrial-Oriented Economy | F15: ≥8 | G15: Great earthquake. Can totally destroy communities near the epicenter | I15: Extremely catastrophic damage | J15: 5
B16: F | C16: Industry with Service
B17: G | C17: Agriculture with Industry & Service | F17: FLOOD | G17: Difficult; based on flood extent, max water level, reported return period; some degree of relativity included
A18: Economy Type 2 | B18: A | C18: Service-Dominated | D18: >75% Services | F18: STAGE | G18: RIVER | H18: FLOOD
B19: B | C19: Service-Oriented | D19: 50-75% Services | F19: Acion stage | G19: Water surface generally near or slightly above top of banks, but no man-made structures flooded | H19: Elevated tides & minor inundation of low-lying beach | I19: Minor damage | J19: 1
B20: C | C20: Industry-Oriented | D20: ≥50% Industry | F20: Minor flood stage | G20: Minor flooding, few buildings expected to be inundated, often raods, parklands, etc. inundated | H20: Overwash on shoreline raods; beach-front intfrastructure impacted | I20: Moderate damage | J20: 2
B21: D | C21: Industry with Services | D21: Industry ≥33%, Services ≥50% | F21: Moderate flood stage | G21: Inundation of buildings; roads closes; evacuation may be necessary | H21: Flooding coastal areas; shoreline roads & beaches inundated; coastal structures damaged/destroyed | I21: Severe damage | J21: 3
B22: E | C22: Agriculture Oriented | D22: ≥50% Agriculture | G22: Significant to catastrophic, life-threatening flooding; extensive, with some low-lying areas completely inundataed; structures completely submerged; large scale evacuations | H22: Water surges over man-made defences; large, destructive waves destroy weak structures & severely damage well-built homes & businesses; if at high time, impacts felt well inland | I22: Catastrophic damage | J22: 4
B23: F | C23: Agriculture and Servcies | D23: Agriculture ≥40%, Services ≥40% | F23: Major flood stage | G23: Extremely catastrophic, siginificant life-threat; total inundation across extensive areas (e.g. whole cities); structures completely submerged and destroyed; large scale evacuations | H23: Water surges over man-made defences; large, destructive waves destroy weak structures & severely damage well-built homes & businesses; if at high time, impacts felt well inland; if low lying, entire cities can be inundated | I23: Extremely catastrophic damage | J23: 5
B24: G | C24: Mixed | D24: All other
A25: =Metric_Definitions!$B$19 -> Income Group | B25: 1 | C25: Low
B26: 2 | C26: Lower middle
B27: 3 | C27: Upper middle
B28: 4 | C28: High
A29: =Metric_Definitions!$B$27 -> Damage Severity | B29: 1 | C29: 0-20% | D29: Minimal
B30: 2 | C30: 20-40% | D30: Moderate
B31: 3 | C31: 40-60% | D31: Severe
B32: 4 | C32: 60-80% | D32: Very severe
B33: 5 | C33: 80-100% | D33: Total destruction
A34: =Metric_Definitions!$B$33 -> Self vs external finance | B34: 1 | C34: Self-funded | D34: Self-funded - No external aid received
B35: 2 | C35: Mostly self-funded | D35: Mostly self-funded - Little external aid received
B36: 3 | C36: Equal | D36: Balanced - Personal capital and external aid were equal in facilitating recovery
B37: 4 | C37: Mostly external | D37: Mostly external - Mostly dependent on external (state, international, insurance) aid
B38: 5 | C38: External | D38: External - Totally dependent on external (state & international) aid
A39: =Metric_Definitions!$B$37 -> Speed of funding | B39: 1 | C39: N/A
B40: 2 | C40: >12 Months
B41: 3 | C41: >24 Months
B42: 4 | C42: <3 Months
B43: 5 | C43: <6 Months
B44: 6 | C44: <12 Months
A45: =Metric_Definitions!$B$38 -> Adequacy funding | B45: 1 | C45: Totally insufficient
B46: 2 | C46: Insufficient
B47: 3 | C47: Sufficient
B48: 4 | C48: More than sufficient
B49: 5 | C49: Surplus
A50: =Metric_Definitions!$B$39 -> Role of Insurance | B50: 1 | C50: Miniimal
B51: 2 | C51: Moderate
B52: 3 | C52: Major
A53: State of Democracy | B53: 1 | C53: Authoritarian
B54: 2 | C54: Flawed democracy
B55: 3 | C55: Hybrid regime
B56: 4 | C56: Full democracy
A57: =Metric_Definitions!$B$42 -> Disaster Management Authority | B57: A | C57: Central gov. | D57: Permanent governmental, non-specialised agency
B58: B | C58: Specialised gov. agency | D58: Permanent governmental, specialised agency (e.g. FEMA)
B59: C | C59: Specially-formed agency | D59: Specialised disaster management/governance agency formed in response to disaster
B60: D | C60: None
A61: =Metric_Definitions!$B$43 -> Preparedness | B61: 1 | C61: Completely unprepared
B62: 2 | C62: Unprepared
B63: 3 | C63: Somewhat prepared
B64: 4 | C64: Well prepared
B65: 5 | C65: Very well prepared
A66: =Metric_Definitions!$B$44 -> Public Participation | B66: 1 | C66: Inadequate | D66: None - No stakeholder/community participation in decision making/ inadequate
B67: 2 | C67: Adequate | D67: Adequate
B68: 3 | C68: Extensive | D68: Full - stakeholders/community consulted and fully involved in recovery decision making
A69: =Metric_Definitions!$B$45 -> Decision Making | B69: 1 | C69: No scientific basis
B70: 2 | C70: Limited scientific basis
B71: 3 | C71: Established scientific basis
A72: =Metric_Definitions!$B$46 -> Experience | B72: 1 | C72: None | D72: In living memory
B73: 2 | C73: Infrequent | D73: Low-mid-magnitude disasters occur infrequently
B74: 3 | C74: Occasional | D74: Low-mid-magnitude disasters occur occasionally
B75: 4 | C75: Frequent | D75: Low-mid-magnitude disasters occur frequently
B76: 5 | C76: Major | D76: High-magnitude disaster in living memory
A77: Quality | B77: 1 | C77: Very poor
B78: 2 | C78: Poor
B79: 3 | C79: Mediocre
B80: 4 | C80: Good
B81: 5 | C81: Very good
A82: Speed of Recovery | B82: 1 | C82: Never
B83: 2 | C83: 21-30 years
B84: 3 | C84: 11-20 Years
B85: 4 | C85: 6-10 Years
B86: 5 | C86: 3-5 Years
B87: 6 | C87: 1-2 Years
B88: 7 | C88: 6-11 Months
B89: 8 | C89: <6 Months
B90: 9 | C90: <1 Month
A91: Quality of recovery | B91: 1 | C91: Much worse | D91: 1
B92: 2 | C92: Worse | D92: 2
B93: 3 | C93: Same | D93: 3
B94: 4 | C94: Improved | D94: 4
B95: 5 | C95: Much improved | D95: 5
A96: Confidence estimate | B96: 1 | C96: Low | D96: Inferences from internet based search of new reports and offical documents
B97: 2 | C97: Medium | D97: Remote survey or highly reliable detailed source material
B98: 3 | C98: High | D98: Site visit to observe and interview; household survey; expert survey
A99: Insurance | B99: 1 | C99: Negligible
B100: 2 | C100: Small
...

Sheet Countries
A1: World Bank list of economies (June 2018) | E1: World Development Indicators http://wdi.worldbank.org/table/4.2 | F1: Economic 2 based on the proportion of Agricultural, Service and Industry GDP | J1: The Economist Democracy Index 2018 https://en.wikipedia.org/wiki/Democracy_Index
A2: Country | B2: Code | C2: Region | D2: Income group | E2: Country | F2: Agricultural | G2: Industrial | H2: Service | I2: Economy 2 | J2: Score | K2: Electoral process and pluralism | L2: Functioning of government | M2: Political participation | N2: Political culture | O2: Civil liberties | P2: Regime type | Q2: Economic Freedom | R2: Index | T2: World Bank | U2: World Development Indicators http://wdi.worldbank.org/table/4.2
A3: Afghanistan | B3: AFG | C3: South Asia | D3: Low | E3: Afghanistan | F3: 0.027 | G3: 0.282 | H3: 0.648 | I3: Service-Oriented | J3: 2.97 | K3: 2.92 | L3: 1.14 | M3: 4.44 | N3: 2.5 | O3: 3.82 | P3: Authoritarian | T3: Economic 2 based on the proportion of Agricultural, Service and Industry GDP
A4: Albania | B4: ALB | C4: Europe & Central Asia | D4: Upper middle | E4: Albania | F4: 0.179 | G4: 0.277 | H4: 0.63 | I4: Mixed | J4: 5.98 | K4: 7 | L4: 4.71 | M4: 5.56 | N4: 5 | O4: 7.65 | P4: Hybrid regime | Q4: Albania | R4: 66.5
A5: Algeria | B5: DZA | C5: Middle East & North Africa | D5: Upper middle | E5: Algeria | F5: 0.066 | G5: 0.207 | H5: 0.568 | I5: Mixed | J5: 3.5 | K5: 2.58 | L5: 2.21 | M5: 3.89 | N5: 5 | O5: 3.82 | P5: Authoritarian | Q5: Algeria | R5: 46.2 | T5: Definition of Economy 2
A6: American Samoa | B6: ASM | C6: East Asia & Pacific | D6: Upper middle | E6: American Samoa | F6: 0.065 | G6: 0.45 | H6: 0.86 | I6: Service-Dominated | P6: Not classified | Q6: Angola | R6: 50.6 | T6: Service-Dominated | U6: >75% Services
A7: Andorra | B7: AND | C7: Europe & Central Asia | D7: High | E7: Andorra | F7: 0.273 | G7: 0.118 | H7: 0.43 | I7: Industry with Service | P7: Not classified | T7: Service-Oriented | U7: 50-75% Services
A8: Angola | B8: AGO | C8: Sub-Saharan Africa | D8: Lower middle | E8: Angola | F8: 0.245 | G8: 0.056 | H8: 0.329 | I8: Agricultural | J8: 3.62 | K8: 1.75 | L8: 2.86 | M8: 5.56 | N8: 5 | O8: 2.94 | P8: Authoritarian | T8: Industry-Oriented | U8: ≥50% Industry
A9: Antigua and Barbuda | B9: ATG | C9: Latin America & Caribbean | D9: High | E9: AntiguaAndBarbuda | F9: 0.036 | G9: 0.253 | H9: 0.612 | I9: Industry with Service | P9: Not classified | T9: Industry with Services | U9: Industry ≥33%, Services ≥50%
A10: Argentina | B10: ARG | C10: Latin America & Caribbean | D10: High | E10: Argentina | F10: 0.345 | G10: 0.178 | H10: 0.536 | I10: Industry with Service | J10: 7.02 | K10: 9.17 | L10: 5.36 | M10: 6.11 | N10: 6.25 | O10: 8.24 | P10: Flawed democracy | Q10: Argentina | R10: 52.2 | T10: Agriculture Oriented | U10: ≥50% Agriculture
A11: Armenia | B11: ARM | C11: Europe & Central Asia | D11: Upper middle | E11: Armenia | F11: 0.003 | G11: 0.074 | H11: 0.397 | I11: Industry-Oriented | J11: 4.79 | K11: 5.67 | L11: 4.64 | M11: 5.56 | N11: 2.5 | O11: 5.59 | P11: Hybrid regime | Q11: Armenia | R11: 67.7 | T11: Agriculture and Servcies | U11: Agriculture ≥40%, Services ≥40%
A12: Aruba | B12: ABW | C12: Latin America & Caribbean | D12: High | E12: Aruba | F12: 0.204 | G12: 0.142 | H12: 0.485 | I12: Industry with Service | P12: Not classified | T12: Mixed | U12: All other
A13: Australia | B13: AUS | C13: East Asia & Pacific | D13: High | E13: Australia | F13: 0.121 | G13: 0.382 | H13: 0.777 | I13: Service-Dominated | J13: 9.09 | K13: 10 | L13: 8.93 | M13: 7.78 | N13: 8.75 | O13: 10 | P13: Full democracy | Q13: Australia | R13: 80.9
A14: Austria | B14: AUT | C14: Europe & Central Asia | D14: High | E14: Austria | F14: 0.24 | G14: 0.195 | H14: 0.55 | I14: Industry with Service | J14: 8.29 | K14: 9.58 | L14: 7.86 | M14: 8.33 | N14: 6.88 | O14: 8.82 | P14: Full democracy | Q14: Austria | R14: 72
A15: Azerbaijan | B15: AZE | C15: Europe & Central Asia | D15: Upper middle | E15: Azerbaijan | F15: 0.602 | G15: 0.074 | H15: 0.387 | I15: Agriculture with Service | J15: 2.65 | K15: 0.5 | L15: 2.14 | M15: 3.33 | N15: 3.75 | O15: 3.53 | P15: Authoritarian | Q15: Azerbaijan | R15: 65.4
A16: Bahamas, The | B16: BHS | C16: Latin America & Caribbean | D16: High | E16: Bahamas, The | F16: 0.015 | G16: 0.098 | H16: 0.409 | I16: Industry-Oriented | P16: Not classified | Q16: The Bahamas | R16: 62.9
A17: Bahrain | B17: BHR | C17: Middle East & North Africa | D17: High | E17: Bahrain | F17: 0.34 | G17: 0.138 | H17: 0.476 | I17: Mixed | J17: 2.71 | K17: 0.83 | L17: 3.21 | M17: 2.78 | N17: 4.38 | O17: 2.35 | P17: Authoritarian | Q17: Bahrain | R17: 66.4
A18: Bangladesh | B18: BGD | C18: South Asia | D18: Lower middle | E18: Bangladesh | F18: 0.167 | G18: 0.265 | H18: 0.625 | I18: Mixed | J18: 5.57 | K18: 7.83 | L18: 5.07 | M18: 5.56 | N18: 4.38 | O18: 5 | P18: Hybrid regime | Q18: Bangladesh | R18: 55.6
A19: Barbados | B19: BRB | C19: Latin America & Caribbean | D19: High | E19: Barbados | F19: 0.088 | G19: 0.376 | H19: 0.772 | I19: Service-Dominated | P19: Not classified | Q19: Barbados | R19: 64.7
A20: Belarus | B20: BLR | C20: Europe & Central Asia | D20: Upper middle | E20: Belarus | F20: 0.03 | G20: 0.1 | H20: 0.419 | I20: Industry with Service | J20: 3.13 | K20: 0.92 | L20: 2.86 | M20: 3.89 | N20: 5.63 | O20: 2.35 | P20: Authoritarian | Q20: Belarus | R20: 57.9
A21: Belgium | B21: BEL | C21: Europe & Central Asia | D21: High | E21: Belgium | F21: 0.028 | G21: 0.292 | H21: 0.666 | I21: Service-Oriented | J21: 7.78 | K21: 9.58 | L21: 8.93 | M21: 5 | N21: 6.88 | O21: 8.53 | P21: Flawed democracy | Q21: Belgium | R21: 67.3
A22: Belize | B22: BLZ | C22: Latin America & Caribbean | D22: Upper middle | E22: Belize | F22: 0.058 | G22: 0.392 | H22: 0.791 | I22: Service-Dominated | P22: Not classified | Q22: Belize | R22: 55.4
A23: Benin | B23: BEN | C23: Sub-Saharan Africa | D23: Low | E23: Benin | F23: 0.007 | G23: 0.155 | H23: 0.504 | I23: Industry with Service | J23: 5.74 | K23: 6.5 | L23: 5.71 | M23: 5 | N23: 5.63 | O23: 5.88 | P23: Hybrid regime | Q23: Benin | R23: 55.3
A24: Bermuda | B24: BMU | C24: North America | D24: High | E24: Bermuda | F24: 0.217 | G24: 0.242 | H24: 0.607 | I24: Industry with Service | P24: Not classified
A25: Bhutan | B25: BTN | C25: South Asia | D25: Lower middle | E25: Bhutan | F25: 0.026 | G25: 0.232 | H25: 0.602 | I25: Service-Oriented | J25: 5.3 | K25: 8.75 | L25: 6.79 | M25: 2.78 | N25: 4.38 | O25: 3.82 | P25: Hybrid regime | Q25: Bhutan | R25: 62.9
A26: Bolivia | B26: BOL | C26: Latin America & Caribbean | D26: Lower middle | E26: Bolivia | F26: 0.103 | G26: 0.216 | H26: 0.576 | I26: Mixed | J26: 5.7 | K26: 7.5 | L26: 4.64 | M26: 5.56 | N26: 3.75 | O26: 7.06 | P26: Hybrid regime | Q26: Bolivia | R26: 42.3
A27: Bosnia and Herzegovina | B27: BIH | C27: Europe & Central Asia | D27: Upper middle | E27: BosniaAnd Herzegovina | F27: 0.011 | G27: 0.3 | H27: 0.68 | I27: Service-Oriented | J27: 4.98 | K27: 6.5 | L27: 2.93 | M27: 5.56 | N27: 3.75 | O27: 6.18 | P27: Hybrid regime | Q27: Bosnia and Herzegovina | R27: 61.9
A28: Botswana | B28: BWA | C28: Sub-Saharan Africa | D28: Upper middle | E28: Botswana | F28: 0.041 | G28: 0.169 | H28: 0.516 | I28: Industry with Service | J28: 7.81 | K28: 9.17 | L28: 7.14 | M28: 6.11 | N28: 7.5 | O28: 9.12 | P28: Flawed democracy | Q28: Botswana | R28: 69.5
A29: Brazil | B29: BRA | C29: Latin America & Caribbean | D29: Upper middle | E29: Brazil | F29: 0.039 | G29: 0.313 | H29: 0.701 | I29: Service-Oriented | J29: 6.97 | K29: 9.58 | L29: 5.36 | M29: 6.67 | N29: 5 | O29: 8.24 | P29: Flawed democracy | Q29: Brazil | R29: 51.9
A30: British Virgin Islands | B30: VGB | C30: Latin America & Caribbean | D30: High | E30: British Virgin Islands | F30: 0.01 | G30: 0.15 | H30: 0.495 | I30: Industry-Oriented | P30: Not classified
A31: Brunei Darussalam | B31: BRN | C31: East Asia & Pacific | D31: High | E31: Brunei | F31: 0.005 | G31: 0.089 | H31: 0.405 | I31: Agriculture with Service | P31: Not classified | Q31: Brunei Darussalam | R31: 65.1
A32: Bulgaria | B32: BGR | C32: Europe & Central Asia | D32: Upper middle | E32: Bulgaria | F32: 0.235 | G32: 0.269 | H32: 0.679 | I32: Service-Oriented | J32: 7.03 | K32: 9.17 | L32: 6.43 | M32: 7.22 | N32: 4.38 | O32: 7.94 | P32: Flawed democracy | Q32: Bulgaria | R32: 69
A33: Burkina Faso | B33: BFA | C33: Sub-Saharan Africa | D33: Low | E33: Burkina Faso | F33: 0.116 | G33: 0.311 | H33: 0.697 | I33: Service-Oriented | J33: 4.75 | K33: 4.42 | L33: 4.29 | M33: 4.44 | N33: 5.63 | O33: 5 | P33: Hybrid regime | Q33: Burkina Faso | R33: 59.4
A34: Burundi | B34: BDI | C34: Sub-Saharan Africa | D34: Low | E34: Burundi | F34: 0.047 | G34: 0.341 | H34: 0.739 | I34: Service-Oriented | J34: 2.33 | K34: 0 | L34: 0.43 | M34: 3.89 | N34: 5 | O34: 2.35 | P34: Authoritarian | Q34: Burundi | R34: 48.9
A35: Cabo Verde | B35: CPV | C35: Sub-Saharan Africa | D35: Lower middle | E35: Cabo Verde | F35: 0.043 | G35: 0.28 | H35: 0.64 | I35: Industry with Service | J35: 7.88 | K35: 9.17 | L35: 7.86 | M35: 6.67 | N35: 6.88 | O35: 8.82 | P35: Flawed democracy | Q35: Cabo Verde | R35: 63.1
A36: Cambodia | B36: KHM | C36: East Asia & Pacific | D36: Lower middle | E36: Cambodia | F36: 0.154 | G36: 0.23 | H36: 0.6 | I36: Service-Oriented | J36: 3.59 | K36: 1.33 | L36: 5 | M36: 2.78 | N36: 5.63 | O36: 3.24 | P36: Authoritarian | Q36: Cambodia | R36: 57.8
A37: Cameroon | B37: CMR | C37: Sub-Saharan Africa | D37: Lower middle | E37: Cameroon | F37: 0.023 | G37: 0.369 | H37: 0.766 | I37: Service-Dominated | J37: 3.28 | K37: 3.17 | L37: 2.86 | M37: 3.33 | N37: 4.38 | O37: 2.65 | P37: Authoritarian | Q37: Cameroon | R37: 52.4
A38: Canada | B38: CAN | C38: North America | D38: High | E38: Canada | F38: 0.004 | G38: 0.333 | H38: 0.737 | I38: Service-Oriented | J38: 9.15 | K38: 9.58 | L38: 9.64 | M38: 7.78 | N38: 8.75 | O38: 10 | P38: Full democracy | Q38: Canada | R38: 77.7
A39: Cayman Islands | B39: CYM | C39: Latin America & Caribbean | D39: High | E39: Cayman Islands | F39: 0.082 | G39: 0.237 | H39: 0.604 | I39: Industry with Service | P39: Not classified
A40: Central African Republic | B40: CAF | C40: Sub-Saharan Africa | D40: Low | E40: CentralAfrican Republic | F40: 0.004 | G40: 0.587 | H40: 0.96 | I40: Service-Dominated | J40: 1.52 | K40: 2.25 | L40: 0 | M40: 1.11 | N40: 1.88 | O40: 2.35 | P40: Authoritarian | Q40: Central African Republic | R40: 49.1
A41: Chad | B41: TCD | C41: Sub-Saharan Africa | D41: Low | E41: Chad | F41: 0.343 | G41: 0.076 | H41: 0.402 | I41: Industry-Oriented | J41: 1.61 | K41: 0 | L41: 0 | M41: 1.67 | N41: 3.75 | O41: 2.65 | P41: Authoritarian | Q41: Chad | R41: 49.9
A42: Channel Islands | B42: CHI | C42: Europe & Central Asia | D42: High | E42: Chile | F42: 0.016 | G42: 0.251 | H42: 0.615 | I42: Service-Oriented | P42: Not classified | Q42: Chile | R42: 75.4
A43: Chile | B43: CHL | C43: Latin America & Caribbean | D43: High | E43: China | F43: 0.199 | G43: 0.203 | H43: 0.565 | I43: Mixed | J43: 7.97 | K43: 9.58 | L43: 8.57 | M43: 4.44 | N43: 8.13 | O43: 9.12 | P43: Flawed democracy | Q43: China | R43: 58.4
A44: China | B44: CHN | C44: East Asia & Pacific | D44: Upper middle | E44: Colombia | F44: 0.018 | G44: 0.275 | H44: 0.632 | I44: Mixed | J44: 3.32 | K44: 0 | L44: 5 | M44: 3.89 | N44: 6.25 | O44: 1.47 | P44: Authoritarian | Q44: Colombia | R44: 67.3
A45: Colombia | B45: COL | C45: Latin America & Caribbean | D45: Upper middle | E45: Comoros | F45: 0.02 | G45: 0.15 | H45: 0.492 | I45: Industry-Oriented | J45: 6.96 | K45: 9.17 | L45: 6.79 | M45: 5 | N45: 5.63 | O45: 8.24 | P45: Flawed democracy | Q45: Comoros | R45: 55.4
A46: Comoros | B46: COM | C46: Sub-Saharan Africa | D46: Low | E46: Congo, Democratic Republic of the | F46: 0.03 | G46: 0.105 | H46: 0.429 | I46: Mixed | J46: 3.71 | K46: 4.33 | L46: 2.21 | M46: 4.44 | N46: 3.75 | O46: 3.82 | P46: Authoritarian
A47: Congo, Dem. Rep. | B47: COD | C47: Sub-Saharan Africa | D47: Low | E47: Congo, Republic of the | F47: 0.288 | G47: 0.218 | H47: 0.578 | I47: Agriculture with Service | J47: 1.49 | K47: 0.5 | L47: 0.71 | M47: 2.22 | N47: 3.13 | O47: 0.88 | P47: Authoritarian | Q47: Democratic Republic of Congo | R47: 50.3
A48: Congo, Rep. | B48: COG | C48: Sub-Saharan Africa | D48: Lower middle | E48: Cook Islands | F48: 0.008 | G48: 0.501 | H48: 0.887 | I48: Service-Dominated | J48: 3.31 | K48: 3.17 | L48: 2.5 | M48: 3.89 | N48: 3.75 | O48: 3.24 | P48: Authoritarian
A49: Costa Rica | B49: CRI | C49: Latin America & Caribbean | D49: Upper middle | E49: Costa Rica | F49: 0.016 | G49: 0.282 | H49: 0.645 | I49: Service-Oriented | J49: 8.07 | K49: 9.58 | L49: 7.5 | M49: 6.67 | N49: 7.5 | O49: 9.12 | P49: Full democracy | Q49: Costa Rica | R49: 65.3
A50: Côte d'Ivoire | B50: CIV | C50: Sub-Saharan Africa | D50: Lower middle | E50: Cote d'Ivoire | F50: 0.261 | G50: 0.228 | H50: 0.599 | I50: Industry with Service | J50: 4.15 | K50: 4.83 | L50: 2.86 | M50: 3.33 | N50: 5.63 | O50: 4.12 | P50: Hybrid regime | Q50: Côte d'Ivoire | R50: 62.4
A51: Croatia | B51: HRV | C51: Europe & Central Asia | D51: High | E51: Croatia | F51: 0.241 | G51: 0.356 | H51: 0.755 | I51: Service-Dominated | J51: 6.57 | K51: 9.17 | L51: 6.07 | M51: 5.56 | N51: 5 | O51: 7.06 | P51: Flawed democracy | Q51: Croatia | R51: 61.4
A52: Cuba | B52: CUB | C52: Latin America & Caribbean | D52: Upper middle | E52: Cuba | F52: 0.201 | G52: 0.266 | H52: 0.623 | I52: Industry with Service | J52: 3 | K52: 1.08 | L52: 3.57 | M52: 3.33 | N52: 4.38 | O52: 2.65 | P52: Authoritarian | Q52: Cuba | R52: 27.8
A53: Curaçao | B53: CUW | C53: Latin America & Caribbean | D53: High | E53: Curacao | F53: 0.142 | G53: 0.288 | H53: 0.659 | I53: Service-Oriented | P53: Not classified
A54: Cyprus | B54: CYP | C54: Europe & Central Asia | D54: High | E54: Cyprus | F54: 0.197 | G54: 0.436 | H54: 0.84 | I54: Service-Dominated | J54: 7.59 | K54: 9.17 | L54: 6.43 | M54: 6.67 | N54: 6.88 | O54: 8.82 | P54: Flawed democracy | Q54: Cyprus | R54: 68.1
A55: Czech Republic | B55: CZE | C55: Europe & Central Asia | D55: High | E55: Czech Republic | F55: 0.007 | G55: 0.202 | H55: 0.564 | I55: Mixed | J55: 7.69 | K55: 9.58 | L55: 6.79 | M55: 6.67 | N55: 6.88 | O55: 8.53 | P55: Flawed democracy | Q55: Czech Republic | R55: 73.7
A56: Denmark | B56: DNK | C56: Europe & Central Asia | D56: High | E56: Denmark | F56: 0.081 | G56: 0.408 | H56: 0.821 | I56: Service-Dominated | J56: 9.22 | K56: 10 | L56: 9.29 | M56: 8.33 | N56: 9.38 | O56: 9.12 | P56: Full democracy | Q56: Denmark | R56: 76.7
A57: Djibouti | B57: DJI | C57: Middle East & North Africa | D57: Lower middle | E57: Djibouti | F57: 0.022 | G57: 0.221 | H57: 0.583 | I57: Industry with Service | J57: 2.87 | K57: 0.42 | L57: 1.79 | M57: 3.89 | N57: 5.63 | O57: 2.65 | P57: Authoritarian | Q57: Djibouti | R57: 47.1
A58: Dominica | B58: DMA | C58: Latin America & Caribbean | D58: Upper middle | E58: Dominica | F58: 0.078 | G58: 0.305 | H58: 0.689 | I58: Service-Oriented | P58: Not classified | Q58: Dominica | R58: 63.6
A59: Dominican Republic | B59: DOM | C59: Latin America & Caribbean | D59: Upper middle | E59: Dominican Republic | F59: 0.159 | G59: 0.101 | H59: 0.42 | I59: Industry with Service | J59: 6.54 | K59: 9.17 | L59: 5.36 | M59: 6.11 | N59: 5 | O59: 7.06 | P59: Flawed democracy | Q59: Dominican Republic | R59: 61
A60: Ecuador | B60: ECU | C60: Latin America & Caribbean | D60: Upper middle | E60: Ecuador | F60: 0.023 | G60: 0.337 | H60: 0.739 | I60: Service-Oriented | J60: 6.27 | K60: 8.75 | L60: 5.36 | M60: 6.11 | N60: 4.38 | O60: 6.76 | P60: Flawed democracy | Q60: Ecuador | R60: 46.9
A61: Egypt, Arab Rep. | B61: EGY | C61: Middle East & North Africa | D61: Lower middle | E61: Egypt | F61: 0.31 | G61: 0.239 | H61: 0.608 | I61: Service-Oriented | J61: 3.36 | K61: 3.58 | L61: 3.21 | M61: 3.33 | N61: 3.75 | O61: 2.94 | P61: Authoritarian | Q61: Egypt | R61: 52.5
A62: El Salvador | B62: SLV | C62: Latin America & Caribbean | D62: Lower middle | E62: El Salvador | F62: 0.416 | G62: 0.195 | H62: 0.556 | I62: Industry with Service | J62: 5.96 | K62: 9.17 | L62: 4.29 | M62: 5.56 | N62: 3.75 | O62: 7.06 | P62: Hybrid regime | Q62: El Salvador | R62: 61.8
A63: Equatorial Guinea | B63: GNQ | C63: Sub-Saharan Africa | D63: Upper middle | E63: Equatorial Guinea | F63: 0.044 | G63: 0.099 | H63: 0.408 | I63: Agriculture with Service | J63: 1.92 | K63: 0 | L63: 0.43 | M63: 3.33 | N63: 4.38 | O63: 1.47 | P63: Authoritarian | Q63: Equatorial Guinea | R63: 41
A64: Eritrea | B64: ERI | C64: Sub-Saharan Africa | D64: Low | E64: Eritrea | F64: 0.418 | G64: 0.181 | H64: 0.54 | I64: Industry with Service | J64: 2.37 | K64: 0 | L64: 2.14 | M64: 1.67 | N64: 6.88 | O64: 1.18 | P64: Authoritarian | Q64: Eritrea | R64: 38.9
A65: Estonia | B65: EST | C65: Europe & Central Asia | D65: High | E65: Estonia | F65: 0.045 | G65: 0.288 | H65: 0.66 | I65: Service-Oriented | J65: 7.97 | K65: 9.58 | L65: 8.21 | M65: 6.67 | N65: 6.88 | O65: 8.53 | P65: Flawed democracy | Q65: Estonia | R65: 76.6
A66: Ethiopia | B66: ETH | C66: Sub-Saharan Africa | D66: Low | E66: Ethiopia | F66: 0.117 | G66: 0.343 | H66: 0.741 | I66: Service-Oriented | J66: 3.35 | K66: 0 | L66: 3.57 | M66: 5.56 | N66: 5 | O66: 2.65 | P66: Authoritarian | Q66: Ethiopia | R66: 53.6
A67: Faroe Islands | B67: FRO | C67: Europe & Central Asia | D67: High | E67: Faroe Islands | F67: 0.02 | G67: 0.02 | H67: 0.299 | I67: Industry with Service | P67: Not classified
A68: Fiji | B68: FJI | C68: East Asia & Pacific | D68: Upper middle | E68: Fiji | F68: 0.169 | G68: 0.243 | H68: 0.608 | I68: Industry with Service | J68: 5.85 | K68: 6.58 | L68: 5.36 | M68: 6.11 | N68: 5.63 | O68: 5.59 | P68: Hybrid regime | Q68: Fiji | R68: 62.2
A69: Finland | B69: FIN | C69: Europe & Central Asia | D69: High | E69: Finland | F69: 0 | G69: 0.063 | H69: 0.344 | I69: Industry-Oriented | J69: 9.14 | K69: 10 | L69: 8.93 | M69: 8.33 | N69: 8.75 | O69: 9.71 | P69: Full democracy | Q69: Finland | R69: 74.9
A70: France | B70: FRA | C70: Europe & Central Asia | D70: High | E70: France | F70: 0.035 | G70: 0.294 | H70: 0.675 | I70: Service-Oriented | J70: 7.8 | K70: 9.58 | L70: 7.5 | M70: 7.78 | N70: 5.63 | O70: 8.53 | P70: Full democracy | Q70: France | R70: 63.8
A71: French Polynesia | B71: PYF | C71: East Asia & Pacific | D71: High | E71: French Polynesia | F71: 0.133 | G71: 0.234 | H71: 0.602 | I71: Industry with Service | P71: Not classified
A72: Gabon | B72: GAB | C72: Sub-Saharan Africa | D72: Upper middle | E72: Gabon | F72: 0.016 | G72: 0.179 | H72: 0.56 | I72: Mixed | J72: 3.61 | K72: 2.58 | L72: 2.21 | M72: 4.44 | N72: 5 | O72: 3.82 | P72: Authoritarian | Q72: Gabon | R72: 56.3
A73: Gambia, The | B73: GMB | C73: Sub-Saharan Africa | D73: Low | E73: Gambia, The | F73: 0.036 | G73: 0.319 | H73: 0.702 | I73: Service-Oriented | J73: 4.31 | K73: 4.48 | L73: 4.29 | M73: 3.33 | N73: 5.63 | O73: 3.82 | P73: Hybrid regime | Q73: The Gambia | R73: 52.4
A74: Georgia | B74: GEO | C74: Europe & Central Asia | D74: Lower middle | E74: Georgia | F74: 0.2 | G74: 0.195 | H74: 0.549 | I74: Industry with Service | J74: 5.5 | K74: 7.83 | L74: 3.57 | M74: 6.11 | N74: 4.38 | O74: 5.59 | P74: Hybrid regime | Q74: Georgia | R74: 75.9
A75: Germany | B75: DEU | C75: Europe & Central Asia | D75: High | E75: Germany | F75: 0.5 | G75: 0.131 | H75: 0.474 | I75: Mixed | J75: 8.68 | K75: 9.58 | L75: 8.57 | M75: 8.33 | N75: 7.5 | O75: 9.41 | P75: Full democracy | Q75: Germany | R75: 73.5
A76: Ghana | B76: GHA | C76: Sub-Saharan Africa | D76: Lower middle | E76: Ghana | F76: 0.278 | G76: 0.293 | H76: 0.67 | I76: Service-Oriented | J76: 6.63 | K76: 8.33 | L76: 5.71 | M76: 6.67 | N76: 6.25 | O76: 6.18 | P76: Flawed democracy | Q76: Ghana | R76: 57.5
A77: Gibraltar | B77: GIB | C77: Europe & Central Asia | D77: High | E77: Gibraltar | F77: 0.075 | G77: 0.353 | H77: 0.752 | I77: Service-Dominated | P77: Not classified
A78: Greece | B78: GRC | C78: Europe & Central Asia | D78: High | E78: Greece | F78: 0.018 | G78: 0.36 | H78: 0.757 | I78: Service-Dominated | J78: 7.29 | K78: 9.58 | L78: 5.36 | M78: 6.11 | N78: 6.88 | O78: 8.53 | P78: Flawed democracy | Q78: Greece | R78: 57.7
A79: Greenland | B79: GRL | C79: Europe & Central Asia | D79: High | E79: Greenland | F79: 0.153 | G79: 0.333 | H79: 0.737 | I79: Service-Oriented | P79: Not classified
A80: Grenada | B80: GRD | C80: Latin America & Caribbean | D80: Upper middle | E80: Grenada | F80: 0.047 | G80: 0.324 | H80: 0.706 | I80: Service-Oriented | P80: Not classified
A81: Guam | B81: GUM | C81: East Asia & Pacific | D81: High | E81: Guatemala | F81: 0.061 | G81: 0.33 | H81: 0.728 | I81: Service-Oriented | P81: Not classified
A82: Guatemala | B82: GTM | C82: Latin America & Caribbean | D82: Upper middle | E82: Guernsey | F82: 0.011 | G82: 0.301 | H82: 0.686 | I82: Service-Oriented | J82: 5.6 | K82: 7.92 | L82: 5.36 | M82: 3.89 | N82: 4.38 | O82: 6.47 | P82: Hybrid regime | Q82: Guatemala | R82: 62.6
A83: Guinea | B83: GIN | C83: Sub-Saharan Africa | D83: Low | E83: Guinea | F83: 0.221 | G83: 0.203 | H83: 0.565 | I83: Mixed | J83: 3.14 | K83: 3.5 | L83: 0.43 | M83: 4.44 | N83: 4.38 | O83: 2.94 | P83: Authoritarian | Q83: Guinea | R83: 55.7
A84: Guinea-Bissau | B84: GNB | C84: Sub-Saharan Africa | D84: Low | E84: Guinea-Bissau | F84: 0.082 | G84: 0.362 | H84: 0.758 | I84: Service-Dominated | J84: 1.98 | K84: 1.67 | L84: 0 | M84: 2.78 | N84: 3.13 | O84: 2.35 | P84: Authoritarian | Q84: Guinea-Bissau | R84: 54
A85: Guyana | B85: GUY | C85: Latin America & Caribbean | D85: Upper middle | E85: Guyana | F85: 0.093 | G85: 0.51 | H85: 0.903 | I85: Service-Dominated | J85: 6.67 | K85: 9.17 | L85: 5.71 | M85: 6.11 | N85: 5 | O85: 7.35 | P85: Flawed democracy | Q85: Guyana | R85: 56.8
A86: Haiti | B86: HTI | C86: Latin America & Caribbean | D86: Low | E86: Haiti | F86: 0.142 | G86: 0.293 | H86: 0.672 | I86: Service-Oriented | J86: 4.91 | K86: 5.58 | L86: 2.93 | M86: 3.89 | N86: 6.25 | O86: 5.88 | P86: Hybrid regime | Q86: Haiti | R86: 52.7
A87: Honduras | B87: HND | C87: Latin America & Caribbean | D87: Lower middle | E87: Honduras | F87: 0.12 | G87: 0.277 | H87: 0.638 | I87: Mixed | J87: 5.63 | K87: 8.5 | L87: 4.64 | M87: 4.44 | N87: 4.38 | O87: 6.18 | P87: Hybrid regime | Q87: Honduras | R87: 60.2
A88: Hong Kong SAR, China | B88: HKG | C88: East Asia & Pacific | D88: High | E88: Hong Kong | F88: 0.024 | G88: 0.173 | H88: 0.517 | I88: Industry with Service | J88: 6.15 | K88: 3.08 | L88: 6.07 | M88: 5.56 | N88: 7.5 | O88: 8.53 | P88: Flawed democracy | Q88: Hong Kong | R88: 90.2
A89: Hungary | B89: HUN | C89: Europe & Central Asia | D89: High | E89: Hungary | F89: 0 | G89: 0.14 | H89: 0.482 | I89: Industry with Service | J89: 6.63 | K89: 8.75 | L89: 6.07 | M89: 5 | N89: 6.25 | O89: 7.06 | P89: Flawed democracy | Q89: Hungary | R89: 65
A90: Iceland | B90: ISL | C90: Europe & Central Asia | D90: High | E90: Iceland | F90: 0.024 | G90: 0.402 | H90: 0.81 | I90: Service-Dominated | J90: 9.58 | K90: 10 | L90: 9.29 | M90: 8.89 | N90: 10 | O90: 9.71 | P90: Full democracy | Q90: Iceland | R90: 77.1
A91: India | B91: IND | C91: South Asia | D91: Lower middle | E91: India | F91: 0.179 | G91: 0.337 | H91: 0.739 | I91: Service-Oriented | J91: 7.23 | K91: 9.17 | L91: 6.79 | M91: 7.22 | N91: 5.63 | O91: 7.35 | P91: Full democracy | Q91: India | R91: 55.2
A92: Indonesia | B92: IDN | C92: East Asia & Pacific | D92: Lower middle | E92: Indonesia | F92: 0.075 | G92: 0.159 | H92: 0.511 | I92: Mixed | J92: 6.39 | K92: 6.92 | L92: 7.14 | M92: 6.67 | N92: 5.63 | O92: 5.59 | P92: Flawed democracy | Q92: Indonesia | R92: 65.8
A93: Iran, Islamic Rep. | B93: IRN | C93: Middle East & North Africa | D93: Upper middle | E93: Iran | F93: 0.068 | G93: 0.155 | H93: 0.495 | I93: Mixed | J93: 2.45 | K93: 0 | L93: 3.21 | M93: 4.44 | N93: 3.13 | O93: 1.47 | P93: Authoritarian | Q93: Iran | R93: 51.1
A94: Iraq | B94: IRQ | C94: Middle East & North Africa | D94: Upper middle | E94: Iraq | F94: 0.274 | G94: 0.124 | H94: 0.442 | I94: Mixed | J94: 4.06 | K94: 4.75 | L94: 0.07 | M94: 6.67 | N94: 5 | O94: 3.82 | P94: Hybrid regime
A95: Ireland | B95: IRL | C95: Europe & Central Asia | D95: High | E95: Ireland | F95: 0.167 | G95: 0.282 | H95: 0.651 | I95: Service-Oriented | J95: 9.15 | K95: 9.58 | L95: 7.86 | M95: 8.33 | N95: 10 | O95: 10 | P95: Full democracy | Q95: Ireland | R95: 80.5
A96: Isle of Man | B96: IMN | C96: Europe & Central Asia | D96: High | E96: Isle of Man | F96: 0.011 | G96: 0.102 | H96: 0.423 | I96: Industry-Oriented | P96: Not classified
A97: Israel | B97: ISR | C97: Middle East & North Africa | D97: High | E97: Israel | F97: 0.101 | G97: 0.262 | H97: 0.617 | I97: Service-Oriented | J97: 7.79 | K97: 9.17 | L97: 7.5 | M97: 8.89 | N97: 7.5 | O97: 5.88 | P97: Flawed democracy | Q97: Israel | R97: 72.8
A98: Italy | B98: ITA | C98: Europe & Central Asia | D98: High | E98: Italy | F98: 0.019 | G98: 0.078 | H98: 0.404 | I98: Industry-Oriented | J98: 7.71 | K98: 9.58 | L98: 6.07 | M98: 7.78 | N98: 6.88 | O98: 8.24 | P98: Flawed democracy | Q98: Italy | R98: 62.2
A99: Jamaica | B99: JAM | C99: Latin America & Caribbean | D99: Upper middle | E99: Jamaica | F99: 0.119 | G99: 0.336 | H99: 0.737 | I99: Service-Oriented | J99: 7.02 | K99: 8.75 | L99: 7.14 | M99: 4.44 | N99: 6.25 | O99: 8.53 | P99: Flawed democracy | Q99: Jamaica | R99: 68.6
A100: Japan | B100: JPN | C100: East Asia & Pacific | D100: High | E100: Japan | F100: 0.234 | G100: 0.286 | H100: 0.658 | I100: Service-Oriented | J100: 7.99 | K100: 8.75 | L100: 8.21 | M100: 6.67 | N100: 7.5 | O100: 8.82 | P100: Full democracy | Q100: Japan | R100: 72.1
...

Sheet Manual - Ai Comparison
A1: CS ID | B1: Disaster Name | C1: Society - Speed | D1: Manual | E1: AI | F1: Society - Confidence | G1: Year | H1: Country | I1: Years to ≥90% Permanent Housing Recovery | J1: DEVIATION | K1: ABS Deviation | L1: Key Reference | M1: COMPARISON Speed of Societal recovery as defined by time in years for ≥90% residents to return to permanent accommodation
A2: 1 | B2: 2004 Bangladesh Floods | C2: 6-11 Months | D2: 1 | E2: 3.5 | F2: Medium | G2: 2004 | H2: Bangladesh | I2: 3–4 years | J2: =SUM(D2-E2) -> -2.5 | K2: =ABS(J2) -> 2.5 | L2: Khan | M2: Manual estimates produced by research team from field study and desk work compared with Ai estimates by ChatGPT based on internet search of over 2000 references
A3: 2 | B3: 2012 Hurricane Sandy | C3: 3-5 Years | D3: 4 | E3: 4.5 | F3: Medium | G3: 2012 | H3: United States | I3: 4–5 years | J3: =SUM(D3-E3) -> -0.5 | K3: =ABS(J3) -> 0.5 | L3: Fussell
A4: 3 | B4: 2005 Hurricane Katrina | C4: 3-5 Years | D4: 4 | E4: 6 | F4: Medium | G4: 2005 | H4: United States | I4: 5–7 years | J4: =SUM(D4-E4) -> -2 | K4: =ABS(J4) -> 2 | L4: Comerio
A5: 4 | B5: 2014 India(-Pakistan) floods | C5: 6-11 Months | D5: 1 | E5: 4.5 | F5: Medium | G5: 2014 | H5: India | I5: 4–5 years | J5: =SUM(D5-E5) -> -3.5 | K5: =ABS(J5) -> 3.5 | L5: UNDP (2015). "India Floods: Recovery and Resilience."
A6: 5 | B6: 2013 Typhoon Haiyan (Yolanda) | C6: 3-5 Years | D6: 4 | E6: 5 | F6: High | G6: 2013 | H6: Philippines | I6: 4–6 years | J6: =SUM(D6-E6) -> -1 | K6: =ABS(J6) -> 1 | L6: Nguyen
A7: 6 | B7: 2017 Typhoon Damrey (Ramil) | C7: <6 Months | D7: 1 | E7: 3.5 | F7: High | G7: 2017 | H7: Vietnam | I7: 3–4 years | J7: =SUM(D7-E7) -> -2.5 | K7: =ABS(J7) -> 2.5 | L7: Asian Development Bank (2018). "Typhoon Damrey Recovery Report."
A8: 7 | B8: 2013 European floods (Germany) | C8: <1 Month | D8: 1 | E8: 2.5 | F8: High | G8: 2013 | H8: Germany | I8: 2–3 years | J8: =SUM(D8-E8) -> -1.5 | K8: =ABS(J8) -> 1.5 | L8: Kreibich
A9: 8 | B9: 2007 UK floods | C9: 1-2 Years | D9: 1.5 | E9: 2 | F9: High | G9: 2007 | H9: United Kingdom | I9: 2–2.5 years | J9: =SUM(D9-E9) -> -0.5 | K9: =ABS(J9) -> 0.5 | L9: Thorne
A10: 9 | B10: 2004 Typhoon Tokage (Siony) | C10: 1-2 Years | D10: 1.5 | E10: 2.5 | F10: Low | G10: 2004 | H10: Japan | I10: 2–3 years | J10: =SUM(D10-E10) -> -1 | K10: =ABS(J10) -> 1 | L10: JMA (2007). "Typhoon Tokage: Lessons in Disaster Recovery."
A11: 10 | B11: 2010 China Floods | C11: 1-2 Years | D11: 1.5 | E11: 3.5 | F11: Low | G11: 2010 | H11: China | I11: 3–4 years | J11: =SUM(D11-E11) -> -2 | K11: =ABS(J11) -> 2 | L11: China Ministry of Water Resources (2013). "2010 China Floods Recovery Report."
A12: 11 | B12: 1998 Hurricane Mitch | C12: 3-5 Years | D12: 4 | E12: 6.5 | F12: Medium | G12: 1998 | H12: Honduras | I12: 6–7 years | J12: =SUM(D12-E12) -> -2.5 | K12: =ABS(J12) -> 2.5 | L12: World Bank (2005). "Hurricane Mitch: Reconstruction Challenges."
A13: 12 | B13: 2004 Hurricane Frances | C13: 1-2 Years | D13: 1.5 | E13: 2.5 | F13: Low | G13: 2004 | H13: Bahamas | I13: 2–3 years | J13: =SUM(D13-E13) -> -1 | K13: =ABS(J13) -> 1 | L13: NOAA (2006). "Hurricane Frances Impact Assessment."
A14: 13 | B14: 2004 Hurricane Ivan | C14: 1-2 Years | D14: 1.5 | E14: 3.5 | F14: Medium | G14: 2004 | H14: Jamaica | I14: 3–4 years | J14: =SUM(D14-E14) -> -2 | K14: =ABS(J14) -> 2 | L14: World Bank (2006). "Hurricane Ivan Recovery Report."
... A51: 50 | B51: 2013 North India Floods | C51: 3-5 Years | D51: 4 | E51: 4.5 | F51: Low | G51: 2013 | H51: India | I51: 4–5 years | J51: =SUM(D51-E51) -> -0.5 | K51: =ABS(J51) -> 0.5 | L51: UNDP (2017). "India Floods: Housing Recovery & Disaster Resilience."
A52: 51 | B52: 2013 Philippines Floods | C52: <1 Month | E52: 4.5 | F52: Medium | G52: 2013 | H52: Philippines | I52: 4–5 years | J52: =SUM(D52-E52) -> -4.5 | K52: =ABS(J52) -> 4.5 | L52: Asian Development Bank (2018). "Philippines Floods: Recovery Efforts."
A53: 52 | B53: 1937 Great Hong Kong typhoon | C53: 1-2 Years | D53: 1.5 | E53: 5.5 | F53: Low | G53: 1937 | H53: China | I53: 5–6 years | J53: =SUM(D53-E53) -> -4 | K53: =ABS(J53) -> 4 | L53: China Meteorological Administration (1940). "Great Hong Kong Typhoon: Impact & Recovery."
A54: 53 | B54: 1943 Chennai (Madras) flood or Rajputana flood (less severe) | C54: 6-11 Months | D54: 1 | E54: 4.5 | F54: Low | G54: 1943 | H54: India | I54: 4–5 years | J54: =SUM(D54-E54) -> -3.5 | K54: =ABS(J54) -> 3.5 | L54: Indian Government Archives (1947). "Chennai Flood Recovery & Housing Reconstruction."
A55: 54 | B55: 1985 Typhoon Cecil (Rubing) | C55: 1-2 Years | D55: 1.5 | E55: 3.5 | F55: Low | G55: 1985 | H55: Vietnam | I55: 3–4 years | J55: =SUM(D55-E55) -> -2 | K55: =ABS(J55) -> 2 | L55: Asian Disaster Preparedness Center (1990). "Typhoon Cecil: Recovery Lessons."
A56: 55 | B56: 1975 Typhoon Nina (Bebeng) | C56: 3-5 Years | D56: 4 | E56: 5.5 | F56: Low | G56: 1975 | H56: China | I56: 5–6 years | J56: =SUM(D56-E56) -> -1.5 | K56: =ABS(J56) -> 1.5 | L56: Chinese Academy of Sciences (1980). "Typhoon Nina: Impact on Housing & Infrastructure."
A57: 56 | B57: 1977 Andhra Pradesh Cyclone (Devi Taluk ) | C57: 1-2 Years | D57: 1.5 | E57: 4.5 | F57: Low | G57: 1977 | H57: India | I57: 4–5 years | J57: =SUM(D57-E57) -> -3 | K57: =ABS(J57) -> 3 | L57: India Meteorological Department (1982). "Andhra Pradesh Cyclone: Recovery & Housing."
A58: 57 | B58: 1989 Hurricane Hugo | C58: 3-5 Years | D58: 4 | E58: 4.5 | F58: Low | G58: 1989 | H58: United States | I58: 4–5 years | J58: =SUM(D58-E58) -> -0.5 | K58: =ABS(J58) -> 0.5 | L58: NOAA (1993). "Hurricane Hugo: Disaster Response & Housing Recovery."
A59: 58 | B59: 1990 Storm Daria (Burns' Day Storm) | C59: 1-2 Years | D59: 1.5 | E59: 3.5 | F59: Low | G59: 1990 | H59: United Kingdom | I59: 3–4 years | J59: =SUM(D59-E59) -> -2 | K59: =ABS(J59) -> 2 | L59: Met Office UK (1994). "Storm Daria: Housing Recovery & Infrastructure."
A60: 59 | B60: 1991 Typhoon Mireille (Rosing) | C60: 1-2 Years | D60: 1.5 | E60: 3.5 | F60: Low | G60: 1991 | H60: Japan | I60: 3–4 years | J60: =SUM(D60-E60) -> -2 | K60: =ABS(J60) -> 2 | L60: JMA (1995). "Typhoon Mireille: Recovery Lessons & Housing Reconstruction."
A61: 60 | B61: 1991 Bangladesh Cyclone | C61: 6-11 Months | D61: 1 | E61: 5.5 | F61: Low | G61: 1991 | H61: Bangladesh | I61: 5–6 years | J61: =SUM(D61-E61) -> -4.5 | K61: =ABS(J61) -> 4.5 | L61: Ahmed
A62: 61 | B62: 1992 Hurricane Andrew | C62: 1-2 Years | D62: 1.5 | E62: 4.5 | F62: Low | G62: 1992 | H62: United States | I62: 4–5 years | J62: =SUM(D62-E62) -> -3 | K62: =ABS(J62) -> 3 | L62: NOAA (1996). "Hurricane Andrew: Recovery and Housing Reconstruction."
A63: 62 | B63: 1993 Tropical Storm Bret | C63: 6-11 Months | D63: 1 | E63: 3.5 | F63: Low | G63: 1993 | H63: Venezuela | I63: 3–4 years | J63: =SUM(D63-E63) -> -2.5 | K63: =ABS(J63) -> 2.5 | L63: UNDP (1997). "Tropical Storm Bret: Disaster Recovery."
A64: 63 | B64: 1999 Cyclones Lothar and Martin | C64: 6-11 Months | D64: 1 | E64: 3.5 | F64: Low | G64: 1999 | H64: France | I64: 3–4 years | J64: =SUM(D64-E64) -> -2.5 | K64: =ABS(J64) -> 2.5 | L64: European Commission (2003). "Cyclones Lothar & Martin: Infrastructure & Housing Recovery."
... A67: 66 | B67: 1999 Cyclone Anatol | C67: 6-11 Months | D67: 1 | E67: 3.5 | F67: Low | G67: 1999 | H67: Denmark | I67: 3–4 years | J67: =SUM(D67-E67) -> -2.5 | K67: =ABS(J67) -> 2.5 | L67: Danish Meteorological Institute (2003). "Cyclone Anatol: Housing & Infrastructure Recovery."
A68: 67 | B68: 2000 Typhoon Prapiroon (Lusing) | D68: 4 | E68: 4.5 | G68: 2000 | H68: Korea | I68: 4–5 years | J68: =SUM(D68-E68) -> -0.5 | K68: =ABS(J68) -> 0.5 | L68: UNDP (2005). "Typhoon Prapiroon: Housing Reconstruction."
A69: 68 | B69: 2004 Hurricane Jeanne | C69: 3-5 Years | D69: 4 | E69: 7 | F69: Low | G69: 2004 | H69: Haiti | I69: 6–8 years | J69: =SUM(D69-E69) -> -3 | K69: =ABS(J69) -> 3 | L69: World Bank (2010). "Hurricane Jeanne: Housing and Infrastructure Recovery."
A70: 69 | B70: 2008 Cyclone Nargis | C70: 3-5 Years | D70: 4 | E70: 6.5 | F70: Low | G70: 2008 | H70: Myanmar | I70: 6–7 years | J70: =SUM(D70-E70) -> -2.5 | K70: =ABS(J70) -> 2.5 | L70: UNDP (2013). "Cyclone Nargis: Recovery and Resilience."
A71: 70 | B71: 2009 Cyclone Klaus | C71: 1-2 Years | D71: 1.5 | E71: 3.5 | F71: Low | G71: 2009 | H71: Spain | I71: 3–4 years | J71: =SUM(D71-E71) -> -2 | K71: =ABS(J71) -> 2 | L71: European Weather Institute (2012). "Cyclone Klaus: Disaster Response & Housing."
A72: 71 | B72: 2009 Typhoon Morakot (Kiko) | C72: 1-2 Years | D72: 1.5 | E72: 4.5 | F72: Low | G72: 2009 | H72: Taiwan | I72: 4–5 years | J72: =SUM(D72-E72) -> -3 | K72: =ABS(J72) -> 3 | L72: Taiwan Meteorological Bureau (2014). "Typhoon Morakot: Housing Recovery."
A73: 72 | B73: 2010 Cyclone Xynthia | C73: 1-2 Years | D73: 1.5 | E73: 2.5 | F73: Low | G73: 2010 | H73: France | I73: 2–3 years | J73: =SUM(D73-E73) -> -1 | K73: =ABS(J73) -> 1 | L73: UNDP (2012). "Cyclone Xynthia: Recovery and Infrastructure."
A74: 73 | B74: 1906 Ecuador–Colombia earthquake | C74: 3-5 Years | D74: 4 | E74: 7 | F74: Low | G74: 1906 | H74: Ecuador | I74: 6–8 years | J74: =SUM(D74-E74) -> -3 | K74: =ABS(J74) -> 3 | L74: USGS (1910). "Ecuador-Colombia Earthquake Impact Study."
A75: 74 | B75: 1908 Messina earthquake | C75: 11-20 Years | D75: 15 | E75: 9 | F75: Low | G75: 1908 | H75: Italy | I75: 8–10 years | J75: =SUM(D75-E75) -> 6 | K75: =ABS(J75) -> 6 | L75: Boschi
A76: 75 | B76: 1920 Haiyuan earthquake | C76: 6-10 Years | D76: 8 | E76: 10 | F76: Low | G76: 1920 | H76: China | I76: 8–10+ years | J76: =SUM(D76-E76) -> -2 | K76: =ABS(J76) -> 2 | L76: Zhang
A77: 76 | B77: 1922 Vallenar earthquake | C77: 6-10 Years | D77: 8 | E77: 5.5 | F77: Low | G77: 1922 | H77: Chile | I77: 5–6 years | J77: =SUM(D77-E77) -> 2.5 | K77: =ABS(J77) -> 2.5 | L77: USGS (1928). "Vallenar Earthquake & Tsunami Recovery."
A78: 77 | B78: 1923 Great Kantō earthquake | C78: 6-10 Years | D78: 8 | E78: 7 | F78: Medium | G78: 1923 | H78: Japan | I78: 6–8 years | J78: =SUM(D78-E78) -> 1 | K78: =ABS(J78) -> 1 | L78: Yoshii
A79: 78 | B79: 1948 Ashgabat earthquake | C79: 6-10 Years | D79: 8 | E79: 6.5 | F79: Low | G79: 1948 | H79: Turkmenistan | I79: 6–7 years | J79: =SUM(D79-E79) -> 1.5 | K79: =ABS(J79) -> 1.5 | L79: UNESCO (1952). "Ashgabat Earthquake Reconstruction."
A80: 79 | B80: 1950 Assam–Tibet earthquake | C80: 6-10 Years | D80: 8 | E80: 5.5 | F80: Low | G80: 1950 | H80: India | I80: 5–6 years | J80: =SUM(D80-E80) -> 2.5 | K80: =ABS(J80) -> 2.5 | L80: GSI (1955). "1950 Assam Earthquake: Impacts and Reconstruction."
... A104: 103 | B104: 1970 Bhola Cyclone | C104: 3-5 Years | D104: 4 | E104: 5.5 | F104: Low | G104: 1970 | H104: Bangladesh | I104: 5–6 years | J104: =SUM(D104-E104) -> -1.5 | K104: =ABS(J104) -> 1.5 | L104: Ahmed
C105: Average | D105: =AVERAGE(D2:D104) -> 4.5147059 | E105: =AVERAGE(E2:E104) -> 5.1650485 | J105: AVERAGE | K105: =AVERAGE(K2:K104) -> 2.6067961
C106: Min | D106: =MIN(D$2:D$104) -> 1 | E106: =MIN(E$2:E$104) -> 2 | J106: AVERAGE HIGH CONFIDENCE | K106: =AVERAGE(K3:K18:J81:J103) -> 0.97524752
C107: Max | D107: =MAX(D$2:D$104) -> 15 | E107: =MAX(E$2:E$104) -> 10 | K107: =AVERAGE(K19:K80) -> 2.7177419
